Workbook
Name BAR_NOM: TABLAS!$B$5:$B$13
Name BAR_DB: TABLAS!$C$5:$C$13
Name BAR_AS: TABLAS!$D$5:$D$13
Name COMB_NOM: TABLAS!$B$17:$B$25
Name COMB_AS: TABLAS!$C$17:$C$25
Name ALIG_H: TABLAS!$B$29:$B$32
Name ALIG_PP: TABLAS!$C$29:$C$32
Name USO_NOM: TABLAS!$G$5:$G$24
Name USO_SC: TABLAS!$H$5:$H$24
Name LNEG: TABLAS!$B$42:$T$52
Name LPCM: TABLAS!$B$56:$T$66
Name LPCV: TABLAS!$B$70:$T$80
Name CASOS: TABLAS!$B$83:$B$91

Sheet INICIO
B2: PLANTILLA EXCEL ESTRUCTURAS ALF
B3: NTE E.060 · Vigas · Columnas · Placas · Losas · Escaleras · Cimentaciones · Muros · v2.1.0
B4: ALF_BIM · www.alfbim.com · Herramienta gratuita
B6: DATOS DEL PROYECTO (aparecen en el encabezado de cada reporte)
B7: Proyecto | D7: VIVIENDA MULTIFAMILIAR DE 4 NIVELES (EJEMPLO)
B8: Propietario | D8: —
B9: Ubicación | D9: Chota, Cajamarca
B10: Calculista | D10: Ing.
B11: CIP
B12: Fecha | D12: 46310
B14: HOJAS DE CÁLCULO
B15: =HYPERLINK("#'PREDIM'!A1","→ PREDIM") | D15: Predimensionamiento: aligerados, losas macizas, vigas, columnas por área tributaria y longitud de placas.
B16: =HYPERLINK("#'VIGA'!A1","→ VIGA") | D16: Viga sísmica: 6 secciones, doble armadura, reglas del cap. 21, cortante por capacidad, confinamiento y anclajes.
B17: =HYPERLINK("#'COLUMNA'!A1","→ COLUMNA") | D17: Columna: diagramas de interacción X e Y, 9 combinaciones, biaxial (Bresler), esbeltez con amplificación de momentos, columna fuerte–viga débil, cortante por capacidad, Ash y confinamiento.
B18: =HYPERLINK("#'PLACA'!A1","→ PLACA") | D18: Muro estructural: flexocompresión, cortante amplificado Mn/Mua, cuantías ρh y ρv, elementos de borde (21.9).
B19: =HYPERLINK("#'LOSA_MACIZA'!A1","→ LOSA_MACIZA") | D19: Losa maciza en dos direcciones: método de coeficientes E.060 13.7 (casos 1 a 9), acero, cortante y espesor.
B20: =HYPERLINK("#'ALIGERADO'!A1","→ ALIGERADO") | D20: Losa aligerada en una dirección (1 a 5 tramos): coeficientes 8.3.3, acero mínimo por 1.2·Mcr, bastones, cortante y deflexiones.
B21: =HYPERLINK("#'ESCALERA'!A1","→ ESCALERA") | D21: Escalera de un tramo con descanso: geometría A.010, cargas, momento máximo, acero y cortante.
B22: =HYPERLINK("#'ZAPATA'!A1","→ ZAPATA") | D22: Zapata aislada con carga axial y momentos biaxiales: presiones, punzonamiento con transferencia de momento, cortante, flexión, anclaje y aplastamiento.
B23: =HYPERLINK("#'ZAP_CONECTADA'!A1","→ ZAP_CONECTADA") | D23: Zapata exterior de lindero con viga de conexión: excentricidad, reacción, viga y zapata.
B24: =HYPERLINK("#'ZAP_COMBINADA'!A1","→ ZAP_COMBINADA") | D24: Zapata combinada rectangular de dos columnas: dimensiones, momentos, acero longitudinal y transversal, cortante y punzonamiento.
B25: =HYPERLINK("#'CIMIENTO'!A1","→ CIMIENTO") | D25: Cimiento corrido de concreto simple para muros de albañilería (E.060 cap. 22).
B26: =HYPERLINK("#'MURO'!A1","→ MURO") | D26: Muro de contención en voladizo: Rankine con sobrecarga y sismo (Mononobe–Okabe), volteo, deslizamiento, presiones, pantalla, puntera y talón.
B27: =HYPERLINK("#'ANCLAJES'!A1","→ ANCLAJES") | D27: Cuadro de longitudes de desarrollo, ganchos y empalmes por varilla (E.060 cap. 12).
B28: =HYPERLINK("#'TABLAS'!A1","→ TABLAS") | D28: Varillas, combinaciones para viguetas, cargas E.020, pesos de aligerados y coeficientes de losas (Tablas 13.1–13.3).
B30: CÓMO SE USA
B31: Celda amarilla con texto azul | D31: Dato que usted ingresa (cargas, dimensiones, materiales, varillas).
B32: Celda gris con texto negro | D32: Resultado calculado. Está protegida para no borrarla por error.
B33: CUMPLE / NO CUMPLE | D33: Verificación de la norma. Si no cumple, cambie el dato indicado en la nota de la derecha. REVISAR (naranja) es un aviso.
B34: Listas desplegables | D34: Varillas, sistema estructural, uso, caso de losa y otras opciones se eligen de una lista.
B35: Protección | D35: Las hojas están protegidas SIN contraseña: Revisar → Desproteger hoja, si necesita cambiar algo.
B37: REPORTE EN PDF
B38: 1. Abra la hoja que quiere imprimir.
B39: 2. Archivo → Exportar → Crear documento PDF/XPS (o Archivo → Imprimir → Microsoft Print to PDF).
B40: 3. Cada hoja ya está configurada en A4 vertical, ajustada al ancho, con encabezado, pie y número de página.
B41: 4. Para un solo PDF con varias hojas: selecciónelas con Ctrl + clic en las pestañas y luego exporte.
B42: 5. Para varios elementos (Z-1, Z-2, C-1…): clic derecho en la pestaña → Mover o copiar → Crear una copia.
B44: NORMAS Y CRITERIOS
B45: NTE E.060 Concreto Armado (DS 010-2009-VIVIENDA), verificada con el texto oficial: φ flexión 0.90, cortante 0.85, compresión con estribos 0.70 (hasta 0.90), aplastamiento 0.70.
B46: Combinaciones: U = 1.4CM + 1.7CV; U = 1.25(CM+CV) ± CS; U = 0.9CM ± CS; empuje lateral 1.7. Capítulo 21 según el sistema: pórticos/dual tipo II o muros/dual tipo I.
B47: NTE E.020 Cargas · NTE E.030 Diseño sismorresistente (para δu, R y combinaciones) · NTE E.050 Suelos · RNE A.010 (escaleras).
B48: Unidades: fuerzas en t (toneladas-fuerza), momentos en t·m, esfuerzos en kgf/cm², longitudes en m o cm según se indique. Las fórmulas de la norma (MPa) se convirtieron a kgf/cm².
B50: AVISO: esta plantilla es una herramienta gratuita de apoyo al cálculo. No reemplaza el criterio del ingeniero. Los resultados deben ser revisados y firmados por un ingeniero civil colegiado y habilitado, responsable del proyecto. ALF_BIM no se responsabiliza por el uso que se dé a los resultados.
B54: ¿Necesita más? Memoria estructural desde ETABS, acero en Revit, valorizaciones y más en www.alfbim.com

Sheet PREDIM
B1: PREDIMENSIONAMIENTO DE ELEMENTOS ESTRUCTURALES
B2: ALF_BIM · Plantilla Excel Estructuras · NTE E.060 Concreto Armado · v2.1.0
B3: Proyecto | C3: =INICIO!$D$7
B4: Ubicación | C4: =INICIO!$D$9
B5: Elemento | C5: Edificación de 4 niveles
B6: Calculista | C6: =INICIO!$D$10&IF(INICIO!$D$11="",""," · CIP "&INICIO!$D$11)
B7: Fecha | C7: =INICIO!$D$12
B10: 1. LOSAS
B11: Resistencia del concreto | C11: f'c | D11: 210 | E11: kgf/cm²
B12: Fluencia del acero | C12: fy | D12: 4200 | E12: kgf/cm²
B13: Luz libre mayor del aligerado (una dirección) | C13: ln | D13: 4.2 | E13: m
B14: Aligerado: criterio práctico ln/25 | C14: h | D14: =$D$13/25*100 | E14: cm | F14: Práctica peruana para s/c ≤ 300 kgf/m²
B15: Aligerado: referencia Tabla 9.1 (ambos extremos continuos ℓ/21) | C15: h | D15: =$D$13/21*100 | E15: cm | F15: E.060 9.6.2.1: sin verificar deflexiones
B16: PERALTE DE ALIGERADO SUGERIDO | C16: h | D16: =IF($D$14<=17,17,IF($D$14<=20,20,IF($D$14<=25,25,30))) | E16: cm | F16: Valores comerciales 17 / 20 / 25 / 30 cm
B17: h sugerido ≥ referencia Tabla 9.1 | C17: =IF($D$16>=$D$15,"CUMPLE","REVISAR") | F17: Si sale REVISAR: verifique deflexiones en la hoja ALIGERADO o use el h mayor
B18: Losa maciza en dos direcciones: luz libre corta A | C18: A | D18: 4 | E18: m
B19: Losa maciza en dos direcciones: luz libre larga B | C19: B | D19: 5 | E19: m
B20: Criterio práctico perímetro/180 | C20: h | D20: =2*($D$18+$D$19)/180*100 | E20: cm
B21: E.060 9.6.3.3 con vigas rígidas (αfm > 2) | C21: h | D21: =MAX(9,$D$19*100*(0.8+$D$12/14000)/(36+9*$D$19/$D$18)) | E21: cm | F21: h = ln(0.8 + fy/14000)/(36 + 9β) ≥ 9 cm
B22: ESPESOR DE LOSA MACIZA SUGERIDO | C22: h | D22: =CEILING(MAX($D$20,$D$21),1) | E22: cm
B24: 2. VIGAS
B25: Luz libre de la viga | C25: ln | D25: 6 | E25: m
B26: Sistema estructural | D26: Pórticos o dual tipo II
B27: Peralte ln/10 (sismo, pórticos) | C27: h | D27: =$D$25/10*100 | E27: cm
B28: Peralte ln/12 (gravedad o muros) | C28: h | D28: =$D$25/12*100 | E28: cm
B29: PERALTE DE VIGA SUGERIDO | C29: h | D29: =CEILING(IF($D$26="Pórticos o dual tipo II",$D$27,($D$27+$D$28)/2),5) | E29: cm | F29: Redondeado a 5 cm
B30: ANCHO DE VIGA SUGERIDO | C30: b | D30: =MAX(25,CEILING($D$29/2,5)) | E30: cm | F30: E.060 21.5.1: bw ≥ 25 cm y ≥ 0.25h
B31: Referencia Tabla 9.1 (ambos extremos continuos ℓ/21) | C31: h | D31: =$D$25/21*100 | E31: cm
B33: 3. COLUMNAS (área tributaria)
B34: Área tributaria | C34: At | D34: 20 | E34: m²
B35: Número de pisos sobre la columna | C35: N | D35: 4
B36: Categoría de la edificación (E.030) | D36: C | F36: A esencial 1.5 · B importante 1.25 · C común 1.0 t/m²
B37: Ubicación de la columna | D37: Interior | F37: Interior: n = 0.45 · Exterior o esquina: n = 0.35
B38: Peso unitario por piso | C38: Pg | D38: =IF($D$36="A",1.5,IF($D$36="B",1.25,1.0)) | E38: t/m²
B39: Carga de servicio P = Pg·At·N | C39: P | D39: =$D$38*$D$34*$D$35 | E39: t
B40: Factor n | C40: n | D40: =IF($D$37="Interior",0.45,0.35)
B41: Área de columna Ac = P/(n·f'c) | C41: Ac | D41: =$D$39*1000/($D$40*$D$11) | E41: cm² | F41: Criterio de Blanco Blasco
B42: LADO DE COLUMNA CUADRADA | C42: b | D42: =MAX(25,CEILING(SQRT($D$41),5)) | E42: cm | F42: Mínimo 25 cm (E.060 21.6.1.2)
B43: Ancho fijo para columna rectangular | C43: b | D43: 30 | E43: cm
B44: LARGO DE COLUMNA RECTANGULAR | C44: h | D44: =MAX($D$43,CEILING($D$41/$D$43,5)) | E44: cm
B46: 4. PLACAS: LONGITUD MÍNIMA POR DIRECCIÓN (estimación)
B47: Factor de zona Z | C47: Z | D47: 0.35 | F47: E.030 Anexo: zona según el distrito
B48: Factor de uso U | C48: U | D48: 1
B49: Factor de suelo S | C49: S | D49: 1.15
B50: Coeficiente de reducción R | C50: R | D50: 6 | F50: Muros estructurales R0 = 6
B51: Área techada total (todos los pisos) | C51: Atot | D51: 480 | E51: m²
B52: Peso sísmico unitario | C52: w | D52: 1 | E52: t/m² | F52: ≈ 1.0 t/m² para edificios de concreto
B53: Espesor de placa | C53: t | D53: 20 | E53: cm | F53: E.060 21.9.3.2: ≥ 15 cm
B54: Cortante basal V = Z·U·C·S/R·P (C = 2.5) | C54: V | D54: =$D$47*$D$48*2.5*$D$49/$D$50*$D$51*$D$52 | E54: t
B55: Resistencia del concreto φ·0.53·√f'c | C55: φvc | D55: =0.85*0.53*SQRT($D$11) | E55: kgf/cm²
B56: LONGITUD DE PLACAS POR DIRECCIÓN L ≥ V/(φvc·t) | C56: L | D56: =$D$54*1000/($D$55*$D$53)/100 | E56: m | F56: Estimación inicial: verifique con el análisis sísmico

Sheet VIGA
B1: DISEÑO DE VIGA SÍSMICA · NTE E.060 CAP. 10, 11 Y 21
B2: ALF_BIM · Plantilla Excel Estructuras · NTE E.060 Concreto Armado · v2.1.0
B3: Proyecto | C3: =INICIO!$D$7
B4: Ubicación | C4: =INICIO!$D$9
B5: Elemento | C5: Viga V-101 (30×60), eje 2, tramo A–B
B6: Calculista | C6: =INICIO!$D$10&IF(INICIO!$D$11="",""," · CIP "&INICIO!$D$11)
B7: Fecha | C7: =INICIO!$D$12
B10: 1. DATOS DE ENTRADA
B11: Resistencia del concreto | C11: f'c | D11: 210 | E11: kgf/cm² | F11: Elementos sísmicos: f'c ≥ 210 (21.3.2)
B12: Fluencia del acero | C12: fy | D12: 4200 | E12: kgf/cm²
B13: Sistema estructural (define el capítulo 21) | D13: Pórticos o dual tipo II
B14: Ancho de la viga | C14: b | D14: 30 | E14: cm
B15: Peralte de la viga | C15: h | D15: 60 | E15: cm
B16: Del borde al centroide del acero en tracción | C16: d' | D16: 6 | E16: cm | F16: Una capa: 4 + Ø estribo + db/2 ≈ 6 cm
B17: Luz libre (cara a cara de columnas) | C17: ln | D17: 5.6 | E17: m
B18: Varilla superior | C18: Øs | D18: 3/4"
B19: Varilla inferior | C19: Øi | D19: 5/8"
B20: Varilla del estribo | C20: Øe | D20: 3/8" | F20: E.060 21: Ø 3/8" para barras hasta 1"
B21: Ramas del estribo | C21: n | D21: 2
B22: Cargas de gravedad sobre la viga (servicio) y cortantes del análisis
B23: Carga muerta repartida | C23: wD | D23: 2.1 | E23: t/m
B24: Carga viva repartida | C24: wL | D24: 0.8 | E24: t/m
B25: Cortante último máximo del análisis (envolvente) | C25: Vua | D25: 14 | E25: t
B26: Cortante de sismo puro en la cara | C26: VS | D26: 5 | E26: t | F26: Para la alternativa 2.5·sismo (21.4.3)
B27: Momentos últimos en las caras (envolvente del análisis, valores positivos)
B28: Sección | C28: Izq (−) | D28: Izq (+) | E28: Centro (−) | F28: Centro (+) | G28: Der (−) | H28: Der (+)
B29: Mu (t·m) | C29: 22 | D29: 9 | E29: 0 | F29: 12 | G29: 24 | H29: 10
B30: n varillas (vacío = automático)
B31: La armadura se elige sola (mínimo 2 varillas corridas). Escriba un número en la fila amarilla para fijarla usted.
B33: 2. PROPIEDADES Y LÍMITES (E.060 10.3, 10.5 y 21)
B34: Peralte efectivo d = h − d' | C34: d | D34: =$D$15-$D$16 | E34: cm
B35: Diámetro superior | C35: db | D35: =INDEX(BAR_DB,MATCH($D$18,BAR_NOM,0)) | E35: cm
B36: Área de la varilla superior | C36: Ab | D36: =INDEX(BAR_AS,MATCH($D$18,BAR_NOM,0)) | E36: cm²
B37: Diámetro inferior | C37: db | D37: =INDEX(BAR_DB,MATCH($D$19,BAR_NOM,0)) | E37: cm
B38: Área de la varilla inferior | C38: Ab | D38: =INDEX(BAR_AS,MATCH($D$19,BAR_NOM,0)) | E38: cm²
B39: Diámetro del estribo | C39: dbe | D39: =INDEX(BAR_DB,MATCH($D$20,BAR_NOM,0)) | E39: cm
B40: Área del estribo | C40: Abe | D40: =INDEX(BAR_AS,MATCH($D$20,BAR_NOM,0)) | E40: cm²
B41: Factor β1 | C41: β1 | D41: =IF($D$11<=280,0.85,MAX(0.65,0.85-0.05*($D$11-280)/70))
B42: Cuantía balanceada | C42: ρb | D42: =0.85*$D$41*$D$11/$D$12*6000/(6000+$D$12)
B43: As mínimo 0.7·√f'c/fy·b·d | C43: Asmín | D43: =0.7*SQRT($D$11)/$D$12*$D$14*$D$34 | E43: cm² | F43: E.060 10.5.2
B44: As máximo (simplemente armada) | C44: Asmáx | D44: =IF($D$13="Pórticos o dual tipo II",MIN(0.75*$D$42,0.025),0.75*$D$42)*$D$14*$D$34 | E44: cm² | F44: 0.75·ρb (10.3.4); pórticos además ρ ≤ 0.025 (21.5.2.1)
B45: Bloque con As máximo | C45: a | D45: =$D$44*$D$12/(0.85*$D$11*$D$14) | E45: cm
B46: φMn máximo simplemente armada | C46: φMn1 | D46: =0.9*$D$44*$D$12*($D$34-$D$45/2)/100000 | E46: t·m
B47: Relación M+ ≥ k·M− en la cara | C47: k | D47: =IF($D$13="Pórticos o dual tipo II",0.5,1/3) | F47: 1/2 pórticos (21.5.2.2) · 1/3 muros (21.4.4.3)
B49: 3. DISEÑO POR FLEXIÓN (φ = 0.90)
B50: Sección | C50: Izq (−) | D50: Izq (+) | E50: Centro (−) | F50: Centro (+) | G50: Der (−) | H50: Der (+)
B51: As por flexión (con doble armadura si hace falta) (cm²) | C51: =IF($C$29<=$D$46,0.85*$D$11*$D$14*$D$34/$D$12*(1-SQRT(MAX(0,1-2*$C$29*100000/(0.9*0.85*$D$11*$D$14*$D$34^2)))),$D$44+($C$29-$D$46)*100000/(0.9*$D$12*($D$34-$D$16))) | D51: =IF($D$29<=$D$46,0.85*$D$11*$D$14*$D$34/$D$12*(1-SQRT(MAX(0,1-2*$D$29*100000/(0.9*0.85*$D$11*$D$14*$D$34^2)))),$D$44+($D$29-$D$46)*100000/(0.9*$D$12*($D$34-$D$16))) | E51: =IF($E$29<=$D$46,0.85*$D$11*$D$14*$D$34/$D$12*(1-SQRT(MAX(0,1-2*$E$29*100000/(0.9*0.85*$D$11*$D$14*$D$34^2)))),$D$44+($E$29-$D$46)*100000/(0.9*$D$12*($D$34-$D$16))) | F51: =IF($F$29<=$D$46,0.85*$D$11*$D$14*$D$34/$D$12*(1-SQRT(MAX(0,1-2*$F$29*100000/(0.9*0.85*$D$11*$D$14*$D$34^2)))),$D$44+($F$29-$D$46)*100000/(0.9*$D$12*($D$34-$D$16))) | G51: =IF($G$29<=$D$46,0.85*$D$11*$D$14*$D$34/$D$12*(1-SQRT(MAX(0,1-2*$G$29*100000/(0.9*0.85*$D$11*$D$14*$D$34^2)))),$D$44+($G$29-$D$46)*100000/(0.9*$D$12*($D$34-$D$16))) | H51: =IF($H$29<=$D$46,0.85*$D$11*$D$14*$D$34/$D$12*(1-SQRT(MAX(0,1-2*$H$29*100000/(0.9*0.85*$D$11*$D$14*$D$34^2)))),$D$44+($H$29-$D$46)*100000/(0.9*$D$12*($D$34-$D$16)))
B52: A's requerido en compresión (cm²) | C52: =IF($C$29>$D$46,($C$29-$D$46)*100000/(0.9*$D$12*($D$34-$D$16)),0) | D52: =IF($D$29>$D$46,($D$29-$D$46)*100000/(0.9*$D$12*($D$34-$D$16)),0) | E52: =IF($E$29>$D$46,($E$29-$D$46)*100000/(0.9*$D$12*($D$34-$D$16)),0) | F52: =IF($F$29>$D$46,($F$29-$D$46)*100000/(0.9*$D$12*($D$34-$D$16)),0) | G52: =IF($G$29>$D$46,($G$29-$D$46)*100000/(0.9*$D$12*($D$34-$D$16)),0) | H52: =IF($H$29>$D$46,($H$29-$D$46)*100000/(0.9*$D$12*($D$34-$D$16)),0)
B53: Mínimo sísmico (¼ máx. y M+ ≥ k·M− en la cara) (cm²) | C53: =0.25*MAX($C$51,$D$51,$G$51,$H$51) | D53: =MAX(0.25*MAX($C$51,$D$51,$G$51,$H$51),$D$47*C55*$D$36) | E53: =0.25*MAX(C56,D56,G56,H56) | F53: =0.25*MAX(C56,D56,G56,H56) | G53: =0.25*MAX($C$51,$D$51,$G$51,$H$51) | H53: =MAX(0.25*MAX($C$51,$D$51,$G$51,$H$51),$D$47*G55*$D$36)
B54: As de diseño = máx(flexión, mínimo, sísmico) (cm²) | C54: =MAX($C$51,$D$43,$C$53) | D54: =MAX($D$51,$D$43,$D$53) | E54: =MAX($E$51,$D$43,$E$53) | F54: =MAX($F$51,$D$43,$F$53) | G54: =MAX($G$51,$D$43,$G$53) | H54: =MAX($H$51,$D$43,$H$53)
B55: Número de varillas | C55: =IF(N($C$30)>0,$C$30,MAX(2,CEILING($C$54/$D$36,1))) | D55: =IF(N($D$30)>0,$D$30,MAX(2,CEILING($D$54/$D$38,1))) | E55: =IF(N($E$30)>0,$E$30,MAX(2,CEILING($E$54/$D$36,1))) | F55: =IF(N($F$30)>0,$F$30,MAX(2,CEILING($F$54/$D$38,1))) | G55: =IF(N($G$30)>0,$G$30,MAX(2,CEILING($G$54/$D$36,1))) | H55: =IF(N($H$30)>0,$H$30,MAX(2,CEILING($H$54/$D$38,1)))
B56: As colocado (cm²) | C56: =$C$55*$D$36 | D56: =$D$55*$D$38 | E56: =$E$55*$D$36 | F56: =$F$55*$D$38 | G56: =$G$55*$D$36 | H56: =$H$55*$D$38
B57: A's que trabaja en compresión (cm²) | C57: =IF($C$52>0,MIN($D$56,$C$56),0) | D57: =IF($D$52>0,MIN($C$56,$D$56),0) | E57: =IF($E$52>0,MIN($F$56,$E$56),0) | F57: =IF($F$52>0,MIN($E$56,$F$56),0) | G57: =IF($G$52>0,MIN($H$56,$G$56),0) | H57: =IF($H$52>0,MIN($G$56,$H$56),0)
B58: Varillas que entran en una capa | C58: =FLOOR(($D$14-2*(4+$D$39)+MAX(2.5,$D$35))/($D$35+MAX(2.5,$D$35)),1) | D58: =FLOOR(($D$14-2*(4+$D$39)+MAX(2.5,$D$37))/($D$37+MAX(2.5,$D$37)),1) | E58: =FLOOR(($D$14-2*(4+$D$39)+MAX(2.5,$D$35))/($D$35+MAX(2.5,$D$35)),1) | F58: =FLOOR(($D$14-2*(4+$D$39)+MAX(2.5,$D$37))/($D$37+MAX(2.5,$D$37)),1) | G58: =FLOOR(($D$14-2*(4+$D$39)+MAX(2.5,$D$35))/($D$35+MAX(2.5,$D$35)),1) | H58: =FLOOR(($D$14-2*(4+$D$39)+MAX(2.5,$D$37))/($D$37+MAX(2.5,$D$37)),1)
B59: Peralte efectivo con 1 o 2 capas (cm) | C59: =$D$34-IF($C$55>$C$58,($D$35+MAX(2.5,$D$35))*($C$55-$C$58)/$C$55,0) | D59: =$D$34-IF($D$55>$D$58,($D$37+MAX(2.5,$D$37))*($D$55-$D$58)/$D$55,0) | E59: =$D$34-IF($E$55>$E$58,($D$35+MAX(2.5,$D$35))*($E$55-$E$58)/$E$55,0) | F59: =$D$34-IF($F$55>$F$58,($D$37+MAX(2.5,$D$37))*($F$55-$F$58)/$F$55,0) | G59: =$D$34-IF($G$55>$G$58,($D$35+MAX(2.5,$D$35))*($G$55-$G$58)/$G$55,0) | H59: =$D$34-IF($H$55>$H$58,($D$37+MAX(2.5,$D$37))*($H$55-$H$58)/$H$55,0)
B60: Eje neutro c (compatibilidad, f's real) (cm) | C60: =IF($C$57=0,$C$56*$D$12/(0.85*$D$11*$D$14*$D$41),IF(6000*(1-$D$16*0.85*$D$11*$D$14*$D$41/(($C$56-$C$57)*$D$12))>=$D$12,($C$56-$C$57)*$D$12/(0.85*$D$11*$D$14*$D$41),(-(6000*$C$57-$C$56*$D$12)+SQRT((6000*$C$57-$C$56*$D$12)^2+4*0.85*$D$11*$D$14*$D$41*6000*$C$57*$D$16))/(2*0.85*$D$11*$D$14*$D$41))) | D60: =IF($D$57=0,$D$56*$D$12/(0.85*$D$11*$D$14*$D$41),IF(6000*(1-$D$16*0.85*$D$11*$D$14*$D$41/(($D$56-$D$57)*$D$12))>=$D$12,($D$56-$D$57)*$D$12/(0.85*$D$11*$D$14*$D$41),(-(6000*$D$57-$D$56*$D$12)+SQRT((6000*$D$57-$D$56*$D$12)^2+4*0.85*$D$11*$D$14*$D$41*6000*$D$57*$D$16))/(2*0.85*$D$11*$D$14*$D$41))) | E60: =IF($E$57=0,$E$56*$D$12/(0.85*$D$11*$D$14*$D$41),IF(6000*(1-$D$16*0.85*$D$11*$D$14*$D$41/(($E$56-$E$57)*$D$12))>=$D$12,($E$56-$E$57)*$D$12/(0.85*$D$11*$D$14*$D$41),(-(6000*$E$57-$E$56*$D$12)+SQRT((6000*$E$57-$E$56*$D$12)^2+4*0.85*$D$11*$D$14*$D$41*6000*$E$57*$D$16))/(2*0.85*$D$11*$D$14*$D$41))) | F60: =IF($F$57=0,$F$56*$D$12/(0.85*$D$11*$D$14*$D$41),IF(6000*(1-$D$16*0.85*$D$11*$D$14*$D$41/(($F$56-$F$57)*$D$12))>=$D$12,($F$56-$F$57)*$D$12/(0.85*$D$11*$D$14*$D$41),(-(6000*$F$57-$F$56*$D$12)+SQRT((6000*$F$57-$F$56*$D$12)^2+4*0.85*$D$11*$D$14*$D$41*6000*$F$57*$D$16))/(2*0.85*$D$11*$D$14*$D$41))) | G60: =IF($G$57=0,$G$56*$D$12/(0.85*$D$11*$D$14*$D$41),IF(6000*(1-$D$16*0.85*$D$11*$D$14*$D$41/(($G$56-$G$57)*$D$12))>=$D$12,($G$56-$G$57)*$D$12/(0.85*$D$11*$D$14*$D$41),(-(6000*$G$57-$G$56*$D$12)+SQRT((6000*$G$57-$G$56*$D$12)^2+4*0.85*$D$11*$D$14*$D$41*6000*$G$57*$D$16))/(2*0.85*$D$11*$D$14*$D$41))) | H60: =IF($H$57=0,$H$56*$D$12/(0.85*$D$11*$D$14*$D$41),IF(6000*(1-$D$16*0.85*$D$11*$D$14*$D$41/(($H$56-$H$57)*$D$12))>=$D$12,($H$56-$H$57)*$D$12/(0.85*$D$11*$D$14*$D$41),(-(6000*$H$57-$H$56*$D$12)+SQRT((6000*$H$57-$H$56*$D$12)^2+4*0.85*$D$11*$D$14*$D$41*6000*$H$57*$D$16))/(2*0.85*$D$11*$D$14*$D$41)))
B61: Esfuerzo en el acero en compresión f's (kgf/cm²) | C61: =IF($C$57=0,0,MAX(-$D$12,MIN($D$12,6000*($C$60-$D$16)/$C$60))) | D61: =IF($D$57=0,0,MAX(-$D$12,MIN($D$12,6000*($D$60-$D$16)/$D$60))) | E61: =IF($E$57=0,0,MAX(-$D$12,MIN($D$12,6000*($E$60-$D$16)/$E$60))) | F61: =IF($F$57=0,0,MAX(-$D$12,MIN($D$12,6000*($F$60-$D$16)/$F$60))) | G61: =IF($G$57=0,0,MAX(-$D$12,MIN($D$12,6000*($G$60-$D$16)/$G$60))) | H61: =IF($H$57=0,0,MAX(-$D$12,MIN($D$12,6000*($H$60-$D$16)/$H$60)))
B62: Profundidad del bloque a = β1·c (cm) | C62: =$D$41*$C$60 | D62: =$D$41*$D$60 | E62: =$D$41*$E$60 | F62: =$D$41*$F$60 | G62: =$D$41*$G$60 | H62: =$D$41*$H$60
B63: φMn colocado (t·m) | C63: =0.9*(0.85*$D$11*$C$62*$D$14*($C$59-$C$62/2)+$C$57*$C$61*($C$59-$D$16))/100000 | D63: =0.9*(0.85*$D$11*$D$62*$D$14*($D$59-$D$62/2)+$D$57*$D$61*($D$59-$D$16))/100000 | E63: =0.9*(0.85*$D$11*$E$62*$D$14*($E$59-$E$62/2)+$E$57*$E$61*($E$59-$D$16))/100000 | F63: =0.9*(0.85*$D$11*$F$62*$D$14*($F$59-$F$62/2)+$F$57*$F$61*($F$59-$D$16))/100000 | G63: =0.9*(0.85*$D$11*$G$62*$D$14*($G$59-$G$62/2)+$G$57*$G$61*($G$59-$D$16))/100000 | H63: =0.9*(0.85*$D$11*$H$62*$D$14*($H$59-$H$62/2)+$H$57*$H$61*($H$59-$D$16))/100000
B64: Control (φMn ≥ Mu, ρ ≤ máx, capas) | C64: =IF($C$63<$C$29-0.0001,"NO CUMPLE",IF($C$56-$C$57*$C$61/$D$12>$D$44+0.0001,"NO CUMPLE: ρ máx",IF(AND($D$13="Pórticos o dual tipo II",$C$56>0.025*$D$14*$D$34),"NO CUMPLE: ρ > 0.025",IF(OR($C$55<2,$C$56<MAX($D$43,$C$53)-0.0001),"NO CUMPLE: As < mín",IF($C$55>2*$C$58,"NO CUMPLE: > 2 capas","CUMPLE"))))) | D64: =IF($D$63<$D$29-0.0001,"NO CUMPLE",IF($D$56-$D$57*$D$61/$D$12>$D$44+0.0001,"NO CUMPLE: ρ máx",IF(AND($D$13="Pórticos o dual tipo II",$D$56>0.025*$D$14*$D$34),"NO CUMPLE: ρ > 0.025",IF(OR($D$55<2,$D$56<MAX($D$43,$D$53)-0.0001),"NO CUMPLE: As < mín",IF($D$55>2*$D$58,"NO CUMPLE: > 2 capas","CUMPLE"))))) | E64: =IF($E$63<$E$29-0.0001,"NO CUMPLE",IF($E$56-$E$57*$E$61/$D$12>$D$44+0.0001,"NO CUMPLE: ρ máx",IF(AND($D$13="Pórticos o dual tipo II",$E$56>0.025*$D$14*$D$34),"NO CUMPLE: ρ > 0.025",IF(OR($E$55<2,$E$56<MAX($D$43,$E$53)-0.0001),"NO CUMPLE: As < mín",IF($E$55>2*$E$58,"NO CUMPLE: > 2 capas","CUMPLE"))))) | F64: =IF($F$63<$F$29-0.0001,"NO CUMPLE",IF($F$56-$F$57*$F$61/$D$12>$D$44+0.0001,"NO CUMPLE: ρ máx",IF(AND($D$13="Pórticos o dual tipo II",$F$56>0.025*$D$14*$D$34),"NO CUMPLE: ρ > 0.025",IF(OR($F$55<2,$F$56<MAX($D$43,$F$53)-0.0001),"NO CUMPLE: As < mín",IF($F$55>2*$F$58,"NO CUMPLE: > 2 capas","CUMPLE"))))) | G64: =IF($G$63<$G$29-0.0001,"NO CUMPLE",IF($G$56-$G$57*$G$61/$D$12>$D$44+0.0001,"NO CUMPLE: ρ máx",IF(AND($D$13="Pórticos o dual tipo II",$G$56>0.025*$D$14*$D$34),"NO CUMPLE: ρ > 0.025",IF(OR($G$55<2,$G$56<MAX($D$43,$G$53)-0.0001),"NO CUMPLE: As < mín",IF($G$55>2*$G$58,"NO CUMPLE: > 2 capas","CUMPLE"))))) | H64: =IF($H$63<$H$29-0.0001,"NO CUMPLE",IF($H$56-$H$57*$H$61/$D$12>$D$44+0.0001,"NO CUMPLE: ρ máx",IF(AND($D$13="Pórticos o dual tipo II",$H$56>0.025*$D$14*$D$34),"NO CUMPLE: ρ > 0.025",IF(OR($H$55<2,$H$56<MAX($D$43,$H$53)-0.0001),"NO CUMPLE: As < mín",IF($H$55>2*$H$58,"NO CUMPLE: > 2 capas","CUMPLE")))))
B65: ARMADURA | C65: =$C$55&" Ø "&$D$18&IF($C$55>$C$58," (2 capas)","") | D65: =$D$55&" Ø "&$D$19&IF($D$55>$D$58," (2 capas)","") | E65: =$E$55&" Ø "&$D$18&IF($E$55>$E$58," (2 capas)","") | F65: =$F$55&" Ø "&$D$19&IF($F$55>$F$58," (2 capas)","") | G65: =$G$55&" Ø "&$D$18&IF($G$55>$G$58," (2 capas)","") | H65: =$H$55&" Ø "&$D$19&IF($H$55>$H$58," (2 capas)","")
B66: Con dos capas se reduce d automáticamente (separación libre entre capas = máx(db, 2.5 cm)). φMn usa f's real del acero en compresión.
B68: 4. CORTANTE POR CAPACIDAD (E.060 21.4.3 / 21.5.4)
B69: Factor de momento probable | C69: k | D69: =IF($D$13="Pórticos o dual tipo II",1.25,1.0) | F69: Pórticos: Mpr = 1.25·Mn (21.5.4.1) · Muros: Mn (21.4.3)
B70: Cortante isostático 1.25(wD + wL)·ln/2 | C70: Vg | D70: =1.25*($D$23+$D$24)*$D$17/2 | E70: t | F70: Cargas de gravedad tributarias amplificadas
B71: Sismo horario: (Mn izq− + Mn der+)/ln | D71: =$D$69*($C$63+$H$63)/0.9/$D$17 | E71: t
B72: Sismo antihorario: (Mn izq+ + Mn der−)/ln | D72: =$D$69*($D$63+$G$63)/0.9/$D$17 | E72: t
B73: Cortante por capacidad Vg + máx | C73: Vcap | D73: =$D$70+MAX($D$71,$D$72) | E73: t
B74: Alternativa (b): Vg + 2.5·VS | C74: Vb | D74: =$D$70+2.5*$D$26 | E74: t | F74: Solo muros / dual tipo I (21.4.3b)
B75: CORTANTE DE DISEÑO Vu | C75: Vu | D75: =IF($D$13="Pórticos o dual tipo II",MAX($D$25,$D$73),MAX($D$25,MIN($D$73,$D$74))) | E75: t | F75: Nunca menor que el del análisis
B76: Vc = 0.53·√f'c·b·d | C76: Vc | D76: =0.53*SQRT($D$11)*$D$14*$D$34/1000 | E76: t | F76: E.060 11.3.1.1
B77: Vs = Vu/φ − Vc (φ = 0.85) | C77: Vs | D77: =MAX(0,$D$75/0.85-$D$76) | E77: t
B78: Vs ≤ 2.1·√f'c·b·d | C78: =IF($D$77<=2.1*SQRT($D$11)*$D$14*$D$34/1000,"CUMPLE","NO CUMPLE") | F78: Si no cumple: aumente la sección (11.5.7.9)
B79: Área de estribos Av = ramas·Abe | C79: Av | D79: =$D$21*$D$40 | E79: cm²
B80: Espaciamiento por resistencia s = Av·fy·d/Vs | C80: s | D80: =IF($D$77<=0,999,$D$79*$D$12*$D$34/($D$77*1000)) | E80: cm
B81: Menor varilla longitudinal | C81: db | D81: =MIN($D$35,$D$37) | E81: cm
B82: Espaciamiento en la zona de confinamiento (2h) | C82: so | D82: =FLOOR(MIN(IF($D$13="Pórticos o dual tipo II",$D$34/4,MAX($D$34/4,15)),IF($D$13="Pórticos o dual tipo II",8,10)*$D$81,24*$D$39,30,$D$80),2.5) | E82: cm | F82: Pórticos: d/4, 8db, 24dbe, 30 (21.5.3.2) · Muros: d/4 ≥ 15, 10db, 24dbe, 30 (21.4.4.4)
B83: Primer estribo desde la cara | C83: s1 | D83: =IF($D$13="Pórticos o dual tipo II",5,10) | E83: cm | F83: ≤ 5 cm pórticos · ≤ 10 cm muros
B84: Longitud de confinamiento 2h | C84: Lc | D84: =2*$D$15 | E84: cm
B85: Estribos en la zona de confinamiento | C85: n | D85: =CEILING(($D$84-$D$83)/$D$82,1)
B86: Espaciamiento fuera de la zona | C86: s | D86: =FLOOR(MIN($D$34/2,$D$80,IF($D$77>1.1*SQRT($D$11)*$D$14*$D$34/1000,$D$34/4,60)),2.5) | E86: cm | F86: d/2 (d/4 si Vs > 1.1√f'c·b·d)
B87: Av ≥ Av mín = máx(0.2√f'c, 3.5)·b·s/fy | C87: =IF($D$79>=MAX(0.2*SQRT($D$11),3.5)*$D$14*$D$86/$D$12,"CUMPLE","NO CUMPLE") | F87: E.060 11.5.6.3
B88: ESTRIBOS (en cada extremo) | D88: ="□ Ø "&$D$20&": 1 @ "&FIXED($D$83/100,IF(MOD(ROUND($D$83*10,0),50)=0,2,3))&", "&$D$85&" @ "&FIXED($D$82/100,IF(MOD(ROUND($D$82*10,0),50)=0,2,3))&", resto @ "&FIXED($D$86/100,IF(MOD(ROUND($D$86*10,0),50)=0,2,3))&" m"
B90: 5. REQUISITOS GEOMÉTRICOS Y ANCLAJES
B91: Pórticos: b ≥ 25 cm, b ≥ 0.25h y ln ≥ 4h (21.5.1) | C91: =IF(OR(NOT($D$13="Pórticos o dual tipo II"),AND($D$14>=25,$D$14>=0.25*$D$15,$D$17*100>=4*$D$15)),"CUMPLE","NO CUMPLE") | F91: Solo aplica a pórticos y dual tipo II
B92: Referencia Tabla 9.1: h ≥ ℓn/21 (ambos extremos continuos) | C92: =IF($D$15>=$D$17*100/21,"CUMPLE","REVISAR") | F92: Si no cumple: verifique deflexiones (9.6.2)
B93: ld de la varilla superior (ψt = 1.3) | C93: ld | D93: =MAX(30,$D$12*1.3*$D$35/(IF($D$35<=1.905,8.2,6.6)*SQRT($D$11))) | E93: cm | F93: E.060 Tabla 12.1
B94: ld de la varilla inferior | C94: ld | D94: =MAX(30,$D$12*1*$D$37/(IF($D$37<=1.905,8.2,6.6)*SQRT($D$11))) | E94: cm
B95: Gancho estándar en la columna (superior) | C95: ldg | D95: =MAX(15,8*$D$35,0.075*$D$12*$D$35/SQRT($D$11)) | E95: cm | F95: 12.5: 0.075·fy·db/√f'c ≥ 8db ≥ 15
B96: Empalme clase B superior (fuera de 2h y del nudo) | C96: le | D96: =MAX(30,1.3*$D$93) | E96: cm | F96: 21.5.2.3 / 21.4.4.2
B98: 6. RESUMEN
B99: Acero superior: Izq · Centro · Der | D99: =$C$65&" · "&$E$65&" · "&$G$65
B100: Acero inferior: Izq · Centro · Der | D100: =$D$65&" · "&$F$65&" · "&$H$65
B101: Estribos | D101: =$D$88
B102: ESTADO GENERAL DEL DISEÑO | C102: =IF(AND(COUNTIF($C$64:$H$64,"NO*")=0,$C$78="CUMPLE",$C$87="CUMPLE",$C$91="CUMPLE"),"CUMPLE","NO CUMPLE") | F102: Revise las líneas en rojo

Sheet COLUMNA
B1: DISEÑO DE COLUMNA · FLEXOCOMPRESIÓN BIAXIAL · NTE E.060
B2: ALF_BIM · Plantilla Excel Estructuras · NTE E.060 Concreto Armado · v2.1.0
B3: Proyecto | C3: =INICIO!$D$7
B4: Ubicación | C4: =INICIO!$D$9
B5: Elemento | C5: Columna C-1, 1er piso, eje B-2
B6: Calculista | C6: =INICIO!$D$10&IF(INICIO!$D$11="",""," · CIP "&INICIO!$D$11) | AD6: Capas de acero (no imprimir)
B7: Fecha | C7: =INICIO!$D$12 | AD7: i | AE7: d X (cm) | AF7: As X | AG7: d Y (cm) | AH7: As Y | AK7: Diagrama X (no imprimir) | AU7: Diagrama Y (no imprimir)
AD8: 1 | AE8: =IF(1<=$D$19,$D$61+($D$15-2*$D$61)*(1-1)/($D$19-1),0) | AF8: =IF(1<=$D$19,IF(OR(1=1,1=$D$19),$D$18,2)*$D$53,0) | AG8: =IF(1<=$D$18,$D$61+($D$14-2*$D$61)*(1-1)/($D$18-1),0) | AH8: =IF(1<=$D$18,IF(OR(1=1,1=$D$18),$D$19,2)*$D$53,0) | AK8: c (cm) | AL8: a (cm) | AM8: Pn (t) | AN8: Mn (t·m) | AO8: φ | AP8: φPn (t) | AQ8: φMn (t·m) | AR8: −e (m) | AS8: φPn sin tope | AU8: c (cm) | AV8: a (cm) | AW8: Pn (t) | AX8: Mn (t·m) | AY8: φ | AZ8: φPn (t) | BA8: φMn (t·m) | BB8: −e (m) | BC8: φPn sin tope
AD9: 2 | AE9: =IF(2<=$D$19,$D$61+($D$15-2*$D$61)*(2-1)/($D$19-1),0) | AF9: =IF(2<=$D$19,IF(OR(2=1,2=$D$19),$D$18,2)*$D$53,0) | AG9: =IF(2<=$D$18,$D$61+($D$14-2*$D$61)*(2-1)/($D$18-1),0) | AH9: =IF(2<=$D$18,IF(OR(2=1,2=$D$18),$D$19,2)*$D$53,0) | AK9: 0 | AL9: 0 | AM9: =-$D$12*$D$57/1000 | AN9: 0 | AO9: 0.9 | AP9: =AO9*AM9 | AQ9: 0 | AR9: -1000000000 | AS9: =AP9 | AU9: 0 | AV9: 0 | AW9: =-$D$12*$D$57/1000 | AX9: 0 | AY9: 0.9 | AZ9: =AY9*AW9 | BA9: 0 | BB9: -1000000000 | BC9: =AZ9
B10: 1. DATOS DE ENTRADA | AD10: 3 | AE10: =IF(3<=$D$19,$D$61+($D$15-2*$D$61)*(3-1)/($D$19-1),0) | AF10: =IF(3<=$D$19,IF(OR(3=1,3=$D$19),$D$18,2)*$D$53,0) | AG10: =IF(3<=$D$18,$D$61+($D$14-2*$D$61)*(3-1)/($D$18-1),0) | AH10: =IF(3<=$D$18,IF(OR(3=1,3=$D$18),$D$19,2)*$D$53,0) | AK10: =0.02*$D$15 | AL10: =MIN($D$66*AK10,$D$15) | AM10: =(0.85*$D$11*AL10*$D$14+SUMPRODUCT($AF$8:$AF$17,(ABS(6000*(1-$AE$8:$AE$17/AK10)+$D$12)-ABS(6000*(1-$AE$8:$AE$17/AK10)-$D$12))/2-0.85*$D$11*($AE$8:$AE$17<AL10)))/1000 | AN10: =(0.85*$D$11*AL10*$D$14*($D$15/2-AL10/2)+SUMPRODUCT($AF$8:$AF$17,(ABS(6000*(1-$AE$8:$AE$17/AK10)+$D$12)-ABS(6000*(1-$AE$8:$AE$17/AK10)-$D$12))/2-0.85*$D$11*($AE$8:$AE$17<AL10),$D$15/2-$AE$8:$AE$17))/100000 | AO10: =IF(AM10<=0,0.9,MAX(0.7,0.9/(1+0.2*AM10/$D$71))) | AP10: =MIN(AO10*AM10,$D$68) | AQ10: =MAX(0,AO10*AN10) | AR10: =IF(AS10>0,-AQ10/AS10,-1E+9) | AS10: =AO10*AM10 | AU10: =0.02*$D$14 | AV10: =MIN($D$66*AU10,$D$14) | AW10: =(0.85*$D$11*AV10*$D$15+SUMPRODUCT($AH$8:$AH$17,(ABS(6000*(1-$AG$8:$AG$17/AU10)+$D$12)-ABS(6000*(1-$AG$8:$AG$17/AU10)-$D$12))/2-0.85*$D$11*($AG$8:$AG$17<AV10)))/1000 | AX10: =(0.85*$D$11*AV10*$D$15*($D$14/2-AV10/2)+SUMPRODUCT($AH$8:$AH$17,(ABS(6000*(1-$AG$8:$AG$17/AU10)+$D$12)-ABS(6000*(1-$AG$8:$AG$17/AU10)-$D$12))/2-0.85*$D$11*($AG$8:$AG$17<AV10),$D$14/2-$AG$8:$AG$17))/100000 | AY10: =IF(AW10<=0,0.9,MAX(0.7,0.9/(1+0.2*AW10/$D$72))) | AZ10: =MIN(AY10*AW10,$D$68) | BA10: =MAX(0,AY10*AX10) | BB10: =IF(BC10>0,-BA10/BC10,-1E+9) | BC10: =AY10*AW10
B11: Resistencia del concreto | C11: f'c | D11: 210 | E11: kgf/cm² | AD11: 4 | AE11: =IF(4<=$D$19,$D$61+($D$15-2*$D$61)*(4-1)/($D$19-1),0) | AF11: =IF(4<=$D$19,IF(OR(4=1,4=$D$19),$D$18,2)*$D$53,0) | AG11: =IF(4<=$D$18,$D$61+($D$14-2*$D$61)*(4-1)/($D$18-1),0) | AH11: =IF(4<=$D$18,IF(OR(4=1,4=$D$18),$D$19,2)*$D$53,0) | AK11: =0.04*$D$15 | AL11: =MIN($D$66*AK11,$D$15) | AM11: =(0.85*$D$11*AL11*$D$14+SUMPRODUCT($AF$8:$AF$17,(ABS(6000*(1-$AE$8:$AE$17/AK11)+$D$12)-ABS(6000*(1-$AE$8:$AE$17/AK11)-$D$12))/2-0.85*$D$11*($AE$8:$AE$17<AL11)))/1000 | AN11: =(0.85*$D$11*AL11*$D$14*($D$15/2-AL11/2)+SUMPRODUCT($AF$8:$AF$17,(ABS(6000*(1-$AE$8:$AE$17/AK11)+$D$12)-ABS(6000*(1-$AE$8:$AE$17/AK11)-$D$12))/2-0.85*$D$11*($AE$8:$AE$17<AL11),$D$15/2-$AE$8:$AE$17))/100000 | AO11: =IF(AM11<=0,0.9,MAX(0.7,0.9/(1+0.2*AM11/$D$71))) | AP11: =MIN(AO11*AM11,$D$68) | AQ11: =MAX(0,AO11*AN11) | AR11: =IF(AS11>0,-AQ11/AS11,-1E+9) | AS11: =AO11*AM11 | AU11: =0.04*$D$14 | AV11: =MIN($D$66*AU11,$D$14) | AW11: =(0.85*$D$11*AV11*$D$15+SUMPRODUCT($AH$8:$AH$17,(ABS(6000*(1-$AG$8:$AG$17/AU11)+$D$12)-ABS(6000*(1-$AG$8:$AG$17/AU11)-$D$12))/2-0.85*$D$11*($AG$8:$AG$17<AV11)))/1000 | AX11: =(0.85*$D$11*AV11*$D$15*($D$14/2-AV11/2)+SUMPRODUCT($AH$8:$AH$17,(ABS(6000*(1-$AG$8:$AG$17/AU11)+$D$12)-ABS(6000*(1-$AG$8:$AG$17/AU11)-$D$12))/2-0.85*$D$11*($AG$8:$AG$17<AV11),$D$14/2-$AG$8:$AG$17))/100000 | AY11: =IF(AW11<=0,0.9,MAX(0.7,0.9/(1+0.2*AW11/$D$72))) | AZ11: =MIN(AY11*AW11,$D$68) | BA11: =MAX(0,AY11*AX11) | BB11: =IF(BC11>0,-BA11/BC11,-1E+9) | BC11: =AY11*AW11
B12: Fluencia del acero | C12: fy | D12: 4200 | E12: kgf/cm² | AD12: 5 | AE12: =IF(5<=$D$19,$D$61+($D$15-2*$D$61)*(5-1)/($D$19-1),0) | AF12: =IF(5<=$D$19,IF(OR(5=1,5=$D$19),$D$18,2)*$D$53,0) | AG12: =IF(5<=$D$18,$D$61+($D$14-2*$D$61)*(5-1)/($D$18-1),0) | AH12: =IF(5<=$D$18,IF(OR(5=1,5=$D$18),$D$19,2)*$D$53,0) | AK12: =0.06*$D$15 | AL12: =MIN($D$66*AK12,$D$15) | AM12: =(0.85*$D$11*AL12*$D$14+SUMPRODUCT($AF$8:$AF$17,(ABS(6000*(1-$AE$8:$AE$17/AK12)+$D$12)-ABS(6000*(1-$AE$8:$AE$17/AK12)-$D$12))/2-0.85*$D$11*($AE$8:$AE$17<AL12)))/1000 | AN12: =(0.85*$D$11*AL12*$D$14*($D$15/2-AL12/2)+SUMPRODUCT($AF$8:$AF$17,(ABS(6000*(1-$AE$8:$AE$17/AK12)+$D$12)-ABS(6000*(1-$AE$8:$AE$17/AK12)-$D$12))/2-0.85*$D$11*($AE$8:$AE$17<AL12),$D$15/2-$AE$8:$AE$17))/100000 | AO12: =IF(AM12<=0,0.9,MAX(0.7,0.9/(1+0.2*AM12/$D$71))) | AP12: =MIN(AO12*AM12,$D$68) | AQ12: =MAX(0,AO12*AN12) | AR12: =IF(AS12>0,-AQ12/AS12,-1E+9) | AS12: =AO12*AM12 | AU12: =0.06*$D$14 | AV12: =MIN($D$66*AU12,$D$14) | AW12: =(0.85*$D$11*AV12*$D$15+SUMPRODUCT($AH$8:$AH$17,(ABS(6000*(1-$AG$8:$AG$17/AU12)+$D$12)-ABS(6000*(1-$AG$8:$AG$17/AU12)-$D$12))/2-0.85*$D$11*($AG$8:$AG$17<AV12)))/1000 | AX12: =(0.85*$D$11*AV12*$D$15*($D$14/2-AV12/2)+SUMPRODUCT($AH$8:$AH$17,(ABS(6000*(1-$AG$8:$AG$17/AU12)+$D$12)-ABS(6000*(1-$AG$8:$AG$17/AU12)-$D$12))/2-0.85*$D$11*($AG$8:$AG$17<AV12),$D$14/2-$AG$8:$AG$17))/100000 | AY12: =IF(AW12<=0,0.9,MAX(0.7,0.9/(1+0.2*AW12/$D$72))) | AZ12: =MIN(AY12*AW12,$D$68) | BA12: =MAX(0,AY12*AX12) | BB12: =IF(BC12>0,-BA12/BC12,-1E+9) | BC12: =AY12*AW12
B13: Sistema estructural (define el capítulo 21) | D13: Muros estructurales o dual tipo I | AD13: 6 | AE13: =IF(6<=$D$19,$D$61+($D$15-2*$D$61)*(6-1)/($D$19-1),0) | AF13: =IF(6<=$D$19,IF(OR(6=1,6=$D$19),$D$18,2)*$D$53,0) | AG13: =IF(6<=$D$18,$D$61+($D$14-2*$D$61)*(6-1)/($D$18-1),0) | AH13: =IF(6<=$D$18,IF(OR(6=1,6=$D$18),$D$19,2)*$D$53,0) | AK13: =0.08*$D$15 | AL13: =MIN($D$66*AK13,$D$15) | AM13: =(0.85*$D$11*AL13*$D$14+SUMPRODUCT($AF$8:$AF$17,(ABS(6000*(1-$AE$8:$AE$17/AK13)+$D$12)-ABS(6000*(1-$AE$8:$AE$17/AK13)-$D$12))/2-0.85*$D$11*($AE$8:$AE$17<AL13)))/1000 | AN13: =(0.85*$D$11*AL13*$D$14*($D$15/2-AL13/2)+SUMPRODUCT($AF$8:$AF$17,(ABS(6000*(1-$AE$8:$AE$17/AK13)+$D$12)-ABS(6000*(1-$AE$8:$AE$17/AK13)-$D$12))/2-0.85*$D$11*($AE$8:$AE$17<AL13),$D$15/2-$AE$8:$AE$17))/100000 | AO13: =IF(AM13<=0,0.9,MAX(0.7,0.9/(1+0.2*AM13/$D$71))) | AP13: =MIN(AO13*AM13,$D$68) | AQ13: =MAX(0,AO13*AN13) | AR13: =IF(AS13>0,-AQ13/AS13,-1E+9) | AS13: =AO13*AM13 | AU13: =0.08*$D$14 | AV13: =MIN($D$66*AU13,$D$14) | AW13: =(0.85*$D$11*AV13*$D$15+SUMPRODUCT($AH$8:$AH$17,(ABS(6000*(1-$AG$8:$AG$17/AU13)+$D$12)-ABS(6000*(1-$AG$8:$AG$17/AU13)-$D$12))/2-0.85*$D$11*($AG$8:$AG$17<AV13)))/1000 | AX13: =(0.85*$D$11*AV13*$D$15*($D$14/2-AV13/2)+SUMPRODUCT($AH$8:$AH$17,(ABS(6000*(1-$AG$8:$AG$17/AU13)+$D$12)-ABS(6000*(1-$AG$8:$AG$17/AU13)-$D$12))/2-0.85*$D$11*($AG$8:$AG$17<AV13),$D$14/2-$AG$8:$AG$17))/100000 | AY13: =IF(AW13<=0,0.9,MAX(0.7,0.9/(1+0.2*AW13/$D$72))) | AZ13: =MIN(AY13*AW13,$D$68) | BA13: =MAX(0,AY13*AX13) | BB13: =IF(BC13>0,-BA13/BC13,-1E+9) | BC13: =AY13*AW13
B14: Dimensión B (paralela al eje X) | C14: B | D14: 35 | E14: cm | AD14: 7 | AE14: =IF(7<=$D$19,$D$61+($D$15-2*$D$61)*(7-1)/($D$19-1),0) | AF14: =IF(7<=$D$19,IF(OR(7=1,7=$D$19),$D$18,2)*$D$53,0) | AG14: =IF(7<=$D$18,$D$61+($D$14-2*$D$61)*(7-1)/($D$18-1),0) | AH14: =IF(7<=$D$18,IF(OR(7=1,7=$D$18),$D$19,2)*$D$53,0) | AK14: =0.1*$D$15 | AL14: =MIN($D$66*AK14,$D$15) | AM14: =(0.85*$D$11*AL14*$D$14+SUMPRODUCT($AF$8:$AF$17,(ABS(6000*(1-$AE$8:$AE$17/AK14)+$D$12)-ABS(6000*(1-$AE$8:$AE$17/AK14)-$D$12))/2-0.85*$D$11*($AE$8:$AE$17<AL14)))/1000 | AN14: =(0.85*$D$11*AL14*$D$14*($D$15/2-AL14/2)+SUMPRODUCT($AF$8:$AF$17,(ABS(6000*(1-$AE$8:$AE$17/AK14)+$D$12)-ABS(6000*(1-$AE$8:$AE$17/AK14)-$D$12))/2-0.85*$D$11*($AE$8:$AE$17<AL14),$D$15/2-$AE$8:$AE$17))/100000 | AO14: =IF(AM14<=0,0.9,MAX(0.7,0.9/(1+0.2*AM14/$D$71))) | AP14: =MIN(AO14*AM14,$D$68) | AQ14: =MAX(0,AO14*AN14) | AR14: =IF(AS14>0,-AQ14/AS14,-1E+9) | AS14: =AO14*AM14 | AU14: =0.1*$D$14 | AV14: =MIN($D$66*AU14,$D$14) | AW14: =(0.85*$D$11*AV14*$D$15+SUMPRODUCT($AH$8:$AH$17,(ABS(6000*(1-$AG$8:$AG$17/AU14)+$D$12)-ABS(6000*(1-$AG$8:$AG$17/AU14)-$D$12))/2-0.85*$D$11*($AG$8:$AG$17<AV14)))/1000 | AX14: =(0.85*$D$11*AV14*$D$15*($D$14/2-AV14/2)+SUMPRODUCT($AH$8:$AH$17,(ABS(6000*(1-$AG$8:$AG$17/AU14)+$D$12)-ABS(6000*(1-$AG$8:$AG$17/AU14)-$D$12))/2-0.85*$D$11*($AG$8:$AG$17<AV14),$D$14/2-$AG$8:$AG$17))/100000 | AY14: =IF(AW14<=0,0.9,MAX(0.7,0.9/(1+0.2*AW14/$D$72))) | AZ14: =MIN(AY14*AW14,$D$68) | BA14: =MAX(0,AY14*AX14) | BB14: =IF(BC14>0,-BA14/BC14,-1E+9) | BC14: =AY14*AW14
B15: Dimensión H (paralela al eje Y) | C15: H | D15: 50 | E15: cm | AD15: 8 | AE15: =IF(8<=$D$19,$D$61+($D$15-2*$D$61)*(8-1)/($D$19-1),0) | AF15: =IF(8<=$D$19,IF(OR(8=1,8=$D$19),$D$18,2)*$D$53,0) | AG15: =IF(8<=$D$18,$D$61+($D$14-2*$D$61)*(8-1)/($D$18-1),0) | AH15: =IF(8<=$D$18,IF(OR(8=1,8=$D$18),$D$19,2)*$D$53,0) | AK15: =0.13*$D$15 | AL15: =MIN($D$66*AK15,$D$15) | AM15: =(0.85*$D$11*AL15*$D$14+SUMPRODUCT($AF$8:$AF$17,(ABS(6000*(1-$AE$8:$AE$17/AK15)+$D$12)-ABS(6000*(1-$AE$8:$AE$17/AK15)-$D$12))/2-0.85*$D$11*($AE$8:$AE$17<AL15)))/1000 | AN15: =(0.85*$D$11*AL15*$D$14*($D$15/2-AL15/2)+SUMPRODUCT($AF$8:$AF$17,(ABS(6000*(1-$AE$8:$AE$17/AK15)+$D$12)-ABS(6000*(1-$AE$8:$AE$17/AK15)-$D$12))/2-0.85*$D$11*($AE$8:$AE$17<AL15),$D$15/2-$AE$8:$AE$17))/100000 | AO15: =IF(AM15<=0,0.9,MAX(0.7,0.9/(1+0.2*AM15/$D$71))) | AP15: =MIN(AO15*AM15,$D$68) | AQ15: =MAX(0,AO15*AN15) | AR15: =IF(AS15>0,-AQ15/AS15,-1E+9) | AS15: =AO15*AM15 | AU15: =0.13*$D$14 | AV15: =MIN($D$66*AU15,$D$14) | AW15: =(0.85*$D$11*AV15*$D$15+SUMPRODUCT($AH$8:$AH$17,(ABS(6000*(1-$AG$8:$AG$17/AU15)+$D$12)-ABS(6000*(1-$AG$8:$AG$17/AU15)-$D$12))/2-0.85*$D$11*($AG$8:$AG$17<AV15)))/1000 | AX15: =(0.85*$D$11*AV15*$D$15*($D$14/2-AV15/2)+SUMPRODUCT($AH$8:$AH$17,(ABS(6000*(1-$AG$8:$AG$17/AU15)+$D$12)-ABS(6000*(1-$AG$8:$AG$17/AU15)-$D$12))/2-0.85*$D$11*($AG$8:$AG$17<AV15),$D$14/2-$AG$8:$AG$17))/100000 | AY15: =IF(AW15<=0,0.9,MAX(0.7,0.9/(1+0.2*AW15/$D$72))) | AZ15: =MIN(AY15*AW15,$D$68) | BA15: =MAX(0,AY15*AX15) | BB15: =IF(BC15>0,-BA15/BC15,-1E+9) | BC15: =AY15*AW15
B16: Recubrimiento libre | C16: r | D16: 4 | E16: cm | F16: E.060 7.7.1: columnas 4 cm | AD16: 9 | AE16: =IF(9<=$D$19,$D$61+($D$15-2*$D$61)*(9-1)/($D$19-1),0) | AF16: =IF(9<=$D$19,IF(OR(9=1,9=$D$19),$D$18,2)*$D$53,0) | AG16: =IF(9<=$D$18,$D$61+($D$14-2*$D$61)*(9-1)/($D$18-1),0) | AH16: =IF(9<=$D$18,IF(OR(9=1,9=$D$18),$D$19,2)*$D$53,0) | AK16: =0.16*$D$15 | AL16: =MIN($D$66*AK16,$D$15) | AM16: =(0.85*$D$11*AL16*$D$14+SUMPRODUCT($AF$8:$AF$17,(ABS(6000*(1-$AE$8:$AE$17/AK16)+$D$12)-ABS(6000*(1-$AE$8:$AE$17/AK16)-$D$12))/2-0.85*$D$11*($AE$8:$AE$17<AL16)))/1000 | AN16: =(0.85*$D$11*AL16*$D$14*($D$15/2-AL16/2)+SUMPRODUCT($AF$8:$AF$17,(ABS(6000*(1-$AE$8:$AE$17/AK16)+$D$12)-ABS(6000*(1-$AE$8:$AE$17/AK16)-$D$12))/2-0.85*$D$11*($AE$8:$AE$17<AL16),$D$15/2-$AE$8:$AE$17))/100000 | AO16: =IF(AM16<=0,0.9,MAX(0.7,0.9/(1+0.2*AM16/$D$71))) | AP16: =MIN(AO16*AM16,$D$68) | AQ16: =MAX(0,AO16*AN16) | AR16: =IF(AS16>0,-AQ16/AS16,-1E+9) | AS16: =AO16*AM16 | AU16: =0.16*$D$14 | AV16: =MIN($D$66*AU16,$D$14) | AW16: =(0.85*$D$11*AV16*$D$15+SUMPRODUCT($AH$8:$AH$17,(ABS(6000*(1-$AG$8:$AG$17/AU16)+$D$12)-ABS(6000*(1-$AG$8:$AG$17/AU16)-$D$12))/2-0.85*$D$11*($AG$8:$AG$17<AV16)))/1000 | AX16: =(0.85*$D$11*AV16*$D$15*($D$14/2-AV16/2)+SUMPRODUCT($AH$8:$AH$17,(ABS(6000*(1-$AG$8:$AG$17/AU16)+$D$12)-ABS(6000*(1-$AG$8:$AG$17/AU16)-$D$12))/2-0.85*$D$11*($AG$8:$AG$17<AV16),$D$14/2-$AG$8:$AG$17))/100000 | AY16: =IF(AW16<=0,0.9,MAX(0.7,0.9/(1+0.2*AW16/$D$72))) | AZ16: =MIN(AY16*AW16,$D$68) | BA16: =MAX(0,AY16*AX16) | BB16: =IF(BC16>0,-BA16/BC16,-1E+9) | BC16: =AY16*AW16
B17: Varilla longitudinal | C17: Ø | D17: 5/8" | AD17: 10 | AE17: =IF(10<=$D$19,$D$61+($D$15-2*$D$61)*(10-1)/($D$19-1),0) | AF17: =IF(10<=$D$19,IF(OR(10=1,10=$D$19),$D$18,2)*$D$53,0) | AG17: =IF(10<=$D$18,$D$61+($D$14-2*$D$61)*(10-1)/($D$18-1),0) | AH17: =IF(10<=$D$18,IF(OR(10=1,10=$D$18),$D$19,2)*$D$53,0) | AK17: =0.2*$D$15 | AL17: =MIN($D$66*AK17,$D$15) | AM17: =(0.85*$D$11*AL17*$D$14+SUMPRODUCT($AF$8:$AF$17,(ABS(6000*(1-$AE$8:$AE$17/AK17)+$D$12)-ABS(6000*(1-$AE$8:$AE$17/AK17)-$D$12))/2-0.85*$D$11*($AE$8:$AE$17<AL17)))/1000 | AN17: =(0.85*$D$11*AL17*$D$14*($D$15/2-AL17/2)+SUMPRODUCT($AF$8:$AF$17,(ABS(6000*(1-$AE$8:$AE$17/AK17)+$D$12)-ABS(6000*(1-$AE$8:$AE$17/AK17)-$D$12))/2-0.85*$D$11*($AE$8:$AE$17<AL17),$D$15/2-$AE$8:$AE$17))/100000 | AO17: =IF(AM17<=0,0.9,MAX(0.7,0.9/(1+0.2*AM17/$D$71))) | AP17: =MIN(AO17*AM17,$D$68) | AQ17: =MAX(0,AO17*AN17) | AR17: =IF(AS17>0,-AQ17/AS17,-1E+9) | AS17: =AO17*AM17 | AU17: =0.2*$D$14 | AV17: =MIN($D$66*AU17,$D$14) | AW17: =(0.85*$D$11*AV17*$D$15+SUMPRODUCT($AH$8:$AH$17,(ABS(6000*(1-$AG$8:$AG$17/AU17)+$D$12)-ABS(6000*(1-$AG$8:$AG$17/AU17)-$D$12))/2-0.85*$D$11*($AG$8:$AG$17<AV17)))/1000 | AX17: =(0.85*$D$11*AV17*$D$15*($D$14/2-AV17/2)+SUMPRODUCT($AH$8:$AH$17,(ABS(6000*(1-$AG$8:$AG$17/AU17)+$D$12)-ABS(6000*(1-$AG$8:$AG$17/AU17)-$D$12))/2-0.85*$D$11*($AG$8:$AG$17<AV17),$D$14/2-$AG$8:$AG$17))/100000 | AY17: =IF(AW17<=0,0.9,MAX(0.7,0.9/(1+0.2*AW17/$D$72))) | AZ17: =MIN(AY17*AW17,$D$68) | BA17: =MAX(0,AY17*AX17) | BB17: =IF(BC17>0,-BA17/BC17,-1E+9) | BC17: =AY17*AW17
B18: Varillas por cara paralela a X (incluye esquinas) | C18: nx | D18: 3 | F18: Cara de longitud B | AK18: =0.25*$D$15 | AL18: =MIN($D$66*AK18,$D$15) | AM18: =(0.85*$D$11*AL18*$D$14+SUMPRODUCT($AF$8:$AF$17,(ABS(6000*(1-$AE$8:$AE$17/AK18)+$D$12)-ABS(6000*(1-$AE$8:$AE$17/AK18)-$D$12))/2-0.85*$D$11*($AE$8:$AE$17<AL18)))/1000 | AN18: =(0.85*$D$11*AL18*$D$14*($D$15/2-AL18/2)+SUMPRODUCT($AF$8:$AF$17,(ABS(6000*(1-$AE$8:$AE$17/AK18)+$D$12)-ABS(6000*(1-$AE$8:$AE$17/AK18)-$D$12))/2-0.85*$D$11*($AE$8:$AE$17<AL18),$D$15/2-$AE$8:$AE$17))/100000 | AO18: =IF(AM18<=0,0.9,MAX(0.7,0.9/(1+0.2*AM18/$D$71))) | AP18: =MIN(AO18*AM18,$D$68) | AQ18: =MAX(0,AO18*AN18) | AR18: =IF(AS18>0,-AQ18/AS18,-1E+9) | AS18: =AO18*AM18 | AU18: =0.25*$D$14 | AV18: =MIN($D$66*AU18,$D$14) | AW18: =(0.85*$D$11*AV18*$D$15+SUMPRODUCT($AH$8:$AH$17,(ABS(6000*(1-$AG$8:$AG$17/AU18)+$D$12)-ABS(6000*(1-$AG$8:$AG$17/AU18)-$D$12))/2-0.85*$D$11*($AG$8:$AG$17<AV18)))/1000 | AX18: =(0.85*$D$11*AV18*$D$15*($D$14/2-AV18/2)+SUMPRODUCT($AH$8:$AH$17,(ABS(6000*(1-$AG$8:$AG$17/AU18)+$D$12)-ABS(6000*(1-$AG$8:$AG$17/AU18)-$D$12))/2-0.85*$D$11*($AG$8:$AG$17<AV18),$D$14/2-$AG$8:$AG$17))/100000 | AY18: =IF(AW18<=0,0.9,MAX(0.7,0.9/(1+0.2*AW18/$D$72))) | AZ18: =MIN(AY18*AW18,$D$68) | BA18: =MAX(0,AY18*AX18) | BB18: =IF(BC18>0,-BA18/BC18,-1E+9) | BC18: =AY18*AW18
B19: Varillas por cara paralela a Y (incluye esquinas) | C19: ny | D19: 4 | F19: Cara de longitud H | AK19: =0.3*$D$15 | AL19: =MIN($D$66*AK19,$D$15) | AM19: =(0.85*$D$11*AL19*$D$14+SUMPRODUCT($AF$8:$AF$17,(ABS(6000*(1-$AE$8:$AE$17/AK19)+$D$12)-ABS(6000*(1-$AE$8:$AE$17/AK19)-$D$12))/2-0.85*$D$11*($AE$8:$AE$17<AL19)))/1000 | AN19: =(0.85*$D$11*AL19*$D$14*($D$15/2-AL19/2)+SUMPRODUCT($AF$8:$AF$17,(ABS(6000*(1-$AE$8:$AE$17/AK19)+$D$12)-ABS(6000*(1-$AE$8:$AE$17/AK19)-$D$12))/2-0.85*$D$11*($AE$8:$AE$17<AL19),$D$15/2-$AE$8:$AE$17))/100000 | AO19: =IF(AM19<=0,0.9,MAX(0.7,0.9/(1+0.2*AM19/$D$71))) | AP19: =MIN(AO19*AM19,$D$68) | AQ19: =MAX(0,AO19*AN19) | AR19: =IF(AS19>0,-AQ19/AS19,-1E+9) | AS19: =AO19*AM19 | AU19: =0.3*$D$14 | AV19: =MIN($D$66*AU19,$D$14) | AW19: =(0.85*$D$11*AV19*$D$15+SUMPRODUCT($AH$8:$AH$17,(ABS(6000*(1-$AG$8:$AG$17/AU19)+$D$12)-ABS(6000*(1-$AG$8:$AG$17/AU19)-$D$12))/2-0.85*$D$11*($AG$8:$AG$17<AV19)))/1000 | AX19: =(0.85*$D$11*AV19*$D$15*($D$14/2-AV19/2)+SUMPRODUCT($AH$8:$AH$17,(ABS(6000*(1-$AG$8:$AG$17/AU19)+$D$12)-ABS(6000*(1-$AG$8:$AG$17/AU19)-$D$12))/2-0.85*$D$11*($AG$8:$AG$17<AV19),$D$14/2-$AG$8:$AG$17))/100000 | AY19: =IF(AW19<=0,0.9,MAX(0.7,0.9/(1+0.2*AW19/$D$72))) | AZ19: =MIN(AY19*AW19,$D$68) | BA19: =MAX(0,AY19*AX19) | BB19: =IF(BC19>0,-BA19/BC19,-1E+9) | BC19: =AY19*AW19
B20: Varilla del estribo | C20: Øe | D20: 3/8" | AK20: =0.35*$D$15 | AL20: =MIN($D$66*AK20,$D$15) | AM20: =(0.85*$D$11*AL20*$D$14+SUMPRODUCT($AF$8:$AF$17,(ABS(6000*(1-$AE$8:$AE$17/AK20)+$D$12)-ABS(6000*(1-$AE$8:$AE$17/AK20)-$D$12))/2-0.85*$D$11*($AE$8:$AE$17<AL20)))/1000 | AN20: =(0.85*$D$11*AL20*$D$14*($D$15/2-AL20/2)+SUMPRODUCT($AF$8:$AF$17,(ABS(6000*(1-$AE$8:$AE$17/AK20)+$D$12)-ABS(6000*(1-$AE$8:$AE$17/AK20)-$D$12))/2-0.85*$D$11*($AE$8:$AE$17<AL20),$D$15/2-$AE$8:$AE$17))/100000 | AO20: =IF(AM20<=0,0.9,MAX(0.7,0.9/(1+0.2*AM20/$D$71))) | AP20: =MIN(AO20*AM20,$D$68) | AQ20: =MAX(0,AO20*AN20) | AR20: =IF(AS20>0,-AQ20/AS20,-1E+9) | AS20: =AO20*AM20 | AU20: =0.35*$D$14 | AV20: =MIN($D$66*AU20,$D$14) | AW20: =(0.85*$D$11*AV20*$D$15+SUMPRODUCT($AH$8:$AH$17,(ABS(6000*(1-$AG$8:$AG$17/AU20)+$D$12)-ABS(6000*(1-$AG$8:$AG$17/AU20)-$D$12))/2-0.85*$D$11*($AG$8:$AG$17<AV20)))/1000 | AX20: =(0.85*$D$11*AV20*$D$15*($D$14/2-AV20/2)+SUMPRODUCT($AH$8:$AH$17,(ABS(6000*(1-$AG$8:$AG$17/AU20)+$D$12)-ABS(6000*(1-$AG$8:$AG$17/AU20)-$D$12))/2-0.85*$D$11*($AG$8:$AG$17<AV20),$D$14/2-$AG$8:$AG$17))/100000 | AY20: =IF(AW20<=0,0.9,MAX(0.7,0.9/(1+0.2*AW20/$D$72))) | AZ20: =MIN(AY20*AW20,$D$68) | BA20: =MAX(0,AY20*AX20) | BB20: =IF(BC20>0,-BA20/BC20,-1E+9) | BC20: =AY20*AW20
B21: Ramas paralelas a H (resisten cortante en Y) | C21: nY | D21: 2 | AK21: =0.375*$D$15 | AL21: =MIN($D$66*AK21,$D$15) | AM21: =(0.85*$D$11*AL21*$D$14+SUMPRODUCT($AF$8:$AF$17,(ABS(6000*(1-$AE$8:$AE$17/AK21)+$D$12)-ABS(6000*(1-$AE$8:$AE$17/AK21)-$D$12))/2-0.85*$D$11*($AE$8:$AE$17<AL21)))/1000 | AN21: =(0.85*$D$11*AL21*$D$14*($D$15/2-AL21/2)+SUMPRODUCT($AF$8:$AF$17,(ABS(6000*(1-$AE$8:$AE$17/AK21)+$D$12)-ABS(6000*(1-$AE$8:$AE$17/AK21)-$D$12))/2-0.85*$D$11*($AE$8:$AE$17<AL21),$D$15/2-$AE$8:$AE$17))/100000 | AO21: =IF(AM21<=0,0.9,MAX(0.7,0.9/(1+0.2*AM21/$D$71))) | AP21: =MIN(AO21*AM21,$D$68) | AQ21: =MAX(0,AO21*AN21) | AR21: =IF(AS21>0,-AQ21/AS21,-1E+9) | AS21: =AO21*AM21 | AU21: =0.375*$D$14 | AV21: =MIN($D$66*AU21,$D$14) | AW21: =(0.85*$D$11*AV21*$D$15+SUMPRODUCT($AH$8:$AH$17,(ABS(6000*(1-$AG$8:$AG$17/AU21)+$D$12)-ABS(6000*(1-$AG$8:$AG$17/AU21)-$D$12))/2-0.85*$D$11*($AG$8:$AG$17<AV21)))/1000 | AX21: =(0.85*$D$11*AV21*$D$15*($D$14/2-AV21/2)+SUMPRODUCT($AH$8:$AH$17,(ABS(6000*(1-$AG$8:$AG$17/AU21)+$D$12)-ABS(6000*(1-$AG$8:$AG$17/AU21)-$D$12))/2-0.85*$D$11*($AG$8:$AG$17<AV21),$D$14/2-$AG$8:$AG$17))/100000 | AY21: =IF(AW21<=0,0.9,MAX(0.7,0.9/(1+0.2*AW21/$D$72))) | AZ21: =MIN(AY21*AW21,$D$68) | BA21: =MAX(0,AY21*AX21) | BB21: =IF(BC21>0,-BA21/BC21,-1E+9) | BC21: =AY21*AW21
B22: Ramas paralelas a B (resisten cortante en X) | C22: nX | D22: 3 | F22: Incluye grapas | AK22: =0.4*$D$15 | AL22: =MIN($D$66*AK22,$D$15) | AM22: =(0.85*$D$11*AL22*$D$14+SUMPRODUCT($AF$8:$AF$17,(ABS(6000*(1-$AE$8:$AE$17/AK22)+$D$12)-ABS(6000*(1-$AE$8:$AE$17/AK22)-$D$12))/2-0.85*$D$11*($AE$8:$AE$17<AL22)))/1000 | AN22: =(0.85*$D$11*AL22*$D$14*($D$15/2-AL22/2)+SUMPRODUCT($AF$8:$AF$17,(ABS(6000*(1-$AE$8:$AE$17/AK22)+$D$12)-ABS(6000*(1-$AE$8:$AE$17/AK22)-$D$12))/2-0.85*$D$11*($AE$8:$AE$17<AL22),$D$15/2-$AE$8:$AE$17))/100000 | AO22: =IF(AM22<=0,0.9,MAX(0.7,0.9/(1+0.2*AM22/$D$71))) | AP22: =MIN(AO22*AM22,$D$68) | AQ22: =MAX(0,AO22*AN22) | AR22: =IF(AS22>0,-AQ22/AS22,-1E+9) | AS22: =AO22*AM22 | AU22: =0.4*$D$14 | AV22: =MIN($D$66*AU22,$D$14) | AW22: =(0.85*$D$11*AV22*$D$15+SUMPRODUCT($AH$8:$AH$17,(ABS(6000*(1-$AG$8:$AG$17/AU22)+$D$12)-ABS(6000*(1-$AG$8:$AG$17/AU22)-$D$12))/2-0.85*$D$11*($AG$8:$AG$17<AV22)))/1000 | AX22: =(0.85*$D$11*AV22*$D$15*($D$14/2-AV22/2)+SUMPRODUCT($AH$8:$AH$17,(ABS(6000*(1-$AG$8:$AG$17/AU22)+$D$12)-ABS(6000*(1-$AG$8:$AG$17/AU22)-$D$12))/2-0.85*$D$11*($AG$8:$AG$17<AV22),$D$14/2-$AG$8:$AG$17))/100000 | AY22: =IF(AW22<=0,0.9,MAX(0.7,0.9/(1+0.2*AW22/$D$72))) | AZ22: =MIN(AY22*AW22,$D$68) | BA22: =MAX(0,AY22*AX22) | BB22: =IF(BC22>0,-BA22/BC22,-1E+9) | BC22: =AY22*AW22
B23: Longitudes y esbeltez | AK23: =0.425*$D$15 | AL23: =MIN($D$66*AK23,$D$15) | AM23: =(0.85*$D$11*AL23*$D$14+SUMPRODUCT($AF$8:$AF$17,(ABS(6000*(1-$AE$8:$AE$17/AK23)+$D$12)-ABS(6000*(1-$AE$8:$AE$17/AK23)-$D$12))/2-0.85*$D$11*($AE$8:$AE$17<AL23)))/1000 | AN23: =(0.85*$D$11*AL23*$D$14*($D$15/2-AL23/2)+SUMPRODUCT($AF$8:$AF$17,(ABS(6000*(1-$AE$8:$AE$17/AK23)+$D$12)-ABS(6000*(1-$AE$8:$AE$17/AK23)-$D$12))/2-0.85*$D$11*($AE$8:$AE$17<AL23),$D$15/2-$AE$8:$AE$17))/100000 | AO23: =IF(AM23<=0,0.9,MAX(0.7,0.9/(1+0.2*AM23/$D$71))) | AP23: =MIN(AO23*AM23,$D$68) | AQ23: =MAX(0,AO23*AN23) | AR23: =IF(AS23>0,-AQ23/AS23,-1E+9) | AS23: =AO23*AM23 | AU23: =0.425*$D$14 | AV23: =MIN($D$66*AU23,$D$14) | AW23: =(0.85*$D$11*AV23*$D$15+SUMPRODUCT($AH$8:$AH$17,(ABS(6000*(1-$AG$8:$AG$17/AU23)+$D$12)-ABS(6000*(1-$AG$8:$AG$17/AU23)-$D$12))/2-0.85*$D$11*($AG$8:$AG$17<AV23)))/1000 | AX23: =(0.85*$D$11*AV23*$D$15*($D$14/2-AV23/2)+SUMPRODUCT($AH$8:$AH$17,(ABS(6000*(1-$AG$8:$AG$17/AU23)+$D$12)-ABS(6000*(1-$AG$8:$AG$17/AU23)-$D$12))/2-0.85*$D$11*($AG$8:$AG$17<AV23),$D$14/2-$AG$8:$AG$17))/100000 | AY23: =IF(AW23<=0,0.9,MAX(0.7,0.9/(1+0.2*AW23/$D$72))) | AZ23: =MIN(AY23*AW23,$D$68) | BA23: =MAX(0,AY23*AX23) | BB23: =IF(BC23>0,-BA23/BC23,-1E+9) | BC23: =AY23*AW23
B24: Luz libre de la columna | C24: hn | D24: 2.6 | E24: m | AK24: =0.45*$D$15 | AL24: =MIN($D$66*AK24,$D$15) | AM24: =(0.85*$D$11*AL24*$D$14+SUMPRODUCT($AF$8:$AF$17,(ABS(6000*(1-$AE$8:$AE$17/AK24)+$D$12)-ABS(6000*(1-$AE$8:$AE$17/AK24)-$D$12))/2-0.85*$D$11*($AE$8:$AE$17<AL24)))/1000 | AN24: =(0.85*$D$11*AL24*$D$14*($D$15/2-AL24/2)+SUMPRODUCT($AF$8:$AF$17,(ABS(6000*(1-$AE$8:$AE$17/AK24)+$D$12)-ABS(6000*(1-$AE$8:$AE$17/AK24)-$D$12))/2-0.85*$D$11*($AE$8:$AE$17<AL24),$D$15/2-$AE$8:$AE$17))/100000 | AO24: =IF(AM24<=0,0.9,MAX(0.7,0.9/(1+0.2*AM24/$D$71))) | AP24: =MIN(AO24*AM24,$D$68) | AQ24: =MAX(0,AO24*AN24) | AR24: =IF(AS24>0,-AQ24/AS24,-1E+9) | AS24: =AO24*AM24 | AU24: =0.45*$D$14 | AV24: =MIN($D$66*AU24,$D$14) | AW24: =(0.85*$D$11*AV24*$D$15+SUMPRODUCT($AH$8:$AH$17,(ABS(6000*(1-$AG$8:$AG$17/AU24)+$D$12)-ABS(6000*(1-$AG$8:$AG$17/AU24)-$D$12))/2-0.85*$D$11*($AG$8:$AG$17<AV24)))/1000 | AX24: =(0.85*$D$11*AV24*$D$15*($D$14/2-AV24/2)+SUMPRODUCT($AH$8:$AH$17,(ABS(6000*(1-$AG$8:$AG$17/AU24)+$D$12)-ABS(6000*(1-$AG$8:$AG$17/AU24)-$D$12))/2-0.85*$D$11*($AG$8:$AG$17<AV24),$D$14/2-$AG$8:$AG$17))/100000 | AY24: =IF(AW24<=0,0.9,MAX(0.7,0.9/(1+0.2*AW24/$D$72))) | AZ24: =MIN(AY24*AW24,$D$68) | BA24: =MAX(0,AY24*AX24) | BB24: =IF(BC24>0,-BA24/BC24,-1E+9) | BC24: =AY24*AW24
B25: Factor de longitud efectiva | C25: k | D25: 1 | F25: E.060 10.12.1: k = 1.0 si es arriostrada | AK25: =0.475*$D$15 | AL25: =MIN($D$66*AK25,$D$15) | AM25: =(0.85*$D$11*AL25*$D$14+SUMPRODUCT($AF$8:$AF$17,(ABS(6000*(1-$AE$8:$AE$17/AK25)+$D$12)-ABS(6000*(1-$AE$8:$AE$17/AK25)-$D$12))/2-0.85*$D$11*($AE$8:$AE$17<AL25)))/1000 | AN25: =(0.85*$D$11*AL25*$D$14*($D$15/2-AL25/2)+SUMPRODUCT($AF$8:$AF$17,(ABS(6000*(1-$AE$8:$AE$17/AK25)+$D$12)-ABS(6000*(1-$AE$8:$AE$17/AK25)-$D$12))/2-0.85*$D$11*($AE$8:$AE$17<AL25),$D$15/2-$AE$8:$AE$17))/100000 | AO25: =IF(AM25<=0,0.9,MAX(0.7,0.9/(1+0.2*AM25/$D$71))) | AP25: =MIN(AO25*AM25,$D$68) | AQ25: =MAX(0,AO25*AN25) | AR25: =IF(AS25>0,-AQ25/AS25,-1E+9) | AS25: =AO25*AM25 | AU25: =0.475*$D$14 | AV25: =MIN($D$66*AU25,$D$14) | AW25: =(0.85*$D$11*AV25*$D$15+SUMPRODUCT($AH$8:$AH$17,(ABS(6000*(1-$AG$8:$AG$17/AU25)+$D$12)-ABS(6000*(1-$AG$8:$AG$17/AU25)-$D$12))/2-0.85*$D$11*($AG$8:$AG$17<AV25)))/1000 | AX25: =(0.85*$D$11*AV25*$D$15*($D$14/2-AV25/2)+SUMPRODUCT($AH$8:$AH$17,(ABS(6000*(1-$AG$8:$AG$17/AU25)+$D$12)-ABS(6000*(1-$AG$8:$AG$17/AU25)-$D$12))/2-0.85*$D$11*($AG$8:$AG$17<AV25),$D$14/2-$AG$8:$AG$17))/100000 | AY25: =IF(AW25<=0,0.9,MAX(0.7,0.9/(1+0.2*AW25/$D$72))) | AZ25: =MIN(AY25*AW25,$D$68) | BA25: =MAX(0,AY25*AX25) | BB25: =IF(BC25>0,-BA25/BC25,-1E+9) | BC25: =AY25*AW25
B26: ¿Entrepiso arriostrado? (Q ≤ 0.06) | D26: Sí | F26: 10.11.4.2 | AK26: =0.5*$D$15 | AL26: =MIN($D$66*AK26,$D$15) | AM26: =(0.85*$D$11*AL26*$D$14+SUMPRODUCT($AF$8:$AF$17,(ABS(6000*(1-$AE$8:$AE$17/AK26)+$D$12)-ABS(6000*(1-$AE$8:$AE$17/AK26)-$D$12))/2-0.85*$D$11*($AE$8:$AE$17<AL26)))/1000 | AN26: =(0.85*$D$11*AL26*$D$14*($D$15/2-AL26/2)+SUMPRODUCT($AF$8:$AF$17,(ABS(6000*(1-$AE$8:$AE$17/AK26)+$D$12)-ABS(6000*(1-$AE$8:$AE$17/AK26)-$D$12))/2-0.85*$D$11*($AE$8:$AE$17<AL26),$D$15/2-$AE$8:$AE$17))/100000 | AO26: =IF(AM26<=0,0.9,MAX(0.7,0.9/(1+0.2*AM26/$D$71))) | AP26: =MIN(AO26*AM26,$D$68) | AQ26: =MAX(0,AO26*AN26) | AR26: =IF(AS26>0,-AQ26/AS26,-1E+9) | AS26: =AO26*AM26 | AU26: =0.5*$D$14 | AV26: =MIN($D$66*AU26,$D$14) | AW26: =(0.85*$D$11*AV26*$D$15+SUMPRODUCT($AH$8:$AH$17,(ABS(6000*(1-$AG$8:$AG$17/AU26)+$D$12)-ABS(6000*(1-$AG$8:$AG$17/AU26)-$D$12))/2-0.85*$D$11*($AG$8:$AG$17<AV26)))/1000 | AX26: =(0.85*$D$11*AV26*$D$15*($D$14/2-AV26/2)+SUMPRODUCT($AH$8:$AH$17,(ABS(6000*(1-$AG$8:$AG$17/AU26)+$D$12)-ABS(6000*(1-$AG$8:$AG$17/AU26)-$D$12))/2-0.85*$D$11*($AG$8:$AG$17<AV26),$D$14/2-$AG$8:$AG$17))/100000 | AY26: =IF(AW26<=0,0.9,MAX(0.7,0.9/(1+0.2*AW26/$D$72))) | AZ26: =MIN(AY26*AW26,$D$68) | BA26: =MAX(0,AY26*AX26) | BB26: =IF(BC26>0,-BA26/BC26,-1E+9) | BC26: =AY26*AW26
B27: Relación M1/M2 (+ curvatura simple, − doble) | C27: M1/M2 | D27: -0.5 | AK27: =0.525*$D$15 | AL27: =MIN($D$66*AK27,$D$15) | AM27: =(0.85*$D$11*AL27*$D$14+SUMPRODUCT($AF$8:$AF$17,(ABS(6000*(1-$AE$8:$AE$17/AK27)+$D$12)-ABS(6000*(1-$AE$8:$AE$17/AK27)-$D$12))/2-0.85*$D$11*($AE$8:$AE$17<AL27)))/1000 | AN27: =(0.85*$D$11*AL27*$D$14*($D$15/2-AL27/2)+SUMPRODUCT($AF$8:$AF$17,(ABS(6000*(1-$AE$8:$AE$17/AK27)+$D$12)-ABS(6000*(1-$AE$8:$AE$17/AK27)-$D$12))/2-0.85*$D$11*($AE$8:$AE$17<AL27),$D$15/2-$AE$8:$AE$17))/100000 | AO27: =IF(AM27<=0,0.9,MAX(0.7,0.9/(1+0.2*AM27/$D$71))) | AP27: =MIN(AO27*AM27,$D$68) | AQ27: =MAX(0,AO27*AN27) | AR27: =IF(AS27>0,-AQ27/AS27,-1E+9) | AS27: =AO27*AM27 | AU27: =0.525*$D$14 | AV27: =MIN($D$66*AU27,$D$14) | AW27: =(0.85*$D$11*AV27*$D$15+SUMPRODUCT($AH$8:$AH$17,(ABS(6000*(1-$AG$8:$AG$17/AU27)+$D$12)-ABS(6000*(1-$AG$8:$AG$17/AU27)-$D$12))/2-0.85*$D$11*($AG$8:$AG$17<AV27)))/1000 | AX27: =(0.85*$D$11*AV27*$D$15*($D$14/2-AV27/2)+SUMPRODUCT($AH$8:$AH$17,(ABS(6000*(1-$AG$8:$AG$17/AU27)+$D$12)-ABS(6000*(1-$AG$8:$AG$17/AU27)-$D$12))/2-0.85*$D$11*($AG$8:$AG$17<AV27),$D$14/2-$AG$8:$AG$17))/100000 | AY27: =IF(AW27<=0,0.9,MAX(0.7,0.9/(1+0.2*AW27/$D$72))) | AZ27: =MIN(AY27*AW27,$D$68) | BA27: =MAX(0,AY27*AX27) | BB27: =IF(BC27>0,-BA27/BC27,-1E+9) | BC27: =AY27*AW27
B28: Factor de carga sostenida βd | C28: βd | D28: 0.6 | F28: CM amplificada / carga axial amplificada total | AK28: =0.55*$D$15 | AL28: =MIN($D$66*AK28,$D$15) | AM28: =(0.85*$D$11*AL28*$D$14+SUMPRODUCT($AF$8:$AF$17,(ABS(6000*(1-$AE$8:$AE$17/AK28)+$D$12)-ABS(6000*(1-$AE$8:$AE$17/AK28)-$D$12))/2-0.85*$D$11*($AE$8:$AE$17<AL28)))/1000 | AN28: =(0.85*$D$11*AL28*$D$14*($D$15/2-AL28/2)+SUMPRODUCT($AF$8:$AF$17,(ABS(6000*(1-$AE$8:$AE$17/AK28)+$D$12)-ABS(6000*(1-$AE$8:$AE$17/AK28)-$D$12))/2-0.85*$D$11*($AE$8:$AE$17<AL28),$D$15/2-$AE$8:$AE$17))/100000 | AO28: =IF(AM28<=0,0.9,MAX(0.7,0.9/(1+0.2*AM28/$D$71))) | AP28: =MIN(AO28*AM28,$D$68) | AQ28: =MAX(0,AO28*AN28) | AR28: =IF(AS28>0,-AQ28/AS28,-1E+9) | AS28: =AO28*AM28 | AU28: =0.55*$D$14 | AV28: =MIN($D$66*AU28,$D$14) | AW28: =(0.85*$D$11*AV28*$D$15+SUMPRODUCT($AH$8:$AH$17,(ABS(6000*(1-$AG$8:$AG$17/AU28)+$D$12)-ABS(6000*(1-$AG$8:$AG$17/AU28)-$D$12))/2-0.85*$D$11*($AG$8:$AG$17<AV28)))/1000 | AX28: =(0.85*$D$11*AV28*$D$15*($D$14/2-AV28/2)+SUMPRODUCT($AH$8:$AH$17,(ABS(6000*(1-$AG$8:$AG$17/AU28)+$D$12)-ABS(6000*(1-$AG$8:$AG$17/AU28)-$D$12))/2-0.85*$D$11*($AG$8:$AG$17<AV28),$D$14/2-$AG$8:$AG$17))/100000 | AY28: =IF(AW28<=0,0.9,MAX(0.7,0.9/(1+0.2*AW28/$D$72))) | AZ28: =MIN(AY28*AW28,$D$68) | BA28: =MAX(0,AY28*AX28) | BB28: =IF(BC28>0,-BA28/BC28,-1E+9) | BC28: =AY28*AW28
B29: Índice de estabilidad Q (no arriostrado) | C29: Q | D29: 0.04 | F29: De ETABS: ΣPu·Δo/(Vus·he); Δo × 0.75R | AK29: =0.575*$D$15 | AL29: =MIN($D$66*AK29,$D$15) | AM29: =(0.85*$D$11*AL29*$D$14+SUMPRODUCT($AF$8:$AF$17,(ABS(6000*(1-$AE$8:$AE$17/AK29)+$D$12)-ABS(6000*(1-$AE$8:$AE$17/AK29)-$D$12))/2-0.85*$D$11*($AE$8:$AE$17<AL29)))/1000 | AN29: =(0.85*$D$11*AL29*$D$14*($D$15/2-AL29/2)+SUMPRODUCT($AF$8:$AF$17,(ABS(6000*(1-$AE$8:$AE$17/AK29)+$D$12)-ABS(6000*(1-$AE$8:$AE$17/AK29)-$D$12))/2-0.85*$D$11*($AE$8:$AE$17<AL29),$D$15/2-$AE$8:$AE$17))/100000 | AO29: =IF(AM29<=0,0.9,MAX(0.7,0.9/(1+0.2*AM29/$D$71))) | AP29: =MIN(AO29*AM29,$D$68) | AQ29: =MAX(0,AO29*AN29) | AR29: =IF(AS29>0,-AQ29/AS29,-1E+9) | AS29: =AO29*AM29 | AU29: =0.575*$D$14 | AV29: =MIN($D$66*AU29,$D$14) | AW29: =(0.85*$D$11*AV29*$D$15+SUMPRODUCT($AH$8:$AH$17,(ABS(6000*(1-$AG$8:$AG$17/AU29)+$D$12)-ABS(6000*(1-$AG$8:$AG$17/AU29)-$D$12))/2-0.85*$D$11*($AG$8:$AG$17<AV29)))/1000 | AX29: =(0.85*$D$11*AV29*$D$15*($D$14/2-AV29/2)+SUMPRODUCT($AH$8:$AH$17,(ABS(6000*(1-$AG$8:$AG$17/AU29)+$D$12)-ABS(6000*(1-$AG$8:$AG$17/AU29)-$D$12))/2-0.85*$D$11*($AG$8:$AG$17<AV29),$D$14/2-$AG$8:$AG$17))/100000 | AY29: =IF(AW29<=0,0.9,MAX(0.7,0.9/(1+0.2*AW29/$D$72))) | AZ29: =MIN(AY29*AW29,$D$68) | BA29: =MAX(0,AY29*AX29) | BB29: =IF(BC29>0,-BA29/BC29,-1E+9) | BC29: =AY29*AW29
B30: Columna fuerte – viga débil (solo pórticos y dual tipo II, 21.6.2.2) | AK30: =0.6*$D$15 | AL30: =MIN($D$66*AK30,$D$15) | AM30: =(0.85*$D$11*AL30*$D$14+SUMPRODUCT($AF$8:$AF$17,(ABS(6000*(1-$AE$8:$AE$17/AK30)+$D$12)-ABS(6000*(1-$AE$8:$AE$17/AK30)-$D$12))/2-0.85*$D$11*($AE$8:$AE$17<AL30)))/1000 | AN30: =(0.85*$D$11*AL30*$D$14*($D$15/2-AL30/2)+SUMPRODUCT($AF$8:$AF$17,(ABS(6000*(1-$AE$8:$AE$17/AK30)+$D$12)-ABS(6000*(1-$AE$8:$AE$17/AK30)-$D$12))/2-0.85*$D$11*($AE$8:$AE$17<AL30),$D$15/2-$AE$8:$AE$17))/100000 | AO30: =IF(AM30<=0,0.9,MAX(0.7,0.9/(1+0.2*AM30/$D$71))) | AP30: =MIN(AO30*AM30,$D$68) | AQ30: =MAX(0,AO30*AN30) | AR30: =IF(AS30>0,-AQ30/AS30,-1E+9) | AS30: =AO30*AM30 | AU30: =0.6*$D$14 | AV30: =MIN($D$66*AU30,$D$14) | AW30: =(0.85*$D$11*AV30*$D$15+SUMPRODUCT($AH$8:$AH$17,(ABS(6000*(1-$AG$8:$AG$17/AU30)+$D$12)-ABS(6000*(1-$AG$8:$AG$17/AU30)-$D$12))/2-0.85*$D$11*($AG$8:$AG$17<AV30)))/1000 | AX30: =(0.85*$D$11*AV30*$D$15*($D$14/2-AV30/2)+SUMPRODUCT($AH$8:$AH$17,(ABS(6000*(1-$AG$8:$AG$17/AU30)+$D$12)-ABS(6000*(1-$AG$8:$AG$17/AU30)-$D$12))/2-0.85*$D$11*($AG$8:$AG$17<AV30),$D$14/2-$AG$8:$AG$17))/100000 | AY30: =IF(AW30<=0,0.9,MAX(0.7,0.9/(1+0.2*AW30/$D$72))) | AZ30: =MIN(AY30*AW30,$D$68) | BA30: =MAX(0,AY30*AX30) | BB30: =IF(BC30>0,-BA30/BC30,-1E+9) | BC30: =AY30*AW30
B31: Suma de Mn de las vigas que llegan al nudo, flexión en X | C31: ΣMnv | D31: 35 | E31: t·m | F31: Mn− de un lado + Mn+ del otro (hoja VIGA: φMn/0.9) | AK31: =0.625*$D$15 | AL31: =MIN($D$66*AK31,$D$15) | AM31: =(0.85*$D$11*AL31*$D$14+SUMPRODUCT($AF$8:$AF$17,(ABS(6000*(1-$AE$8:$AE$17/AK31)+$D$12)-ABS(6000*(1-$AE$8:$AE$17/AK31)-$D$12))/2-0.85*$D$11*($AE$8:$AE$17<AL31)))/1000 | AN31: =(0.85*$D$11*AL31*$D$14*($D$15/2-AL31/2)+SUMPRODUCT($AF$8:$AF$17,(ABS(6000*(1-$AE$8:$AE$17/AK31)+$D$12)-ABS(6000*(1-$AE$8:$AE$17/AK31)-$D$12))/2-0.85*$D$11*($AE$8:$AE$17<AL31),$D$15/2-$AE$8:$AE$17))/100000 | AO31: =IF(AM31<=0,0.9,MAX(0.7,0.9/(1+0.2*AM31/$D$71))) | AP31: =MIN(AO31*AM31,$D$68) | AQ31: =MAX(0,AO31*AN31) | AR31: =IF(AS31>0,-AQ31/AS31,-1E+9) | AS31: =AO31*AM31 | AU31: =0.625*$D$14 | AV31: =MIN($D$66*AU31,$D$14) | AW31: =(0.85*$D$11*AV31*$D$15+SUMPRODUCT($AH$8:$AH$17,(ABS(6000*(1-$AG$8:$AG$17/AU31)+$D$12)-ABS(6000*(1-$AG$8:$AG$17/AU31)-$D$12))/2-0.85*$D$11*($AG$8:$AG$17<AV31)))/1000 | AX31: =(0.85*$D$11*AV31*$D$15*($D$14/2-AV31/2)+SUMPRODUCT($AH$8:$AH$17,(ABS(6000*(1-$AG$8:$AG$17/AU31)+$D$12)-ABS(6000*(1-$AG$8:$AG$17/AU31)-$D$12))/2-0.85*$D$11*($AG$8:$AG$17<AV31),$D$14/2-$AG$8:$AG$17))/100000 | AY31: =IF(AW31<=0,0.9,MAX(0.7,0.9/(1+0.2*AW31/$D$72))) | AZ31: =MIN(AY31*AW31,$D$68) | BA31: =MAX(0,AY31*AX31) | BB31: =IF(BC31>0,-BA31/BC31,-1E+9) | BC31: =AY31*AW31
B32: Suma de Mn de las vigas que llegan al nudo, flexión en Y | C32: ΣMnv | D32: 20 | E32: t·m | AK32: =0.65*$D$15 | AL32: =MIN($D$66*AK32,$D$15) | AM32: =(0.85*$D$11*AL32*$D$14+SUMPRODUCT($AF$8:$AF$17,(ABS(6000*(1-$AE$8:$AE$17/AK32)+$D$12)-ABS(6000*(1-$AE$8:$AE$17/AK32)-$D$12))/2-0.85*$D$11*($AE$8:$AE$17<AL32)))/1000 | AN32: =(0.85*$D$11*AL32*$D$14*($D$15/2-AL32/2)+SUMPRODUCT($AF$8:$AF$17,(ABS(6000*(1-$AE$8:$AE$17/AK32)+$D$12)-ABS(6000*(1-$AE$8:$AE$17/AK32)-$D$12))/2-0.85*$D$11*($AE$8:$AE$17<AL32),$D$15/2-$AE$8:$AE$17))/100000 | AO32: =IF(AM32<=0,0.9,MAX(0.7,0.9/(1+0.2*AM32/$D$71))) | AP32: =MIN(AO32*AM32,$D$68) | AQ32: =MAX(0,AO32*AN32) | AR32: =IF(AS32>0,-AQ32/AS32,-1E+9) | AS32: =AO32*AM32 | AU32: =0.65*$D$14 | AV32: =MIN($D$66*AU32,$D$14) | AW32: =(0.85*$D$11*AV32*$D$15+SUMPRODUCT($AH$8:$AH$17,(ABS(6000*(1-$AG$8:$AG$17/AU32)+$D$12)-ABS(6000*(1-$AG$8:$AG$17/AU32)-$D$12))/2-0.85*$D$11*($AG$8:$AG$17<AV32)))/1000 | AX32: =(0.85*$D$11*AV32*$D$15*($D$14/2-AV32/2)+SUMPRODUCT($AH$8:$AH$17,(ABS(6000*(1-$AG$8:$AG$17/AU32)+$D$12)-ABS(6000*(1-$AG$8:$AG$17/AU32)-$D$12))/2-0.85*$D$11*($AG$8:$AG$17<AV32),$D$14/2-$AG$8:$AG$17))/100000 | AY32: =IF(AW32<=0,0.9,MAX(0.7,0.9/(1+0.2*AW32/$D$72))) | AZ32: =MIN(AY32*AW32,$D$68) | BA32: =MAX(0,AY32*AX32) | BB32: =IF(BC32>0,-BA32/BC32,-1E+9) | BC32: =AY32*AW32
B33: Cortantes del análisis (t) | AK33: =0.675*$D$15 | AL33: =MIN($D$66*AK33,$D$15) | AM33: =(0.85*$D$11*AL33*$D$14+SUMPRODUCT($AF$8:$AF$17,(ABS(6000*(1-$AE$8:$AE$17/AK33)+$D$12)-ABS(6000*(1-$AE$8:$AE$17/AK33)-$D$12))/2-0.85*$D$11*($AE$8:$AE$17<AL33)))/1000 | AN33: =(0.85*$D$11*AL33*$D$14*($D$15/2-AL33/2)+SUMPRODUCT($AF$8:$AF$17,(ABS(6000*(1-$AE$8:$AE$17/AK33)+$D$12)-ABS(6000*(1-$AE$8:$AE$17/AK33)-$D$12))/2-0.85*$D$11*($AE$8:$AE$17<AL33),$D$15/2-$AE$8:$AE$17))/100000 | AO33: =IF(AM33<=0,0.9,MAX(0.7,0.9/(1+0.2*AM33/$D$71))) | AP33: =MIN(AO33*AM33,$D$68) | AQ33: =MAX(0,AO33*AN33) | AR33: =IF(AS33>0,-AQ33/AS33,-1E+9) | AS33: =AO33*AM33 | AU33: =0.675*$D$14 | AV33: =MIN($D$66*AU33,$D$14) | AW33: =(0.85*$D$11*AV33*$D$15+SUMPRODUCT($AH$8:$AH$17,(ABS(6000*(1-$AG$8:$AG$17/AU33)+$D$12)-ABS(6000*(1-$AG$8:$AG$17/AU33)-$D$12))/2-0.85*$D$11*($AG$8:$AG$17<AV33)))/1000 | AX33: =(0.85*$D$11*AV33*$D$15*($D$14/2-AV33/2)+SUMPRODUCT($AH$8:$AH$17,(ABS(6000*(1-$AG$8:$AG$17/AU33)+$D$12)-ABS(6000*(1-$AG$8:$AG$17/AU33)-$D$12))/2-0.85*$D$11*($AG$8:$AG$17<AV33),$D$14/2-$AG$8:$AG$17))/100000 | AY33: =IF(AW33<=0,0.9,MAX(0.7,0.9/(1+0.2*AW33/$D$72))) | AZ33: =MIN(AY33*AW33,$D$68) | BA33: =MAX(0,AY33*AX33) | BB33: =IF(BC33>0,-BA33/BC33,-1E+9) | BC33: =AY33*AW33
B34: Cortante último en Y (máx. envolvente) | C34: VuY | D34: 6 | E34: t | F34: Asociado a Mux | AK34: =0.7*$D$15 | AL34: =MIN($D$66*AK34,$D$15) | AM34: =(0.85*$D$11*AL34*$D$14+SUMPRODUCT($AF$8:$AF$17,(ABS(6000*(1-$AE$8:$AE$17/AK34)+$D$12)-ABS(6000*(1-$AE$8:$AE$17/AK34)-$D$12))/2-0.85*$D$11*($AE$8:$AE$17<AL34)))/1000 | AN34: =(0.85*$D$11*AL34*$D$14*($D$15/2-AL34/2)+SUMPRODUCT($AF$8:$AF$17,(ABS(6000*(1-$AE$8:$AE$17/AK34)+$D$12)-ABS(6000*(1-$AE$8:$AE$17/AK34)-$D$12))/2-0.85*$D$11*($AE$8:$AE$17<AL34),$D$15/2-$AE$8:$AE$17))/100000 | AO34: =IF(AM34<=0,0.9,MAX(0.7,0.9/(1+0.2*AM34/$D$71))) | AP34: =MIN(AO34*AM34,$D$68) | AQ34: =MAX(0,AO34*AN34) | AR34: =IF(AS34>0,-AQ34/AS34,-1E+9) | AS34: =AO34*AM34 | AU34: =0.7*$D$14 | AV34: =MIN($D$66*AU34,$D$14) | AW34: =(0.85*$D$11*AV34*$D$15+SUMPRODUCT($AH$8:$AH$17,(ABS(6000*(1-$AG$8:$AG$17/AU34)+$D$12)-ABS(6000*(1-$AG$8:$AG$17/AU34)-$D$12))/2-0.85*$D$11*($AG$8:$AG$17<AV34)))/1000 | AX34: =(0.85*$D$11*AV34*$D$15*($D$14/2-AV34/2)+SUMPRODUCT($AH$8:$AH$17,(ABS(6000*(1-$AG$8:$AG$17/AU34)+$D$12)-ABS(6000*(1-$AG$8:$AG$17/AU34)-$D$12))/2-0.85*$D$11*($AG$8:$AG$17<AV34),$D$14/2-$AG$8:$AG$17))/100000 | AY34: =IF(AW34<=0,0.9,MAX(0.7,0.9/(1+0.2*AW34/$D$72))) | AZ34: =MIN(AY34*AW34,$D$68) | BA34: =MAX(0,AY34*AX34) | BB34: =IF(BC34>0,-BA34/BC34,-1E+9) | BC34: =AY34*AW34
B35: Cortante de sismo puro en Y | C35: VSY | D35: 3.5 | E35: t | AK35: =0.75*$D$15 | AL35: =MIN($D$66*AK35,$D$15) | AM35: =(0.85*$D$11*AL35*$D$14+SUMPRODUCT($AF$8:$AF$17,(ABS(6000*(1-$AE$8:$AE$17/AK35)+$D$12)-ABS(6000*(1-$AE$8:$AE$17/AK35)-$D$12))/2-0.85*$D$11*($AE$8:$AE$17<AL35)))/1000 | AN35: =(0.85*$D$11*AL35*$D$14*($D$15/2-AL35/2)+SUMPRODUCT($AF$8:$AF$17,(ABS(6000*(1-$AE$8:$AE$17/AK35)+$D$12)-ABS(6000*(1-$AE$8:$AE$17/AK35)-$D$12))/2-0.85*$D$11*($AE$8:$AE$17<AL35),$D$15/2-$AE$8:$AE$17))/100000 | AO35: =IF(AM35<=0,0.9,MAX(0.7,0.9/(1+0.2*AM35/$D$71))) | AP35: =MIN(AO35*AM35,$D$68) | AQ35: =MAX(0,AO35*AN35) | AR35: =IF(AS35>0,-AQ35/AS35,-1E+9) | AS35: =AO35*AM35 | AU35: =0.75*$D$14 | AV35: =MIN($D$66*AU35,$D$14) | AW35: =(0.85*$D$11*AV35*$D$15+SUMPRODUCT($AH$8:$AH$17,(ABS(6000*(1-$AG$8:$AG$17/AU35)+$D$12)-ABS(6000*(1-$AG$8:$AG$17/AU35)-$D$12))/2-0.85*$D$11*($AG$8:$AG$17<AV35)))/1000 | AX35: =(0.85*$D$11*AV35*$D$15*($D$14/2-AV35/2)+SUMPRODUCT($AH$8:$AH$17,(ABS(6000*(1-$AG$8:$AG$17/AU35)+$D$12)-ABS(6000*(1-$AG$8:$AG$17/AU35)-$D$12))/2-0.85*$D$11*($AG$8:$AG$17<AV35),$D$14/2-$AG$8:$AG$17))/100000 | AY35: =IF(AW35<=0,0.9,MAX(0.7,0.9/(1+0.2*AW35/$D$72))) | AZ35: =MIN(AY35*AW35,$D$68) | BA35: =MAX(0,AY35*AX35) | BB35: =IF(BC35>0,-BA35/BC35,-1E+9) | BC35: =AY35*AW35
B36: Cortante último en X (máx. envolvente) | C36: VuX | D36: 4 | E36: t | F36: Asociado a Muy | AK36: =0.8*$D$15 | AL36: =MIN($D$66*AK36,$D$15) | AM36: =(0.85*$D$11*AL36*$D$14+SUMPRODUCT($AF$8:$AF$17,(ABS(6000*(1-$AE$8:$AE$17/AK36)+$D$12)-ABS(6000*(1-$AE$8:$AE$17/AK36)-$D$12))/2-0.85*$D$11*($AE$8:$AE$17<AL36)))/1000 | AN36: =(0.85*$D$11*AL36*$D$14*($D$15/2-AL36/2)+SUMPRODUCT($AF$8:$AF$17,(ABS(6000*(1-$AE$8:$AE$17/AK36)+$D$12)-ABS(6000*(1-$AE$8:$AE$17/AK36)-$D$12))/2-0.85*$D$11*($AE$8:$AE$17<AL36),$D$15/2-$AE$8:$AE$17))/100000 | AO36: =IF(AM36<=0,0.9,MAX(0.7,0.9/(1+0.2*AM36/$D$71))) | AP36: =MIN(AO36*AM36,$D$68) | AQ36: =MAX(0,AO36*AN36) | AR36: =IF(AS36>0,-AQ36/AS36,-1E+9) | AS36: =AO36*AM36 | AU36: =0.8*$D$14 | AV36: =MIN($D$66*AU36,$D$14) | AW36: =(0.85*$D$11*AV36*$D$15+SUMPRODUCT($AH$8:$AH$17,(ABS(6000*(1-$AG$8:$AG$17/AU36)+$D$12)-ABS(6000*(1-$AG$8:$AG$17/AU36)-$D$12))/2-0.85*$D$11*($AG$8:$AG$17<AV36)))/1000 | AX36: =(0.85*$D$11*AV36*$D$15*($D$14/2-AV36/2)+SUMPRODUCT($AH$8:$AH$17,(ABS(6000*(1-$AG$8:$AG$17/AU36)+$D$12)-ABS(6000*(1-$AG$8:$AG$17/AU36)-$D$12))/2-0.85*$D$11*($AG$8:$AG$17<AV36),$D$14/2-$AG$8:$AG$17))/100000 | AY36: =IF(AW36<=0,0.9,MAX(0.7,0.9/(1+0.2*AW36/$D$72))) | AZ36: =MIN(AY36*AW36,$D$68) | BA36: =MAX(0,AY36*AX36) | BB36: =IF(BC36>0,-BA36/BC36,-1E+9) | BC36: =AY36*AW36
B37: Cortante de sismo puro en X | C37: VSX | D37: 2.5 | E37: t | AK37: =0.85*$D$15 | AL37: =MIN($D$66*AK37,$D$15) | AM37: =(0.85*$D$11*AL37*$D$14+SUMPRODUCT($AF$8:$AF$17,(ABS(6000*(1-$AE$8:$AE$17/AK37)+$D$12)-ABS(6000*(1-$AE$8:$AE$17/AK37)-$D$12))/2-0.85*$D$11*($AE$8:$AE$17<AL37)))/1000 | AN37: =(0.85*$D$11*AL37*$D$14*($D$15/2-AL37/2)+SUMPRODUCT($AF$8:$AF$17,(ABS(6000*(1-$AE$8:$AE$17/AK37)+$D$12)-ABS(6000*(1-$AE$8:$AE$17/AK37)-$D$12))/2-0.85*$D$11*($AE$8:$AE$17<AL37),$D$15/2-$AE$8:$AE$17))/100000 | AO37: =IF(AM37<=0,0.9,MAX(0.7,0.9/(1+0.2*AM37/$D$71))) | AP37: =MIN(AO37*AM37,$D$68) | AQ37: =MAX(0,AO37*AN37) | AR37: =IF(AS37>0,-AQ37/AS37,-1E+9) | AS37: =AO37*AM37 | AU37: =0.85*$D$14 | AV37: =MIN($D$66*AU37,$D$14) | AW37: =(0.85*$D$11*AV37*$D$15+SUMPRODUCT($AH$8:$AH$17,(ABS(6000*(1-$AG$8:$AG$17/AU37)+$D$12)-ABS(6000*(1-$AG$8:$AG$17/AU37)-$D$12))/2-0.85*$D$11*($AG$8:$AG$17<AV37)))/1000 | AX37: =(0.85*$D$11*AV37*$D$15*($D$14/2-AV37/2)+SUMPRODUCT($AH$8:$AH$17,(ABS(6000*(1-$AG$8:$AG$17/AU37)+$D$12)-ABS(6000*(1-$AG$8:$AG$17/AU37)-$D$12))/2-0.85*$D$11*($AG$8:$AG$17<AV37),$D$14/2-$AG$8:$AG$17))/100000 | AY37: =IF(AW37<=0,0.9,MAX(0.7,0.9/(1+0.2*AW37/$D$72))) | AZ37: =MIN(AY37*AW37,$D$68) | BA37: =MAX(0,AY37*AX37) | BB37: =IF(BC37>0,-BA37/BC37,-1E+9) | BC37: =AY37*AW37
B38: Combinaciones de diseño: Mux gira alrededor del eje X (la flexión comprime una cara de longitud B) | AK38: =0.9*$D$15 | AL38: =MIN($D$66*AK38,$D$15) | AM38: =(0.85*$D$11*AL38*$D$14+SUMPRODUCT($AF$8:$AF$17,(ABS(6000*(1-$AE$8:$AE$17/AK38)+$D$12)-ABS(6000*(1-$AE$8:$AE$17/AK38)-$D$12))/2-0.85*$D$11*($AE$8:$AE$17<AL38)))/1000 | AN38: =(0.85*$D$11*AL38*$D$14*($D$15/2-AL38/2)+SUMPRODUCT($AF$8:$AF$17,(ABS(6000*(1-$AE$8:$AE$17/AK38)+$D$12)-ABS(6000*(1-$AE$8:$AE$17/AK38)-$D$12))/2-0.85*$D$11*($AE$8:$AE$17<AL38),$D$15/2-$AE$8:$AE$17))/100000 | AO38: =IF(AM38<=0,0.9,MAX(0.7,0.9/(1+0.2*AM38/$D$71))) | AP38: =MIN(AO38*AM38,$D$68) | AQ38: =MAX(0,AO38*AN38) | AR38: =IF(AS38>0,-AQ38/AS38,-1E+9) | AS38: =AO38*AM38 | AU38: =0.9*$D$14 | AV38: =MIN($D$66*AU38,$D$14) | AW38: =(0.85*$D$11*AV38*$D$15+SUMPRODUCT($AH$8:$AH$17,(ABS(6000*(1-$AG$8:$AG$17/AU38)+$D$12)-ABS(6000*(1-$AG$8:$AG$17/AU38)-$D$12))/2-0.85*$D$11*($AG$8:$AG$17<AV38)))/1000 | AX38: =(0.85*$D$11*AV38*$D$15*($D$14/2-AV38/2)+SUMPRODUCT($AH$8:$AH$17,(ABS(6000*(1-$AG$8:$AG$17/AU38)+$D$12)-ABS(6000*(1-$AG$8:$AG$17/AU38)-$D$12))/2-0.85*$D$11*($AG$8:$AG$17<AV38),$D$14/2-$AG$8:$AG$17))/100000 | AY38: =IF(AW38<=0,0.9,MAX(0.7,0.9/(1+0.2*AW38/$D$72))) | AZ38: =MIN(AY38*AW38,$D$68) | BA38: =MAX(0,AY38*AX38) | BB38: =IF(BC38>0,-BA38/BC38,-1E+9) | BC38: =AY38*AW38
B39: Combinación | C39: Pu (t) | D39: Mux (t·m) | E39: Muy (t·m) | F39: φMnx (t·m) | G39: φMny (t·m) | H39: D/C | AK39: =0.95*$D$15 | AL39: =MIN($D$66*AK39,$D$15) | AM39: =(0.85*$D$11*AL39*$D$14+SUMPRODUCT($AF$8:$AF$17,(ABS(6000*(1-$AE$8:$AE$17/AK39)+$D$12)-ABS(6000*(1-$AE$8:$AE$17/AK39)-$D$12))/2-0.85*$D$11*($AE$8:$AE$17<AL39)))/1000 | AN39: =(0.85*$D$11*AL39*$D$14*($D$15/2-AL39/2)+SUMPRODUCT($AF$8:$AF$17,(ABS(6000*(1-$AE$8:$AE$17/AK39)+$D$12)-ABS(6000*(1-$AE$8:$AE$17/AK39)-$D$12))/2-0.85*$D$11*($AE$8:$AE$17<AL39),$D$15/2-$AE$8:$AE$17))/100000 | AO39: =IF(AM39<=0,0.9,MAX(0.7,0.9/(1+0.2*AM39/$D$71))) | AP39: =MIN(AO39*AM39,$D$68) | AQ39: =MAX(0,AO39*AN39) | AR39: =IF(AS39>0,-AQ39/AS39,-1E+9) | AS39: =AO39*AM39 | AU39: =0.95*$D$14 | AV39: =MIN($D$66*AU39,$D$14) | AW39: =(0.85*$D$11*AV39*$D$15+SUMPRODUCT($AH$8:$AH$17,(ABS(6000*(1-$AG$8:$AG$17/AU39)+$D$12)-ABS(6000*(1-$AG$8:$AG$17/AU39)-$D$12))/2-0.85*$D$11*($AG$8:$AG$17<AV39)))/1000 | AX39: =(0.85*$D$11*AV39*$D$15*($D$14/2-AV39/2)+SUMPRODUCT($AH$8:$AH$17,(ABS(6000*(1-$AG$8:$AG$17/AU39)+$D$12)-ABS(6000*(1-$AG$8:$AG$17/AU39)-$D$12))/2-0.85*$D$11*($AG$8:$AG$17<AV39),$D$14/2-$AG$8:$AG$17))/100000 | AY39: =IF(AW39<=0,0.9,MAX(0.7,0.9/(1+0.2*AW39/$D$72))) | AZ39: =MIN(AY39*AW39,$D$68) | BA39: =MAX(0,AY39*AX39) | BB39: =IF(BC39>0,-BA39/BC39,-1E+9) | BC39: =AY39*AW39 | BE39: |Mux|c | BF39: |Muy|c | BG39: iX | BH39: iY | BI39: φMnx | BJ39: φMny | BK39: eX | BL39: eY | BM39: jX | BN39: jY | BO39: φPnx | BP39: φPny | BQ39: φPni | BR39: D/C | BS39: δx | BT39: δy | BU39: Mnx | BV39: Mny
B40: 1.4CM + 1.7CV | C40: 145 | D40: 3 | E40: 1.5 | F40: =BI40 | G40: =BJ40 | H40: =BR40 | AK40: =1.0*$D$15 | AL40: =MIN($D$66*AK40,$D$15) | AM40: =(0.85*$D$11*AL40*$D$14+SUMPRODUCT($AF$8:$AF$17,(ABS(6000*(1-$AE$8:$AE$17/AK40)+$D$12)-ABS(6000*(1-$AE$8:$AE$17/AK40)-$D$12))/2-0.85*$D$11*($AE$8:$AE$17<AL40)))/1000 | AN40: =(0.85*$D$11*AL40*$D$14*($D$15/2-AL40/2)+SUMPRODUCT($AF$8:$AF$17,(ABS(6000*(1-$AE$8:$AE$17/AK40)+$D$12)-ABS(6000*(1-$AE$8:$AE$17/AK40)-$D$12))/2-0.85*$D$11*($AE$8:$AE$17<AL40),$D$15/2-$AE$8:$AE$17))/100000 | AO40: =IF(AM40<=0,0.9,MAX(0.7,0.9/(1+0.2*AM40/$D$71))) | AP40: =MIN(AO40*AM40,$D$68) | AQ40: =MAX(0,AO40*AN40) | AR40: =IF(AS40>0,-AQ40/AS40,-1E+9) | AS40: =AO40*AM40 | AU40: =1.0*$D$14 | AV40: =MIN($D$66*AU40,$D$14) | AW40: =(0.85*$D$11*AV40*$D$15+SUMPRODUCT($AH$8:$AH$17,(ABS(6000*(1-$AG$8:$AG$17/AU40)+$D$12)-ABS(6000*(1-$AG$8:$AG$17/AU40)-$D$12))/2-0.85*$D$11*($AG$8:$AG$17<AV40)))/1000 | AX40: =(0.85*$D$11*AV40*$D$15*($D$14/2-AV40/2)+SUMPRODUCT($AH$8:$AH$17,(ABS(6000*(1-$AG$8:$AG$17/AU40)+$D$12)-ABS(6000*(1-$AG$8:$AG$17/AU40)-$D$12))/2-0.85*$D$11*($AG$8:$AG$17<AV40),$D$14/2-$AG$8:$AG$17))/100000 | AY40: =IF(AW40<=0,0.9,MAX(0.7,0.9/(1+0.2*AW40/$D$72))) | AZ40: =MIN(AY40*AW40,$D$68) | BA40: =MAX(0,AY40*AX40) | BB40: =IF(BC40>0,-BA40/BC40,-1E+9) | BC40: =AY40*AW40 | BE40: =BS40*IF(AND($D$74>=$D$73,$D$26="Sí"),MAX(ABS($D$40),MAX(0,$C$40)*(1.5+0.03*$D$15)/100),ABS($D$40)) | BF40: =BT40*IF(AND($D$75>=$D$73,$D$26="Sí"),MAX(ABS($E$40),MAX(0,$C$40)*(1.5+0.03*$D$14)/100),ABS($E$40)) | BG40: =IFERROR(MATCH($C$40,$AP$9:$AP$48,1),0) | BH40: =IFERROR(MATCH($C$40,$AZ$9:$AZ$48,1),0) | BI40: =IF(BG40<=0,INDEX($AQ$9:$AQ$48,1),IF(BG40>=40,INDEX($AQ$9:$AQ$48,40),INDEX($AQ$9:$AQ$48,BG40)+(INDEX($AQ$9:$AQ$48,BG40+1)-INDEX($AQ$9:$AQ$48,BG40))*($C$40-INDEX($AP$9:$AP$48,BG40))/MAX(1E-9,INDEX($AP$9:$AP$48,BG40+1)-INDEX($AP$9:$AP$48,BG40)))) | BJ40: =IF(BH40<=0,INDEX($BA$9:$BA$48,1),IF(BH40>=40,INDEX($BA$9:$BA$48,40),INDEX($BA$9:$BA$48,BH40)+(INDEX($BA$9:$BA$48,BH40+1)-INDEX($BA$9:$BA$48,BH40))*($C$40-INDEX($AZ$9:$AZ$48,BH40))/MAX(1E-9,INDEX($AZ$9:$AZ$48,BH40+1)-INDEX($AZ$9:$AZ$48,BH40)))) | BK40: =IF($C$40>0,BE40/$C$40,0) | BL40: =IF($C$40>0,BF40/$C$40,0) | BM40: =IFERROR(MATCH(-BK40,$AR$9:$AR$48,1),0) | BN40: =IFERROR(MATCH(-BL40,$BB$9:$BB$48,1),0) | BO40: =IF(BM40<=0,INDEX($AS$9:$AS$48,1),IF(BM40>=40,INDEX($AS$9:$AS$48,40),INDEX($AS$9:$AS$48,BM40)+(INDEX($AS$9:$AS$48,BM40+1)-INDEX($AS$9:$AS$48,BM40))*(-BK40-INDEX($AR$9:$AR$48,BM40))/MAX(1E-9,INDEX($AR$9:$AR$48,BM40+1)-INDEX($AR$9:$AR$48,BM40)))) | BP40: =IF(BN40<=0,INDEX($BC$9:$BC$48,1),IF(BN40>=40,INDEX($BC$9:$BC$48,40),INDEX($BC$9:$BC$48,BN40)+(INDEX($BC$9:$BC$48,BN40+1)-INDEX($BC$9:$BC$48,BN40))*(-BL40-INDEX($BB$9:$BB$48,BN40))/MAX(1E-9,INDEX($BB$9:$BB$48,BN40+1)-INDEX($BB$9:$BB$48,BN40)))) | BQ40: =IFERROR(1/(1/BO40+1/BP40-1/(0.7*$D$67)),0.0001) | BR40: =IF(AND($C$40=0,$D$40=0,$E$40=0),0,IF($C$40>$D$68,99,IF($C$40>=0.1*$D$11*$D$58/1000,$C$40/MAX(0.0001,MIN(BQ40,$D$68)),BE40/MAX(0.0001,BI40)+BF40/MAX(0.0001,BJ40)))) | BS40: =IF($D$74<$D$73,1,IF($D$26="Sí",IF($C$40>=0.75*$D$77,99,MAX(1,$D$79/(1-MAX(0,$C$40)/(0.75*$D$77)))),$D$80)) | BT40: =IF($D$75<$D$73,1,IF($D$26="Sí",IF($C$40>=0.75*$D$78,99,MAX(1,$D$79/(1-MAX(0,$C$40)/(0.75*$D$78)))),$D$80)) | BU40: =IF(IFERROR(MATCH($C$40,$AM$9:$AM$48,1),0)<=0,INDEX($AN$9:$AN$48,1),IF(IFERROR(MATCH($C$40,$AM$9:$AM$48,1),0)>=40,INDEX($AN$9:$AN$48,40),INDEX($AN$9:$AN$48,IFERROR(MATCH($C$40,$AM$9:$AM$48,1),0))+(INDEX($AN$9:$AN$48,IFERROR(MATCH($C$40,$AM$9:$AM$48,1),0)+1)-INDEX($AN$9:$AN$48,IFERROR(MATCH($C$40,$AM$9:$AM$48,1),0)))*($C$40-INDEX($AM$9:$AM$48,IFERROR(MATCH($C$40,$AM$9:$AM$48,1),0)))/MAX(1E-9,INDEX($AM$9:$AM$48,IFERROR(MATCH($C$40,$AM$9:$AM$48,1),0)+1)-INDEX($AM$9:$AM$48,IFERROR(MATCH($C$40,$AM$9:$AM$48,1),0))))) | BV40: =IF(IFERROR(MATCH($C$40,$AW$9:$AW$48,1),0)<=0,INDEX($AX$9:$AX$48,1),IF(IFERROR(MATCH($C$40,$AW$9:$AW$48,1),0)>=40,INDEX($AX$9:$AX$48,40),INDEX($AX$9:$AX$48,IFERROR(MATCH($C$40,$AW$9:$AW$48,1),0))+(INDEX($AX$9:$AX$48,IFERROR(MATCH($C$40,$AW$9:$AW$48,1),0)+1)-INDEX($AX$9:$AX$48,IFERROR(MATCH($C$40,$AW$9:$AW$48,1),0)))*($C$40-INDEX($AW$9:$AW$48,IFERROR(MATCH($C$40,$AW$9:$AW$48,1),0)))/MAX(1E-9,INDEX($AW$9:$AW$48,IFERROR(MATCH($C$40,$AW$9:$AW$48,1),0)+1)-INDEX($AW$9:$AW$48,IFERROR(MATCH($C$40,$AW$9:$AW$48,1),0)))))
B41: 1.25(CM+CV) + SX | C41: 128 | D41: 4 | E41: 9.5 | F41: =BI41 | G41: =BJ41 | H41: =BR41 | AK41: =1.1*$D$15 | AL41: =MIN($D$66*AK41,$D$15) | AM41: =(0.85*$D$11*AL41*$D$14+SUMPRODUCT($AF$8:$AF$17,(ABS(6000*(1-$AE$8:$AE$17/AK41)+$D$12)-ABS(6000*(1-$AE$8:$AE$17/AK41)-$D$12))/2-0.85*$D$11*($AE$8:$AE$17<AL41)))/1000 | AN41: =(0.85*$D$11*AL41*$D$14*($D$15/2-AL41/2)+SUMPRODUCT($AF$8:$AF$17,(ABS(6000*(1-$AE$8:$AE$17/AK41)+$D$12)-ABS(6000*(1-$AE$8:$AE$17/AK41)-$D$12))/2-0.85*$D$11*($AE$8:$AE$17<AL41),$D$15/2-$AE$8:$AE$17))/100000 | AO41: =IF(AM41<=0,0.9,MAX(0.7,0.9/(1+0.2*AM41/$D$71))) | AP41: =MIN(AO41*AM41,$D$68) | AQ41: =MAX(0,AO41*AN41) | AR41: =IF(AS41>0,-AQ41/AS41,-1E+9) | AS41: =AO41*AM41 | AU41: =1.1*$D$14 | AV41: =MIN($D$66*AU41,$D$14) | AW41: =(0.85*$D$11*AV41*$D$15+SUMPRODUCT($AH$8:$AH$17,(ABS(6000*(1-$AG$8:$AG$17/AU41)+$D$12)-ABS(6000*(1-$AG$8:$AG$17/AU41)-$D$12))/2-0.85*$D$11*($AG$8:$AG$17<AV41)))/1000 | AX41: =(0.85*$D$11*AV41*$D$15*($D$14/2-AV41/2)+SUMPRODUCT($AH$8:$AH$17,(ABS(6000*(1-$AG$8:$AG$17/AU41)+$D$12)-ABS(6000*(1-$AG$8:$AG$17/AU41)-$D$12))/2-0.85*$D$11*($AG$8:$AG$17<AV41),$D$14/2-$AG$8:$AG$17))/100000 | AY41: =IF(AW41<=0,0.9,MAX(0.7,0.9/(1+0.2*AW41/$D$72))) | AZ41: =MIN(AY41*AW41,$D$68) | BA41: =MAX(0,AY41*AX41) | BB41: =IF(BC41>0,-BA41/BC41,-1E+9) | BC41: =AY41*AW41 | BE41: =BS41*IF(AND($D$74>=$D$73,$D$26="Sí"),MAX(ABS($D$41),MAX(0,$C$41)*(1.5+0.03*$D$15)/100),ABS($D$41)) | BF41: =BT41*IF(AND($D$75>=$D$73,$D$26="Sí"),MAX(ABS($E$41),MAX(0,$C$41)*(1.5+0.03*$D$14)/100),ABS($E$41)) | BG41: =IFERROR(MATCH($C$41,$AP$9:$AP$48,1),0) | BH41: =IFERROR(MATCH($C$41,$AZ$9:$AZ$48,1),0) | BI41: =IF(BG41<=0,INDEX($AQ$9:$AQ$48,1),IF(BG41>=40,INDEX($AQ$9:$AQ$48,40),INDEX($AQ$9:$AQ$48,BG41)+(INDEX($AQ$9:$AQ$48,BG41+1)-INDEX($AQ$9:$AQ$48,BG41))*($C$41-INDEX($AP$9:$AP$48,BG41))/MAX(1E-9,INDEX($AP$9:$AP$48,BG41+1)-INDEX($AP$9:$AP$48,BG41)))) | BJ41: =IF(BH41<=0,INDEX($BA$9:$BA$48,1),IF(BH41>=40,INDEX($BA$9:$BA$48,40),INDEX($BA$9:$BA$48,BH41)+(INDEX($BA$9:$BA$48,BH41+1)-INDEX($BA$9:$BA$48,BH41))*($C$41-INDEX($AZ$9:$AZ$48,BH41))/MAX(1E-9,INDEX($AZ$9:$AZ$48,BH41+1)-INDEX($AZ$9:$AZ$48,BH41)))) | BK41: =IF($C$41>0,BE41/$C$41,0) | BL41: =IF($C$41>0,BF41/$C$41,0) | BM41: =IFERROR(MATCH(-BK41,$AR$9:$AR$48,1),0) | BN41: =IFERROR(MATCH(-BL41,$BB$9:$BB$48,1),0) | BO41: =IF(BM41<=0,INDEX($AS$9:$AS$48,1),IF(BM41>=40,INDEX($AS$9:$AS$48,40),INDEX($AS$9:$AS$48,BM41)+(INDEX($AS$9:$AS$48,BM41+1)-INDEX($AS$9:$AS$48,BM41))*(-BK41-INDEX($AR$9:$AR$48,BM41))/MAX(1E-9,INDEX($AR$9:$AR$48,BM41+1)-INDEX($AR$9:$AR$48,BM41)))) | BP41: =IF(BN41<=0,INDEX($BC$9:$BC$48,1),IF(BN41>=40,INDEX($BC$9:$BC$48,40),INDEX($BC$9:$BC$48,BN41)+(INDEX($BC$9:$BC$48,BN41+1)-INDEX($BC$9:$BC$48,BN41))*(-BL41-INDEX($BB$9:$BB$48,BN41))/MAX(1E-9,INDEX($BB$9:$BB$48,BN41+1)-INDEX($BB$9:$BB$48,BN41)))) | BQ41: =IFERROR(1/(1/BO41+1/BP41-1/(0.7*$D$67)),0.0001) | BR41: =IF(AND($C$41=0,$D$41=0,$E$41=0),0,IF($C$41>$D$68,99,IF($C$41>=0.1*$D$11*$D$58/1000,$C$41/MAX(0.0001,MIN(BQ41,$D$68)),BE41/MAX(0.0001,BI41)+BF41/MAX(0.0001,BJ41)))) | BS41: =IF($D$74<$D$73,1,IF($D$26="Sí",IF($C$41>=0.75*$D$77,99,MAX(1,$D$79/(1-MAX(0,$C$41)/(0.75*$D$77)))),$D$80)) | BT41: =IF($D$75<$D$73,1,IF($D$26="Sí",IF($C$41>=0.75*$D$78,99,MAX(1,$D$79/(1-MAX(0,$C$41)/(0.75*$D$78)))),$D$80)) | BU41: =IF(IFERROR(MATCH($C$41,$AM$9:$AM$48,1),0)<=0,INDEX($AN$9:$AN$48,1),IF(IFERROR(MATCH($C$41,$AM$9:$AM$48,1),0)>=40,INDEX($AN$9:$AN$48,40),INDEX($AN$9:$AN$48,IFERROR(MATCH($C$41,$AM$9:$AM$48,1),0))+(INDEX($AN$9:$AN$48,IFERROR(MATCH($C$41,$AM$9:$AM$48,1),0)+1)-INDEX($AN$9:$AN$48,IFERROR(MATCH($C$41,$AM$9:$AM$48,1),0)))*($C$41-INDEX($AM$9:$AM$48,IFERROR(MATCH($C$41,$AM$9:$AM$48,1),0)))/MAX(1E-9,INDEX($AM$9:$AM$48,IFERROR(MATCH($C$41,$AM$9:$AM$48,1),0)+1)-INDEX($AM$9:$AM$48,IFERROR(MATCH($C$41,$AM$9:$AM$48,1),0))))) | BV41: =IF(IFERROR(MATCH($C$41,$AW$9:$AW$48,1),0)<=0,INDEX($AX$9:$AX$48,1),IF(IFERROR(MATCH($C$41,$AW$9:$AW$48,1),0)>=40,INDEX($AX$9:$AX$48,40),INDEX($AX$9:$AX$48,IFERROR(MATCH($C$41,$AW$9:$AW$48,1),0))+(INDEX($AX$9:$AX$48,IFERROR(MATCH($C$41,$AW$9:$AW$48,1),0)+1)-INDEX($AX$9:$AX$48,IFERROR(MATCH($C$41,$AW$9:$AW$48,1),0)))*($C$41-INDEX($AW$9:$AW$48,IFERROR(MATCH($C$41,$AW$9:$AW$48,1),0)))/MAX(1E-9,INDEX($AW$9:$AW$48,IFERROR(MATCH($C$41,$AW$9:$AW$48,1),0)+1)-INDEX($AW$9:$AW$48,IFERROR(MATCH($C$41,$AW$9:$AW$48,1),0)))))
B42: 1.25(CM+CV) − SX | C42: 120 | D42: 2 | E42: -8 | F42: =BI42 | G42: =BJ42 | H42: =BR42 | AK42: =1.2*$D$15 | AL42: =MIN($D$66*AK42,$D$15) | AM42: =(0.85*$D$11*AL42*$D$14+SUMPRODUCT($AF$8:$AF$17,(ABS(6000*(1-$AE$8:$AE$17/AK42)+$D$12)-ABS(6000*(1-$AE$8:$AE$17/AK42)-$D$12))/2-0.85*$D$11*($AE$8:$AE$17<AL42)))/1000 | AN42: =(0.85*$D$11*AL42*$D$14*($D$15/2-AL42/2)+SUMPRODUCT($AF$8:$AF$17,(ABS(6000*(1-$AE$8:$AE$17/AK42)+$D$12)-ABS(6000*(1-$AE$8:$AE$17/AK42)-$D$12))/2-0.85*$D$11*($AE$8:$AE$17<AL42),$D$15/2-$AE$8:$AE$17))/100000 | AO42: =IF(AM42<=0,0.9,MAX(0.7,0.9/(1+0.2*AM42/$D$71))) | AP42: =MIN(AO42*AM42,$D$68) | AQ42: =MAX(0,AO42*AN42) | AR42: =IF(AS42>0,-AQ42/AS42,-1E+9) | AS42: =AO42*AM42 | AU42: =1.2*$D$14 | AV42: =MIN($D$66*AU42,$D$14) | AW42: =(0.85*$D$11*AV42*$D$15+SUMPRODUCT($AH$8:$AH$17,(ABS(6000*(1-$AG$8:$AG$17/AU42)+$D$12)-ABS(6000*(1-$AG$8:$AG$17/AU42)-$D$12))/2-0.85*$D$11*($AG$8:$AG$17<AV42)))/1000 | AX42: =(0.85*$D$11*AV42*$D$15*($D$14/2-AV42/2)+SUMPRODUCT($AH$8:$AH$17,(ABS(6000*(1-$AG$8:$AG$17/AU42)+$D$12)-ABS(6000*(1-$AG$8:$AG$17/AU42)-$D$12))/2-0.85*$D$11*($AG$8:$AG$17<AV42),$D$14/2-$AG$8:$AG$17))/100000 | AY42: =IF(AW42<=0,0.9,MAX(0.7,0.9/(1+0.2*AW42/$D$72))) | AZ42: =MIN(AY42*AW42,$D$68) | BA42: =MAX(0,AY42*AX42) | BB42: =IF(BC42>0,-BA42/BC42,-1E+9) | BC42: =AY42*AW42 | BE42: =BS42*IF(AND($D$74>=$D$73,$D$26="Sí"),MAX(ABS($D$42),MAX(0,$C$42)*(1.5+0.03*$D$15)/100),ABS($D$42)) | BF42: =BT42*IF(AND($D$75>=$D$73,$D$26="Sí"),MAX(ABS($E$42),MAX(0,$C$42)*(1.5+0.03*$D$14)/100),ABS($E$42)) | BG42: =IFERROR(MATCH($C$42,$AP$9:$AP$48,1),0) | BH42: =IFERROR(MATCH($C$42,$AZ$9:$AZ$48,1),0) | BI42: =IF(BG42<=0,INDEX($AQ$9:$AQ$48,1),IF(BG42>=40,INDEX($AQ$9:$AQ$48,40),INDEX($AQ$9:$AQ$48,BG42)+(INDEX($AQ$9:$AQ$48,BG42+1)-INDEX($AQ$9:$AQ$48,BG42))*($C$42-INDEX($AP$9:$AP$48,BG42))/MAX(1E-9,INDEX($AP$9:$AP$48,BG42+1)-INDEX($AP$9:$AP$48,BG42)))) | BJ42: =IF(BH42<=0,INDEX($BA$9:$BA$48,1),IF(BH42>=40,INDEX($BA$9:$BA$48,40),INDEX($BA$9:$BA$48,BH42)+(INDEX($BA$9:$BA$48,BH42+1)-INDEX($BA$9:$BA$48,BH42))*($C$42-INDEX($AZ$9:$AZ$48,BH42))/MAX(1E-9,INDEX($AZ$9:$AZ$48,BH42+1)-INDEX($AZ$9:$AZ$48,BH42)))) | BK42: =IF($C$42>0,BE42/$C$42,0) | BL42: =IF($C$42>0,BF42/$C$42,0) | BM42: =IFERROR(MATCH(-BK42,$AR$9:$AR$48,1),0) | BN42: =IFERROR(MATCH(-BL42,$BB$9:$BB$48,1),0) | BO42: =IF(BM42<=0,INDEX($AS$9:$AS$48,1),IF(BM42>=40,INDEX($AS$9:$AS$48,40),INDEX($AS$9:$AS$48,BM42)+(INDEX($AS$9:$AS$48,BM42+1)-INDEX($AS$9:$AS$48,BM42))*(-BK42-INDEX($AR$9:$AR$48,BM42))/MAX(1E-9,INDEX($AR$9:$AR$48,BM42+1)-INDEX($AR$9:$AR$48,BM42)))) | BP42: =IF(BN42<=0,INDEX($BC$9:$BC$48,1),IF(BN42>=40,INDEX($BC$9:$BC$48,40),INDEX($BC$9:$BC$48,BN42)+(INDEX($BC$9:$BC$48,BN42+1)-INDEX($BC$9:$BC$48,BN42))*(-BL42-INDEX($BB$9:$BB$48,BN42))/MAX(1E-9,INDEX($BB$9:$BB$48,BN42+1)-INDEX($BB$9:$BB$48,BN42)))) | BQ42: =IFERROR(1/(1/BO42+1/BP42-1/(0.7*$D$67)),0.0001) | BR42: =IF(AND($C$42=0,$D$42=0,$E$42=0),0,IF($C$42>$D$68,99,IF($C$42>=0.1*$D$11*$D$58/1000,$C$42/MAX(0.0001,MIN(BQ42,$D$68)),BE42/MAX(0.0001,BI42)+BF42/MAX(0.0001,BJ42)))) | BS42: =IF($D$74<$D$73,1,IF($D$26="Sí",IF($C$42>=0.75*$D$77,99,MAX(1,$D$79/(1-MAX(0,$C$42)/(0.75*$D$77)))),$D$80)) | BT42: =IF($D$75<$D$73,1,IF($D$26="Sí",IF($C$42>=0.75*$D$78,99,MAX(1,$D$79/(1-MAX(0,$C$42)/(0.75*$D$78)))),$D$80)) | BU42: =IF(IFERROR(MATCH($C$42,$AM$9:$AM$48,1),0)<=0,INDEX($AN$9:$AN$48,1),IF(IFERROR(MATCH($C$42,$AM$9:$AM$48,1),0)>=40,INDEX($AN$9:$AN$48,40),INDEX($AN$9:$AN$48,IFERROR(MATCH($C$42,$AM$9:$AM$48,1),0))+(INDEX($AN$9:$AN$48,IFERROR(MATCH($C$42,$AM$9:$AM$48,1),0)+1)-INDEX($AN$9:$AN$48,IFERROR(MATCH($C$42,$AM$9:$AM$48,1),0)))*($C$42-INDEX($AM$9:$AM$48,IFERROR(MATCH($C$42,$AM$9:$AM$48,1),0)))/MAX(1E-9,INDEX($AM$9:$AM$48,IFERROR(MATCH($C$42,$AM$9:$AM$48,1),0)+1)-INDEX($AM$9:$AM$48,IFERROR(MATCH($C$42,$AM$9:$AM$48,1),0))))) | BV42: =IF(IFERROR(MATCH($C$42,$AW$9:$AW$48,1),0)<=0,INDEX($AX$9:$AX$48,1),IF(IFERROR(MATCH($C$42,$AW$9:$AW$48,1),0)>=40,INDEX($AX$9:$AX$48,40),INDEX($AX$9:$AX$48,IFERROR(MATCH($C$42,$AW$9:$AW$48,1),0))+(INDEX($AX$9:$AX$48,IFERROR(MATCH($C$42,$AW$9:$AW$48,1),0)+1)-INDEX($AX$9:$AX$48,IFERROR(MATCH($C$42,$AW$9:$AW$48,1),0)))*($C$42-INDEX($AW$9:$AW$48,IFERROR(MATCH($C$42,$AW$9:$AW$48,1),0)))/MAX(1E-9,INDEX($AW$9:$AW$48,IFERROR(MATCH($C$42,$AW$9:$AW$48,1),0)+1)-INDEX($AW$9:$AW$48,IFERROR(MATCH($C$42,$AW$9:$AW$48,1),0)))))
B43: 1.25(CM+CV) + SY | C43: 132 | D43: 13 | E43: 2 | F43: =BI43 | G43: =BJ43 | H43: =BR43 | AK43: =1.35*$D$15 | AL43: =MIN($D$66*AK43,$D$15) | AM43: =(0.85*$D$11*AL43*$D$14+SUMPRODUCT($AF$8:$AF$17,(ABS(6000*(1-$AE$8:$AE$17/AK43)+$D$12)-ABS(6000*(1-$AE$8:$AE$17/AK43)-$D$12))/2-0.85*$D$11*($AE$8:$AE$17<AL43)))/1000 | AN43: =(0.85*$D$11*AL43*$D$14*($D$15/2-AL43/2)+SUMPRODUCT($AF$8:$AF$17,(ABS(6000*(1-$AE$8:$AE$17/AK43)+$D$12)-ABS(6000*(1-$AE$8:$AE$17/AK43)-$D$12))/2-0.85*$D$11*($AE$8:$AE$17<AL43),$D$15/2-$AE$8:$AE$17))/100000 | AO43: =IF(AM43<=0,0.9,MAX(0.7,0.9/(1+0.2*AM43/$D$71))) | AP43: =MIN(AO43*AM43,$D$68) | AQ43: =MAX(0,AO43*AN43) | AR43: =IF(AS43>0,-AQ43/AS43,-1E+9) | AS43: =AO43*AM43 | AU43: =1.35*$D$14 | AV43: =MIN($D$66*AU43,$D$14) | AW43: =(0.85*$D$11*AV43*$D$15+SUMPRODUCT($AH$8:$AH$17,(ABS(6000*(1-$AG$8:$AG$17/AU43)+$D$12)-ABS(6000*(1-$AG$8:$AG$17/AU43)-$D$12))/2-0.85*$D$11*($AG$8:$AG$17<AV43)))/1000 | AX43: =(0.85*$D$11*AV43*$D$15*($D$14/2-AV43/2)+SUMPRODUCT($AH$8:$AH$17,(ABS(6000*(1-$AG$8:$AG$17/AU43)+$D$12)-ABS(6000*(1-$AG$8:$AG$17/AU43)-$D$12))/2-0.85*$D$11*($AG$8:$AG$17<AV43),$D$14/2-$AG$8:$AG$17))/100000 | AY43: =IF(AW43<=0,0.9,MAX(0.7,0.9/(1+0.2*AW43/$D$72))) | AZ43: =MIN(AY43*AW43,$D$68) | BA43: =MAX(0,AY43*AX43) | BB43: =IF(BC43>0,-BA43/BC43,-1E+9) | BC43: =AY43*AW43 | BE43: =BS43*IF(AND($D$74>=$D$73,$D$26="Sí"),MAX(ABS($D$43),MAX(0,$C$43)*(1.5+0.03*$D$15)/100),ABS($D$43)) | BF43: =BT43*IF(AND($D$75>=$D$73,$D$26="Sí"),MAX(ABS($E$43),MAX(0,$C$43)*(1.5+0.03*$D$14)/100),ABS($E$43)) | BG43: =IFERROR(MATCH($C$43,$AP$9:$AP$48,1),0) | BH43: =IFERROR(MATCH($C$43,$AZ$9:$AZ$48,1),0) | BI43: =IF(BG43<=0,INDEX($AQ$9:$AQ$48,1),IF(BG43>=40,INDEX($AQ$9:$AQ$48,40),INDEX($AQ$9:$AQ$48,BG43)+(INDEX($AQ$9:$AQ$48,BG43+1)-INDEX($AQ$9:$AQ$48,BG43))*($C$43-INDEX($AP$9:$AP$48,BG43))/MAX(1E-9,INDEX($AP$9:$AP$48,BG43+1)-INDEX($AP$9:$AP$48,BG43)))) | BJ43: =IF(BH43<=0,INDEX($BA$9:$BA$48,1),IF(BH43>=40,INDEX($BA$9:$BA$48,40),INDEX($BA$9:$BA$48,BH43)+(INDEX($BA$9:$BA$48,BH43+1)-INDEX($BA$9:$BA$48,BH43))*($C$43-INDEX($AZ$9:$AZ$48,BH43))/MAX(1E-9,INDEX($AZ$9:$AZ$48,BH43+1)-INDEX($AZ$9:$AZ$48,BH43)))) | BK43: =IF($C$43>0,BE43/$C$43,0) | BL43: =IF($C$43>0,BF43/$C$43,0) | BM43: =IFERROR(MATCH(-BK43,$AR$9:$AR$48,1),0) | BN43: =IFERROR(MATCH(-BL43,$BB$9:$BB$48,1),0) | BO43: =IF(BM43<=0,INDEX($AS$9:$AS$48,1),IF(BM43>=40,INDEX($AS$9:$AS$48,40),INDEX($AS$9:$AS$48,BM43)+(INDEX($AS$9:$AS$48,BM43+1)-INDEX($AS$9:$AS$48,BM43))*(-BK43-INDEX($AR$9:$AR$48,BM43))/MAX(1E-9,INDEX($AR$9:$AR$48,BM43+1)-INDEX($AR$9:$AR$48,BM43)))) | BP43: =IF(BN43<=0,INDEX($BC$9:$BC$48,1),IF(BN43>=40,INDEX($BC$9:$BC$48,40),INDEX($BC$9:$BC$48,BN43)+(INDEX($BC$9:$BC$48,BN43+1)-INDEX($BC$9:$BC$48,BN43))*(-BL43-INDEX($BB$9:$BB$48,BN43))/MAX(1E-9,INDEX($BB$9:$BB$48,BN43+1)-INDEX($BB$9:$BB$48,BN43)))) | BQ43: =IFERROR(1/(1/BO43+1/BP43-1/(0.7*$D$67)),0.0001) | BR43: =IF(AND($C$43=0,$D$43=0,$E$43=0),0,IF($C$43>$D$68,99,IF($C$43>=0.1*$D$11*$D$58/1000,$C$43/MAX(0.0001,MIN(BQ43,$D$68)),BE43/MAX(0.0001,BI43)+BF43/MAX(0.0001,BJ43)))) | BS43: =IF($D$74<$D$73,1,IF($D$26="Sí",IF($C$43>=0.75*$D$77,99,MAX(1,$D$79/(1-MAX(0,$C$43)/(0.75*$D$77)))),$D$80)) | BT43: =IF($D$75<$D$73,1,IF($D$26="Sí",IF($C$43>=0.75*$D$78,99,MAX(1,$D$79/(1-MAX(0,$C$43)/(0.75*$D$78)))),$D$80)) | BU43: =IF(IFERROR(MATCH($C$43,$AM$9:$AM$48,1),0)<=0,INDEX($AN$9:$AN$48,1),IF(IFERROR(MATCH($C$43,$AM$9:$AM$48,1),0)>=40,INDEX($AN$9:$AN$48,40),INDEX($AN$9:$AN$48,IFERROR(MATCH($C$43,$AM$9:$AM$48,1),0))+(INDEX($AN$9:$AN$48,IFERROR(MATCH($C$43,$AM$9:$AM$48,1),0)+1)-INDEX($AN$9:$AN$48,IFERROR(MATCH($C$43,$AM$9:$AM$48,1),0)))*($C$43-INDEX($AM$9:$AM$48,IFERROR(MATCH($C$43,$AM$9:$AM$48,1),0)))/MAX(1E-9,INDEX($AM$9:$AM$48,IFERROR(MATCH($C$43,$AM$9:$AM$48,1),0)+1)-INDEX($AM$9:$AM$48,IFERROR(MATCH($C$43,$AM$9:$AM$48,1),0))))) | BV43: =IF(IFERROR(MATCH($C$43,$AW$9:$AW$48,1),0)<=0,INDEX($AX$9:$AX$48,1),IF(IFERROR(MATCH($C$43,$AW$9:$AW$48,1),0)>=40,INDEX($AX$9:$AX$48,40),INDEX($AX$9:$AX$48,IFERROR(MATCH($C$43,$AW$9:$AW$48,1),0))+(INDEX($AX$9:$AX$48,IFERROR(MATCH($C$43,$AW$9:$AW$48,1),0)+1)-INDEX($AX$9:$AX$48,IFERROR(MATCH($C$43,$AW$9:$AW$48,1),0)))*($C$43-INDEX($AW$9:$AW$48,IFERROR(MATCH($C$43,$AW$9:$AW$48,1),0)))/MAX(1E-9,INDEX($AW$9:$AW$48,IFERROR(MATCH($C$43,$AW$9:$AW$48,1),0)+1)-INDEX($AW$9:$AW$48,IFERROR(MATCH($C$43,$AW$9:$AW$48,1),0)))))
B44: 1.25(CM+CV) − SY | C44: 116 | D44: -11 | E44: 1 | F44: =BI44 | G44: =BJ44 | H44: =BR44 | AK44: =1.5*$D$15 | AL44: =MIN($D$66*AK44,$D$15) | AM44: =(0.85*$D$11*AL44*$D$14+SUMPRODUCT($AF$8:$AF$17,(ABS(6000*(1-$AE$8:$AE$17/AK44)+$D$12)-ABS(6000*(1-$AE$8:$AE$17/AK44)-$D$12))/2-0.85*$D$11*($AE$8:$AE$17<AL44)))/1000 | AN44: =(0.85*$D$11*AL44*$D$14*($D$15/2-AL44/2)+SUMPRODUCT($AF$8:$AF$17,(ABS(6000*(1-$AE$8:$AE$17/AK44)+$D$12)-ABS(6000*(1-$AE$8:$AE$17/AK44)-$D$12))/2-0.85*$D$11*($AE$8:$AE$17<AL44),$D$15/2-$AE$8:$AE$17))/100000 | AO44: =IF(AM44<=0,0.9,MAX(0.7,0.9/(1+0.2*AM44/$D$71))) | AP44: =MIN(AO44*AM44,$D$68) | AQ44: =MAX(0,AO44*AN44) | AR44: =IF(AS44>0,-AQ44/AS44,-1E+9) | AS44: =AO44*AM44 | AU44: =1.5*$D$14 | AV44: =MIN($D$66*AU44,$D$14) | AW44: =(0.85*$D$11*AV44*$D$15+SUMPRODUCT($AH$8:$AH$17,(ABS(6000*(1-$AG$8:$AG$17/AU44)+$D$12)-ABS(6000*(1-$AG$8:$AG$17/AU44)-$D$12))/2-0.85*$D$11*($AG$8:$AG$17<AV44)))/1000 | AX44: =(0.85*$D$11*AV44*$D$15*($D$14/2-AV44/2)+SUMPRODUCT($AH$8:$AH$17,(ABS(6000*(1-$AG$8:$AG$17/AU44)+$D$12)-ABS(6000*(1-$AG$8:$AG$17/AU44)-$D$12))/2-0.85*$D$11*($AG$8:$AG$17<AV44),$D$14/2-$AG$8:$AG$17))/100000 | AY44: =IF(AW44<=0,0.9,MAX(0.7,0.9/(1+0.2*AW44/$D$72))) | AZ44: =MIN(AY44*AW44,$D$68) | BA44: =MAX(0,AY44*AX44) | BB44: =IF(BC44>0,-BA44/BC44,-1E+9) | BC44: =AY44*AW44 | BE44: =BS44*IF(AND($D$74>=$D$73,$D$26="Sí"),MAX(ABS($D$44),MAX(0,$C$44)*(1.5+0.03*$D$15)/100),ABS($D$44)) | BF44: =BT44*IF(AND($D$75>=$D$73,$D$26="Sí"),MAX(ABS($E$44),MAX(0,$C$44)*(1.5+0.03*$D$14)/100),ABS($E$44)) | BG44: =IFERROR(MATCH($C$44,$AP$9:$AP$48,1),0) | BH44: =IFERROR(MATCH($C$44,$AZ$9:$AZ$48,1),0) | BI44: =IF(BG44<=0,INDEX($AQ$9:$AQ$48,1),IF(BG44>=40,INDEX($AQ$9:$AQ$48,40),INDEX($AQ$9:$AQ$48,BG44)+(INDEX($AQ$9:$AQ$48,BG44+1)-INDEX($AQ$9:$AQ$48,BG44))*($C$44-INDEX($AP$9:$AP$48,BG44))/MAX(1E-9,INDEX($AP$9:$AP$48,BG44+1)-INDEX($AP$9:$AP$48,BG44)))) | BJ44: =IF(BH44<=0,INDEX($BA$9:$BA$48,1),IF(BH44>=40,INDEX($BA$9:$BA$48,40),INDEX($BA$9:$BA$48,BH44)+(INDEX($BA$9:$BA$48,BH44+1)-INDEX($BA$9:$BA$48,BH44))*($C$44-INDEX($AZ$9:$AZ$48,BH44))/MAX(1E-9,INDEX($AZ$9:$AZ$48,BH44+1)-INDEX($AZ$9:$AZ$48,BH44)))) | BK44: =IF($C$44>0,BE44/$C$44,0) | BL44: =IF($C$44>0,BF44/$C$44,0) | BM44: =IFERROR(MATCH(-BK44,$AR$9:$AR$48,1),0) | BN44: =IFERROR(MATCH(-BL44,$BB$9:$BB$48,1),0) | BO44: =IF(BM44<=0,INDEX($AS$9:$AS$48,1),IF(BM44>=40,INDEX($AS$9:$AS$48,40),INDEX($AS$9:$AS$48,BM44)+(INDEX($AS$9:$AS$48,BM44+1)-INDEX($AS$9:$AS$48,BM44))*(-BK44-INDEX($AR$9:$AR$48,BM44))/MAX(1E-9,INDEX($AR$9:$AR$48,BM44+1)-INDEX($AR$9:$AR$48,BM44)))) | BP44: =IF(BN44<=0,INDEX($BC$9:$BC$48,1),IF(BN44>=40,INDEX($BC$9:$BC$48,40),INDEX($BC$9:$BC$48,BN44)+(INDEX($BC$9:$BC$48,BN44+1)-INDEX($BC$9:$BC$48,BN44))*(-BL44-INDEX($BB$9:$BB$48,BN44))/MAX(1E-9,INDEX($BB$9:$BB$48,BN44+1)-INDEX($BB$9:$BB$48,BN44)))) | BQ44: =IFERROR(1/(1/BO44+1/BP44-1/(0.7*$D$67)),0.0001) | BR44: =IF(AND($C$44=0,$D$44=0,$E$44=0),0,IF($C$44>$D$68,99,IF($C$44>=0.1*$D$11*$D$58/1000,$C$44/MAX(0.0001,MIN(BQ44,$D$68)),BE44/MAX(0.0001,BI44)+BF44/MAX(0.0001,BJ44)))) | BS44: =IF($D$74<$D$73,1,IF($D$26="Sí",IF($C$44>=0.75*$D$77,99,MAX(1,$D$79/(1-MAX(0,$C$44)/(0.75*$D$77)))),$D$80)) | BT44: =IF($D$75<$D$73,1,IF($D$26="Sí",IF($C$44>=0.75*$D$78,99,MAX(1,$D$79/(1-MAX(0,$C$44)/(0.75*$D$78)))),$D$80)) | BU44: =IF(IFERROR(MATCH($C$44,$AM$9:$AM$48,1),0)<=0,INDEX($AN$9:$AN$48,1),IF(IFERROR(MATCH($C$44,$AM$9:$AM$48,1),0)>=40,INDEX($AN$9:$AN$48,40),INDEX($AN$9:$AN$48,IFERROR(MATCH($C$44,$AM$9:$AM$48,1),0))+(INDEX($AN$9:$AN$48,IFERROR(MATCH($C$44,$AM$9:$AM$48,1),0)+1)-INDEX($AN$9:$AN$48,IFERROR(MATCH($C$44,$AM$9:$AM$48,1),0)))*($C$44-INDEX($AM$9:$AM$48,IFERROR(MATCH($C$44,$AM$9:$AM$48,1),0)))/MAX(1E-9,INDEX($AM$9:$AM$48,IFERROR(MATCH($C$44,$AM$9:$AM$48,1),0)+1)-INDEX($AM$9:$AM$48,IFERROR(MATCH($C$44,$AM$9:$AM$48,1),0))))) | BV44: =IF(IFERROR(MATCH($C$44,$AW$9:$AW$48,1),0)<=0,INDEX($AX$9:$AX$48,1),IF(IFERROR(MATCH($C$44,$AW$9:$AW$48,1),0)>=40,INDEX($AX$9:$AX$48,40),INDEX($AX$9:$AX$48,IFERROR(MATCH($C$44,$AW$9:$AW$48,1),0))+(INDEX($AX$9:$AX$48,IFERROR(MATCH($C$44,$AW$9:$AW$48,1),0)+1)-INDEX($AX$9:$AX$48,IFERROR(MATCH($C$44,$AW$9:$AW$48,1),0)))*($C$44-INDEX($AW$9:$AW$48,IFERROR(MATCH($C$44,$AW$9:$AW$48,1),0)))/MAX(1E-9,INDEX($AW$9:$AW$48,IFERROR(MATCH($C$44,$AW$9:$AW$48,1),0)+1)-INDEX($AW$9:$AW$48,IFERROR(MATCH($C$44,$AW$9:$AW$48,1),0)))))
B45: 0.9CM + SX | C45: 64 | D45: 2 | E45: 9 | F45: =BI45 | G45: =BJ45 | H45: =BR45 | AK45: =1.75*$D$15 | AL45: =MIN($D$66*AK45,$D$15) | AM45: =(0.85*$D$11*AL45*$D$14+SUMPRODUCT($AF$8:$AF$17,(ABS(6000*(1-$AE$8:$AE$17/AK45)+$D$12)-ABS(6000*(1-$AE$8:$AE$17/AK45)-$D$12))/2-0.85*$D$11*($AE$8:$AE$17<AL45)))/1000 | AN45: =(0.85*$D$11*AL45*$D$14*($D$15/2-AL45/2)+SUMPRODUCT($AF$8:$AF$17,(ABS(6000*(1-$AE$8:$AE$17/AK45)+$D$12)-ABS(6000*(1-$AE$8:$AE$17/AK45)-$D$12))/2-0.85*$D$11*($AE$8:$AE$17<AL45),$D$15/2-$AE$8:$AE$17))/100000 | AO45: =IF(AM45<=0,0.9,MAX(0.7,0.9/(1+0.2*AM45/$D$71))) | AP45: =MIN(AO45*AM45,$D$68) | AQ45: =MAX(0,AO45*AN45) | AR45: =IF(AS45>0,-AQ45/AS45,-1E+9) | AS45: =AO45*AM45 | AU45: =1.75*$D$14 | AV45: =MIN($D$66*AU45,$D$14) | AW45: =(0.85*$D$11*AV45*$D$15+SUMPRODUCT($AH$8:$AH$17,(ABS(6000*(1-$AG$8:$AG$17/AU45)+$D$12)-ABS(6000*(1-$AG$8:$AG$17/AU45)-$D$12))/2-0.85*$D$11*($AG$8:$AG$17<AV45)))/1000 | AX45: =(0.85*$D$11*AV45*$D$15*($D$14/2-AV45/2)+SUMPRODUCT($AH$8:$AH$17,(ABS(6000*(1-$AG$8:$AG$17/AU45)+$D$12)-ABS(6000*(1-$AG$8:$AG$17/AU45)-$D$12))/2-0.85*$D$11*($AG$8:$AG$17<AV45),$D$14/2-$AG$8:$AG$17))/100000 | AY45: =IF(AW45<=0,0.9,MAX(0.7,0.9/(1+0.2*AW45/$D$72))) | AZ45: =MIN(AY45*AW45,$D$68) | BA45: =MAX(0,AY45*AX45) | BB45: =IF(BC45>0,-BA45/BC45,-1E+9) | BC45: =AY45*AW45 | BE45: =BS45*IF(AND($D$74>=$D$73,$D$26="Sí"),MAX(ABS($D$45),MAX(0,$C$45)*(1.5+0.03*$D$15)/100),ABS($D$45)) | BF45: =BT45*IF(AND($D$75>=$D$73,$D$26="Sí"),MAX(ABS($E$45),MAX(0,$C$45)*(1.5+0.03*$D$14)/100),ABS($E$45)) | BG45: =IFERROR(MATCH($C$45,$AP$9:$AP$48,1),0) | BH45: =IFERROR(MATCH($C$45,$AZ$9:$AZ$48,1),0) | BI45: =IF(BG45<=0,INDEX($AQ$9:$AQ$48,1),IF(BG45>=40,INDEX($AQ$9:$AQ$48,40),INDEX($AQ$9:$AQ$48,BG45)+(INDEX($AQ$9:$AQ$48,BG45+1)-INDEX($AQ$9:$AQ$48,BG45))*($C$45-INDEX($AP$9:$AP$48,BG45))/MAX(1E-9,INDEX($AP$9:$AP$48,BG45+1)-INDEX($AP$9:$AP$48,BG45)))) | BJ45: =IF(BH45<=0,INDEX($BA$9:$BA$48,1),IF(BH45>=40,INDEX($BA$9:$BA$48,40),INDEX($BA$9:$BA$48,BH45)+(INDEX($BA$9:$BA$48,BH45+1)-INDEX($BA$9:$BA$48,BH45))*($C$45-INDEX($AZ$9:$AZ$48,BH45))/MAX(1E-9,INDEX($AZ$9:$AZ$48,BH45+1)-INDEX($AZ$9:$AZ$48,BH45)))) | BK45: =IF($C$45>0,BE45/$C$45,0) | BL45: =IF($C$45>0,BF45/$C$45,0) | BM45: =IFERROR(MATCH(-BK45,$AR$9:$AR$48,1),0) | BN45: =IFERROR(MATCH(-BL45,$BB$9:$BB$48,1),0) | BO45: =IF(BM45<=0,INDEX($AS$9:$AS$48,1),IF(BM45>=40,INDEX($AS$9:$AS$48,40),INDEX($AS$9:$AS$48,BM45)+(INDEX($AS$9:$AS$48,BM45+1)-INDEX($AS$9:$AS$48,BM45))*(-BK45-INDEX($AR$9:$AR$48,BM45))/MAX(1E-9,INDEX($AR$9:$AR$48,BM45+1)-INDEX($AR$9:$AR$48,BM45)))) | BP45: =IF(BN45<=0,INDEX($BC$9:$BC$48,1),IF(BN45>=40,INDEX($BC$9:$BC$48,40),INDEX($BC$9:$BC$48,BN45)+(INDEX($BC$9:$BC$48,BN45+1)-INDEX($BC$9:$BC$48,BN45))*(-BL45-INDEX($BB$9:$BB$48,BN45))/MAX(1E-9,INDEX($BB$9:$BB$48,BN45+1)-INDEX($BB$9:$BB$48,BN45)))) | BQ45: =IFERROR(1/(1/BO45+1/BP45-1/(0.7*$D$67)),0.0001) | BR45: =IF(AND($C$45=0,$D$45=0,$E$45=0),0,IF($C$45>$D$68,99,IF($C$45>=0.1*$D$11*$D$58/1000,$C$45/MAX(0.0001,MIN(BQ45,$D$68)),BE45/MAX(0.0001,BI45)+BF45/MAX(0.0001,BJ45)))) | BS45: =IF($D$74<$D$73,1,IF($D$26="Sí",IF($C$45>=0.75*$D$77,99,MAX(1,$D$79/(1-MAX(0,$C$45)/(0.75*$D$77)))),$D$80)) | BT45: =IF($D$75<$D$73,1,IF($D$26="Sí",IF($C$45>=0.75*$D$78,99,MAX(1,$D$79/(1-MAX(0,$C$45)/(0.75*$D$78)))),$D$80)) | BU45: =IF(IFERROR(MATCH($C$45,$AM$9:$AM$48,1),0)<=0,INDEX($AN$9:$AN$48,1),IF(IFERROR(MATCH($C$45,$AM$9:$AM$48,1),0)>=40,INDEX($AN$9:$AN$48,40),INDEX($AN$9:$AN$48,IFERROR(MATCH($C$45,$AM$9:$AM$48,1),0))+(INDEX($AN$9:$AN$48,IFERROR(MATCH($C$45,$AM$9:$AM$48,1),0)+1)-INDEX($AN$9:$AN$48,IFERROR(MATCH($C$45,$AM$9:$AM$48,1),0)))*($C$45-INDEX($AM$9:$AM$48,IFERROR(MATCH($C$45,$AM$9:$AM$48,1),0)))/MAX(1E-9,INDEX($AM$9:$AM$48,IFERROR(MATCH($C$45,$AM$9:$AM$48,1),0)+1)-INDEX($AM$9:$AM$48,IFERROR(MATCH($C$45,$AM$9:$AM$48,1),0))))) | BV45: =IF(IFERROR(MATCH($C$45,$AW$9:$AW$48,1),0)<=0,INDEX($AX$9:$AX$48,1),IF(IFERROR(MATCH($C$45,$AW$9:$AW$48,1),0)>=40,INDEX($AX$9:$AX$48,40),INDEX($AX$9:$AX$48,IFERROR(MATCH($C$45,$AW$9:$AW$48,1),0))+(INDEX($AX$9:$AX$48,IFERROR(MATCH($C$45,$AW$9:$AW$48,1),0)+1)-INDEX($AX$9:$AX$48,IFERROR(MATCH($C$45,$AW$9:$AW$48,1),0)))*($C$45-INDEX($AW$9:$AW$48,IFERROR(MATCH($C$45,$AW$9:$AW$48,1),0)))/MAX(1E-9,INDEX($AW$9:$AW$48,IFERROR(MATCH($C$45,$AW$9:$AW$48,1),0)+1)-INDEX($AW$9:$AW$48,IFERROR(MATCH($C$45,$AW$9:$AW$48,1),0)))))
B46: 0.9CM − SX | C46: 58 | D46: 1.5 | E46: -8.5 | F46: =BI46 | G46: =BJ46 | H46: =BR46 | AK46: =2.0*$D$15 | AL46: =MIN($D$66*AK46,$D$15) | AM46: =(0.85*$D$11*AL46*$D$14+SUMPRODUCT($AF$8:$AF$17,(ABS(6000*(1-$AE$8:$AE$17/AK46)+$D$12)-ABS(6000*(1-$AE$8:$AE$17/AK46)-$D$12))/2-0.85*$D$11*($AE$8:$AE$17<AL46)))/1000 | AN46: =(0.85*$D$11*AL46*$D$14*($D$15/2-AL46/2)+SUMPRODUCT($AF$8:$AF$17,(ABS(6000*(1-$AE$8:$AE$17/AK46)+$D$12)-ABS(6000*(1-$AE$8:$AE$17/AK46)-$D$12))/2-0.85*$D$11*($AE$8:$AE$17<AL46),$D$15/2-$AE$8:$AE$17))/100000 | AO46: =IF(AM46<=0,0.9,MAX(0.7,0.9/(1+0.2*AM46/$D$71))) | AP46: =MIN(AO46*AM46,$D$68) | AQ46: =MAX(0,AO46*AN46) | AR46: =IF(AS46>0,-AQ46/AS46,-1E+9) | AS46: =AO46*AM46 | AU46: =2.0*$D$14 | AV46: =MIN($D$66*AU46,$D$14) | AW46: =(0.85*$D$11*AV46*$D$15+SUMPRODUCT($AH$8:$AH$17,(ABS(6000*(1-$AG$8:$AG$17/AU46)+$D$12)-ABS(6000*(1-$AG$8:$AG$17/AU46)-$D$12))/2-0.85*$D$11*($AG$8:$AG$17<AV46)))/1000 | AX46: =(0.85*$D$11*AV46*$D$15*($D$14/2-AV46/2)+SUMPRODUCT($AH$8:$AH$17,(ABS(6000*(1-$AG$8:$AG$17/AU46)+$D$12)-ABS(6000*(1-$AG$8:$AG$17/AU46)-$D$12))/2-0.85*$D$11*($AG$8:$AG$17<AV46),$D$14/2-$AG$8:$AG$17))/100000 | AY46: =IF(AW46<=0,0.9,MAX(0.7,0.9/(1+0.2*AW46/$D$72))) | AZ46: =MIN(AY46*AW46,$D$68) | BA46: =MAX(0,AY46*AX46) | BB46: =IF(BC46>0,-BA46/BC46,-1E+9) | BC46: =AY46*AW46 | BE46: =BS46*IF(AND($D$74>=$D$73,$D$26="Sí"),MAX(ABS($D$46),MAX(0,$C$46)*(1.5+0.03*$D$15)/100),ABS($D$46)) | BF46: =BT46*IF(AND($D$75>=$D$73,$D$26="Sí"),MAX(ABS($E$46),MAX(0,$C$46)*(1.5+0.03*$D$14)/100),ABS($E$46)) | BG46: =IFERROR(MATCH($C$46,$AP$9:$AP$48,1),0) | BH46: =IFERROR(MATCH($C$46,$AZ$9:$AZ$48,1),0) | BI46: =IF(BG46<=0,INDEX($AQ$9:$AQ$48,1),IF(BG46>=40,INDEX($AQ$9:$AQ$48,40),INDEX($AQ$9:$AQ$48,BG46)+(INDEX($AQ$9:$AQ$48,BG46+1)-INDEX($AQ$9:$AQ$48,BG46))*($C$46-INDEX($AP$9:$AP$48,BG46))/MAX(1E-9,INDEX($AP$9:$AP$48,BG46+1)-INDEX($AP$9:$AP$48,BG46)))) | BJ46: =IF(BH46<=0,INDEX($BA$9:$BA$48,1),IF(BH46>=40,INDEX($BA$9:$BA$48,40),INDEX($BA$9:$BA$48,BH46)+(INDEX($BA$9:$BA$48,BH46+1)-INDEX($BA$9:$BA$48,BH46))*($C$46-INDEX($AZ$9:$AZ$48,BH46))/MAX(1E-9,INDEX($AZ$9:$AZ$48,BH46+1)-INDEX($AZ$9:$AZ$48,BH46)))) | BK46: =IF($C$46>0,BE46/$C$46,0) | BL46: =IF($C$46>0,BF46/$C$46,0) | BM46: =IFERROR(MATCH(-BK46,$AR$9:$AR$48,1),0) | BN46: =IFERROR(MATCH(-BL46,$BB$9:$BB$48,1),0) | BO46: =IF(BM46<=0,INDEX($AS$9:$AS$48,1),IF(BM46>=40,INDEX($AS$9:$AS$48,40),INDEX($AS$9:$AS$48,BM46)+(INDEX($AS$9:$AS$48,BM46+1)-INDEX($AS$9:$AS$48,BM46))*(-BK46-INDEX($AR$9:$AR$48,BM46))/MAX(1E-9,INDEX($AR$9:$AR$48,BM46+1)-INDEX($AR$9:$AR$48,BM46)))) | BP46: =IF(BN46<=0,INDEX($BC$9:$BC$48,1),IF(BN46>=40,INDEX($BC$9:$BC$48,40),INDEX($BC$9:$BC$48,BN46)+(INDEX($BC$9:$BC$48,BN46+1)-INDEX($BC$9:$BC$48,BN46))*(-BL46-INDEX($BB$9:$BB$48,BN46))/MAX(1E-9,INDEX($BB$9:$BB$48,BN46+1)-INDEX($BB$9:$BB$48,BN46)))) | BQ46: =IFERROR(1/(1/BO46+1/BP46-1/(0.7*$D$67)),0.0001) | BR46: =IF(AND($C$46=0,$D$46=0,$E$46=0),0,IF($C$46>$D$68,99,IF($C$46>=0.1*$D$11*$D$58/1000,$C$46/MAX(0.0001,MIN(BQ46,$D$68)),BE46/MAX(0.0001,BI46)+BF46/MAX(0.0001,BJ46)))) | BS46: =IF($D$74<$D$73,1,IF($D$26="Sí",IF($C$46>=0.75*$D$77,99,MAX(1,$D$79/(1-MAX(0,$C$46)/(0.75*$D$77)))),$D$80)) | BT46: =IF($D$75<$D$73,1,IF($D$26="Sí",IF($C$46>=0.75*$D$78,99,MAX(1,$D$79/(1-MAX(0,$C$46)/(0.75*$D$78)))),$D$80)) | BU46: =IF(IFERROR(MATCH($C$46,$AM$9:$AM$48,1),0)<=0,INDEX($AN$9:$AN$48,1),IF(IFERROR(MATCH($C$46,$AM$9:$AM$48,1),0)>=40,INDEX($AN$9:$AN$48,40),INDEX($AN$9:$AN$48,IFERROR(MATCH($C$46,$AM$9:$AM$48,1),0))+(INDEX($AN$9:$AN$48,IFERROR(MATCH($C$46,$AM$9:$AM$48,1),0)+1)-INDEX($AN$9:$AN$48,IFERROR(MATCH($C$46,$AM$9:$AM$48,1),0)))*($C$46-INDEX($AM$9:$AM$48,IFERROR(MATCH($C$46,$AM$9:$AM$48,1),0)))/MAX(1E-9,INDEX($AM$9:$AM$48,IFERROR(MATCH($C$46,$AM$9:$AM$48,1),0)+1)-INDEX($AM$9:$AM$48,IFERROR(MATCH($C$46,$AM$9:$AM$48,1),0))))) | BV46: =IF(IFERROR(MATCH($C$46,$AW$9:$AW$48,1),0)<=0,INDEX($AX$9:$AX$48,1),IF(IFERROR(MATCH($C$46,$AW$9:$AW$48,1),0)>=40,INDEX($AX$9:$AX$48,40),INDEX($AX$9:$AX$48,IFERROR(MATCH($C$46,$AW$9:$AW$48,1),0))+(INDEX($AX$9:$AX$48,IFERROR(MATCH($C$46,$AW$9:$AW$48,1),0)+1)-INDEX($AX$9:$AX$48,IFERROR(MATCH($C$46,$AW$9:$AW$48,1),0)))*($C$46-INDEX($AW$9:$AW$48,IFERROR(MATCH($C$46,$AW$9:$AW$48,1),0)))/MAX(1E-9,INDEX($AW$9:$AW$48,IFERROR(MATCH($C$46,$AW$9:$AW$48,1),0)+1)-INDEX($AW$9:$AW$48,IFERROR(MATCH($C$46,$AW$9:$AW$48,1),0)))))
B47: 0.9CM + SY | C47: 70 | D47: 12.5 | E47: 1.5 | F47: =BI47 | G47: =BJ47 | H47: =BR47 | AK47: =3.0*$D$15 | AL47: =MIN($D$66*AK47,$D$15) | AM47: =(0.85*$D$11*AL47*$D$14+SUMPRODUCT($AF$8:$AF$17,(ABS(6000*(1-$AE$8:$AE$17/AK47)+$D$12)-ABS(6000*(1-$AE$8:$AE$17/AK47)-$D$12))/2-0.85*$D$11*($AE$8:$AE$17<AL47)))/1000 | AN47: =(0.85*$D$11*AL47*$D$14*($D$15/2-AL47/2)+SUMPRODUCT($AF$8:$AF$17,(ABS(6000*(1-$AE$8:$AE$17/AK47)+$D$12)-ABS(6000*(1-$AE$8:$AE$17/AK47)-$D$12))/2-0.85*$D$11*($AE$8:$AE$17<AL47),$D$15/2-$AE$8:$AE$17))/100000 | AO47: =IF(AM47<=0,0.9,MAX(0.7,0.9/(1+0.2*AM47/$D$71))) | AP47: =MIN(AO47*AM47,$D$68) | AQ47: =MAX(0,AO47*AN47) | AR47: =IF(AS47>0,-AQ47/AS47,-1E+9) | AS47: =AO47*AM47 | AU47: =3.0*$D$14 | AV47: =MIN($D$66*AU47,$D$14) | AW47: =(0.85*$D$11*AV47*$D$15+SUMPRODUCT($AH$8:$AH$17,(ABS(6000*(1-$AG$8:$AG$17/AU47)+$D$12)-ABS(6000*(1-$AG$8:$AG$17/AU47)-$D$12))/2-0.85*$D$11*($AG$8:$AG$17<AV47)))/1000 | AX47: =(0.85*$D$11*AV47*$D$15*($D$14/2-AV47/2)+SUMPRODUCT($AH$8:$AH$17,(ABS(6000*(1-$AG$8:$AG$17/AU47)+$D$12)-ABS(6000*(1-$AG$8:$AG$17/AU47)-$D$12))/2-0.85*$D$11*($AG$8:$AG$17<AV47),$D$14/2-$AG$8:$AG$17))/100000 | AY47: =IF(AW47<=0,0.9,MAX(0.7,0.9/(1+0.2*AW47/$D$72))) | AZ47: =MIN(AY47*AW47,$D$68) | BA47: =MAX(0,AY47*AX47) | BB47: =IF(BC47>0,-BA47/BC47,-1E+9) | BC47: =AY47*AW47 | BE47: =BS47*IF(AND($D$74>=$D$73,$D$26="Sí"),MAX(ABS($D$47),MAX(0,$C$47)*(1.5+0.03*$D$15)/100),ABS($D$47)) | BF47: =BT47*IF(AND($D$75>=$D$73,$D$26="Sí"),MAX(ABS($E$47),MAX(0,$C$47)*(1.5+0.03*$D$14)/100),ABS($E$47)) | BG47: =IFERROR(MATCH($C$47,$AP$9:$AP$48,1),0) | BH47: =IFERROR(MATCH($C$47,$AZ$9:$AZ$48,1),0) | BI47: =IF(BG47<=0,INDEX($AQ$9:$AQ$48,1),IF(BG47>=40,INDEX($AQ$9:$AQ$48,40),INDEX($AQ$9:$AQ$48,BG47)+(INDEX($AQ$9:$AQ$48,BG47+1)-INDEX($AQ$9:$AQ$48,BG47))*($C$47-INDEX($AP$9:$AP$48,BG47))/MAX(1E-9,INDEX($AP$9:$AP$48,BG47+1)-INDEX($AP$9:$AP$48,BG47)))) | BJ47: =IF(BH47<=0,INDEX($BA$9:$BA$48,1),IF(BH47>=40,INDEX($BA$9:$BA$48,40),INDEX($BA$9:$BA$48,BH47)+(INDEX($BA$9:$BA$48,BH47+1)-INDEX($BA$9:$BA$48,BH47))*($C$47-INDEX($AZ$9:$AZ$48,BH47))/MAX(1E-9,INDEX($AZ$9:$AZ$48,BH47+1)-INDEX($AZ$9:$AZ$48,BH47)))) | BK47: =IF($C$47>0,BE47/$C$47,0) | BL47: =IF($C$47>0,BF47/$C$47,0) | BM47: =IFERROR(MATCH(-BK47,$AR$9:$AR$48,1),0) | BN47: =IFERROR(MATCH(-BL47,$BB$9:$BB$48,1),0) | BO47: =IF(BM47<=0,INDEX($AS$9:$AS$48,1),IF(BM47>=40,INDEX($AS$9:$AS$48,40),INDEX($AS$9:$AS$48,BM47)+(INDEX($AS$9:$AS$48,BM47+1)-INDEX($AS$9:$AS$48,BM47))*(-BK47-INDEX($AR$9:$AR$48,BM47))/MAX(1E-9,INDEX($AR$9:$AR$48,BM47+1)-INDEX($AR$9:$AR$48,BM47)))) | BP47: =IF(BN47<=0,INDEX($BC$9:$BC$48,1),IF(BN47>=40,INDEX($BC$9:$BC$48,40),INDEX($BC$9:$BC$48,BN47)+(INDEX($BC$9:$BC$48,BN47+1)-INDEX($BC$9:$BC$48,BN47))*(-BL47-INDEX($BB$9:$BB$48,BN47))/MAX(1E-9,INDEX($BB$9:$BB$48,BN47+1)-INDEX($BB$9:$BB$48,BN47)))) | BQ47: =IFERROR(1/(1/BO47+1/BP47-1/(0.7*$D$67)),0.0001) | BR47: =IF(AND($C$47=0,$D$47=0,$E$47=0),0,IF($C$47>$D$68,99,IF($C$47>=0.1*$D$11*$D$58/1000,$C$47/MAX(0.0001,MIN(BQ47,$D$68)),BE47/MAX(0.0001,BI47)+BF47/MAX(0.0001,BJ47)))) | BS47: =IF($D$74<$D$73,1,IF($D$26="Sí",IF($C$47>=0.75*$D$77,99,MAX(1,$D$79/(1-MAX(0,$C$47)/(0.75*$D$77)))),$D$80)) | BT47: =IF($D$75<$D$73,1,IF($D$26="Sí",IF($C$47>=0.75*$D$78,99,MAX(1,$D$79/(1-MAX(0,$C$47)/(0.75*$D$78)))),$D$80)) | BU47: =IF(IFERROR(MATCH($C$47,$AM$9:$AM$48,1),0)<=0,INDEX($AN$9:$AN$48,1),IF(IFERROR(MATCH($C$47,$AM$9:$AM$48,1),0)>=40,INDEX($AN$9:$AN$48,40),INDEX($AN$9:$AN$48,IFERROR(MATCH($C$47,$AM$9:$AM$48,1),0))+(INDEX($AN$9:$AN$48,IFERROR(MATCH($C$47,$AM$9:$AM$48,1),0)+1)-INDEX($AN$9:$AN$48,IFERROR(MATCH($C$47,$AM$9:$AM$48,1),0)))*($C$47-INDEX($AM$9:$AM$48,IFERROR(MATCH($C$47,$AM$9:$AM$48,1),0)))/MAX(1E-9,INDEX($AM$9:$AM$48,IFERROR(MATCH($C$47,$AM$9:$AM$48,1),0)+1)-INDEX($AM$9:$AM$48,IFERROR(MATCH($C$47,$AM$9:$AM$48,1),0))))) | BV47: =IF(IFERROR(MATCH($C$47,$AW$9:$AW$48,1),0)<=0,INDEX($AX$9:$AX$48,1),IF(IFERROR(MATCH($C$47,$AW$9:$AW$48,1),0)>=40,INDEX($AX$9:$AX$48,40),INDEX($AX$9:$AX$48,IFERROR(MATCH($C$47,$AW$9:$AW$48,1),0))+(INDEX($AX$9:$AX$48,IFERROR(MATCH($C$47,$AW$9:$AW$48,1),0)+1)-INDEX($AX$9:$AX$48,IFERROR(MATCH($C$47,$AW$9:$AW$48,1),0)))*($C$47-INDEX($AW$9:$AW$48,IFERROR(MATCH($C$47,$AW$9:$AW$48,1),0)))/MAX(1E-9,INDEX($AW$9:$AW$48,IFERROR(MATCH($C$47,$AW$9:$AW$48,1),0)+1)-INDEX($AW$9:$AW$48,IFERROR(MATCH($C$47,$AW$9:$AW$48,1),0)))))
B48: 0.9CM − SY | C48: 52 | D48: -11.5 | E48: 1 | F48: =BI48 | G48: =BJ48 | H48: =BR48 | AK48: =10.0*$D$15 | AL48: =MIN($D$66*AK48,$D$15) | AM48: =(0.85*$D$11*AL48*$D$14+SUMPRODUCT($AF$8:$AF$17,(ABS(6000*(1-$AE$8:$AE$17/AK48)+$D$12)-ABS(6000*(1-$AE$8:$AE$17/AK48)-$D$12))/2-0.85*$D$11*($AE$8:$AE$17<AL48)))/1000 | AN48: =(0.85*$D$11*AL48*$D$14*($D$15/2-AL48/2)+SUMPRODUCT($AF$8:$AF$17,(ABS(6000*(1-$AE$8:$AE$17/AK48)+$D$12)-ABS(6000*(1-$AE$8:$AE$17/AK48)-$D$12))/2-0.85*$D$11*($AE$8:$AE$17<AL48),$D$15/2-$AE$8:$AE$17))/100000 | AO48: =IF(AM48<=0,0.9,MAX(0.7,0.9/(1+0.2*AM48/$D$71))) | AP48: =MIN(AO48*AM48,$D$68) | AQ48: =MAX(0,AO48*AN48) | AR48: =IF(AS48>0,-AQ48/AS48,-1E+9) | AS48: =AO48*AM48 | AU48: =10.0*$D$14 | AV48: =MIN($D$66*AU48,$D$14) | AW48: =(0.85*$D$11*AV48*$D$15+SUMPRODUCT($AH$8:$AH$17,(ABS(6000*(1-$AG$8:$AG$17/AU48)+$D$12)-ABS(6000*(1-$AG$8:$AG$17/AU48)-$D$12))/2-0.85*$D$11*($AG$8:$AG$17<AV48)))/1000 | AX48: =(0.85*$D$11*AV48*$D$15*($D$14/2-AV48/2)+SUMPRODUCT($AH$8:$AH$17,(ABS(6000*(1-$AG$8:$AG$17/AU48)+$D$12)-ABS(6000*(1-$AG$8:$AG$17/AU48)-$D$12))/2-0.85*$D$11*($AG$8:$AG$17<AV48),$D$14/2-$AG$8:$AG$17))/100000 | AY48: =IF(AW48<=0,0.9,MAX(0.7,0.9/(1+0.2*AW48/$D$72))) | AZ48: =MIN(AY48*AW48,$D$68) | BA48: =MAX(0,AY48*AX48) | BB48: =IF(BC48>0,-BA48/BC48,-1E+9) | BC48: =AY48*AW48 | BE48: =BS48*IF(AND($D$74>=$D$73,$D$26="Sí"),MAX(ABS($D$48),MAX(0,$C$48)*(1.5+0.03*$D$15)/100),ABS($D$48)) | BF48: =BT48*IF(AND($D$75>=$D$73,$D$26="Sí"),MAX(ABS($E$48),MAX(0,$C$48)*(1.5+0.03*$D$14)/100),ABS($E$48)) | BG48: =IFERROR(MATCH($C$48,$AP$9:$AP$48,1),0) | BH48: =IFERROR(MATCH($C$48,$AZ$9:$AZ$48,1),0) | BI48: =IF(BG48<=0,INDEX($AQ$9:$AQ$48,1),IF(BG48>=40,INDEX($AQ$9:$AQ$48,40),INDEX($AQ$9:$AQ$48,BG48)+(INDEX($AQ$9:$AQ$48,BG48+1)-INDEX($AQ$9:$AQ$48,BG48))*($C$48-INDEX($AP$9:$AP$48,BG48))/MAX(1E-9,INDEX($AP$9:$AP$48,BG48+1)-INDEX($AP$9:$AP$48,BG48)))) | BJ48: =IF(BH48<=0,INDEX($BA$9:$BA$48,1),IF(BH48>=40,INDEX($BA$9:$BA$48,40),INDEX($BA$9:$BA$48,BH48)+(INDEX($BA$9:$BA$48,BH48+1)-INDEX($BA$9:$BA$48,BH48))*($C$48-INDEX($AZ$9:$AZ$48,BH48))/MAX(1E-9,INDEX($AZ$9:$AZ$48,BH48+1)-INDEX($AZ$9:$AZ$48,BH48)))) | BK48: =IF($C$48>0,BE48/$C$48,0) | BL48: =IF($C$48>0,BF48/$C$48,0) | BM48: =IFERROR(MATCH(-BK48,$AR$9:$AR$48,1),0) | BN48: =IFERROR(MATCH(-BL48,$BB$9:$BB$48,1),0) | BO48: =IF(BM48<=0,INDEX($AS$9:$AS$48,1),IF(BM48>=40,INDEX($AS$9:$AS$48,40),INDEX($AS$9:$AS$48,BM48)+(INDEX($AS$9:$AS$48,BM48+1)-INDEX($AS$9:$AS$48,BM48))*(-BK48-INDEX($AR$9:$AR$48,BM48))/MAX(1E-9,INDEX($AR$9:$AR$48,BM48+1)-INDEX($AR$9:$AR$48,BM48)))) | BP48: =IF(BN48<=0,INDEX($BC$9:$BC$48,1),IF(BN48>=40,INDEX($BC$9:$BC$48,40),INDEX($BC$9:$BC$48,BN48)+(INDEX($BC$9:$BC$48,BN48+1)-INDEX($BC$9:$BC$48,BN48))*(-BL48-INDEX($BB$9:$BB$48,BN48))/MAX(1E-9,INDEX($BB$9:$BB$48,BN48+1)-INDEX($BB$9:$BB$48,BN48)))) | BQ48: =IFERROR(1/(1/BO48+1/BP48-1/(0.7*$D$67)),0.0001) | BR48: =IF(AND($C$48=0,$D$48=0,$E$48=0),0,IF($C$48>$D$68,99,IF($C$48>=0.1*$D$11*$D$58/1000,$C$48/MAX(0.0001,MIN(BQ48,$D$68)),BE48/MAX(0.0001,BI48)+BF48/MAX(0.0001,BJ48)))) | BS48: =IF($D$74<$D$73,1,IF($D$26="Sí",IF($C$48>=0.75*$D$77,99,MAX(1,$D$79/(1-MAX(0,$C$48)/(0.75*$D$77)))),$D$80)) | BT48: =IF($D$75<$D$73,1,IF($D$26="Sí",IF($C$48>=0.75*$D$78,99,MAX(1,$D$79/(1-MAX(0,$C$48)/(0.75*$D$78)))),$D$80)) | BU48: =IF(IFERROR(MATCH($C$48,$AM$9:$AM$48,1),0)<=0,INDEX($AN$9:$AN$48,1),IF(IFERROR(MATCH($C$48,$AM$9:$AM$48,1),0)>=40,INDEX($AN$9:$AN$48,40),INDEX($AN$9:$AN$48,IFERROR(MATCH($C$48,$AM$9:$AM$48,1),0))+(INDEX($AN$9:$AN$48,IFERROR(MATCH($C$48,$AM$9:$AM$48,1),0)+1)-INDEX($AN$9:$AN$48,IFERROR(MATCH($C$48,$AM$9:$AM$48,1),0)))*($C$48-INDEX($AM$9:$AM$48,IFERROR(MATCH($C$48,$AM$9:$AM$48,1),0)))/MAX(1E-9,INDEX($AM$9:$AM$48,IFERROR(MATCH($C$48,$AM$9:$AM$48,1),0)+1)-INDEX($AM$9:$AM$48,IFERROR(MATCH($C$48,$AM$9:$AM$48,1),0))))) | BV48: =IF(IFERROR(MATCH($C$48,$AW$9:$AW$48,1),0)<=0,INDEX($AX$9:$AX$48,1),IF(IFERROR(MATCH($C$48,$AW$9:$AW$48,1),0)>=40,INDEX($AX$9:$AX$48,40),INDEX($AX$9:$AX$48,IFERROR(MATCH($C$48,$AW$9:$AW$48,1),0))+(INDEX($AX$9:$AX$48,IFERROR(MATCH($C$48,$AW$9:$AW$48,1),0)+1)-INDEX($AX$9:$AX$48,IFERROR(MATCH($C$48,$AW$9:$AW$48,1),0)))*($C$48-INDEX($AW$9:$AW$48,IFERROR(MATCH($C$48,$AW$9:$AW$48,1),0)))/MAX(1E-9,INDEX($AW$9:$AW$48,IFERROR(MATCH($C$48,$AW$9:$AW$48,1),0)+1)-INDEX($AW$9:$AW$48,IFERROR(MATCH($C$48,$AW$9:$AW$48,1),0)))))
B49: Copie las combinaciones de ETABS (Pu positivo en compresión). Puede dejar filas en 0. D/C se calcula con los momentos amplificados por esbeltez cuando corresponde.
B51: 2. PROPIEDADES DE LA SECCIÓN
B52: Diámetro de la varilla | C52: db | D52: =INDEX(BAR_DB,MATCH($D$17,BAR_NOM,0)) | E52: cm
B53: Área de la varilla | C53: Ab | D53: =INDEX(BAR_AS,MATCH($D$17,BAR_NOM,0)) | E53: cm²
B54: Diámetro del estribo | C54: dbe | D54: =INDEX(BAR_DB,MATCH($D$20,BAR_NOM,0)) | E54: cm
B55: Área del estribo | C55: Abe | D55: =INDEX(BAR_AS,MATCH($D$20,BAR_NOM,0)) | E55: cm²
B56: Número total de varillas 2nx + 2ny − 4 | C56: n | D56: =2*$D$18+2*$D$19-4
B57: Acero longitudinal total | C57: Ast | D57: =$D$56*$D$53 | E57: cm²
B58: Área bruta | C58: Ag | D58: =$D$14*$D$15 | E58: cm²
B59: Cuantía ρ = Ast/Ag | C59: ρ | D59: =$D$57/$D$58
B60: 1 % ≤ ρ ≤ 6 % (10.9.1 y 21) | C60: =IF(AND($D$59>=0.01-0.00001,$D$59<=0.06),"CUMPLE","NO CUMPLE") | F60: Si ρ > 4 %: detalle el nudo en los planos
B61: Recubrimiento al centro de la varilla | C61: rc | D61: =$D$16+$D$54+$D$52/2 | E61: cm
B62: Espacio libre entre varillas en la cara B | D62: =($D$14-2*$D$61)/MAX(1,$D$18-1)-$D$52 | E62: cm
B63: Espacio libre entre varillas en la cara H | D63: =($D$15-2*$D$61)/MAX(1,$D$19-1)-$D$52 | E63: cm
B64: Espacio libre ≥ máx(1.5db, 4 cm) | C64: =IF(MIN($D$62,$D$63)>=MAX(1.5*$D$52,4),"CUMPLE","NO CUMPLE") | F64: E.060 7.6.3
B65: Pórticos: lado menor ≥ 25 cm y relación ≥ 0.25 (21.6.1) | C65: =IF(OR(NOT($D$13="Pórticos o dual tipo II"),AND(MIN($D$14,$D$15)>=25,MIN($D$14,$D$15)/MAX($D$14,$D$15)>=0.25)),"CUMPLE","NO CUMPLE")
B66: Factor β1 | C66: β1 | D66: =IF($D$11<=280,0.85,MAX(0.65,0.85-0.05*($D$11-280)/70))
B67: Resistencia axial Po = 0.85f'c(Ag − Ast) + fy·Ast | C67: Po | D67: =(0.85*$D$11*($D$58-$D$57)+$D$12*$D$57)/1000 | E67: t
B68: φPn máx = 0.80·0.70·Po | C68: φPnmáx | D68: =0.8*0.7*$D$67 | E68: t | F68: E.060 10.3.6.2 (estribos)
B69: Carga balanceada (flexión en X) | C69: Pb | D69: =(0.85*$D$11*MIN($D$66*(6000*MAX($AE$8:$AE$17)/(6000+$D$12)),$D$15)*$D$14+SUMPRODUCT($AF$8:$AF$17,(ABS(6000*(1-$AE$8:$AE$17/(6000*MAX($AE$8:$AE$17)/(6000+$D$12)))+$D$12)-ABS(6000*(1-$AE$8:$AE$17/(6000*MAX($AE$8:$AE$17)/(6000+$D$12)))-$D$12))/2-0.85*$D$11*($AE$8:$AE$17<MIN($D$66*(6000*MAX($AE$8:$AE$17)/(6000+$D$12)),$D$15))))/1000 | E69: t
B70: Carga balanceada (flexión en Y) | C70: Pb | D70: =(0.85*$D$11*MIN($D$66*(6000*MAX($AG$8:$AG$17)/(6000+$D$12)),$D$14)*$D$15+SUMPRODUCT($AH$8:$AH$17,(ABS(6000*(1-$AG$8:$AG$17/(6000*MAX($AG$8:$AG$17)/(6000+$D$12)))+$D$12)-ABS(6000*(1-$AG$8:$AG$17/(6000*MAX($AG$8:$AG$17)/(6000+$D$12)))-$D$12))/2-0.85*$D$11*($AG$8:$AG$17<MIN($D$66*(6000*MAX($AG$8:$AG$17)/(6000+$D$12)),$D$14))))/1000 | E70: t
B71: Límite de transición de φ en X: mín(0.1f'c·Ag, φPb) | D71: =MAX(0.001,MIN(0.1*$D$11*$D$58/1000,0.7*$D$69)) | E71: t | F71: E.060 9.3.2.2: φ sube de 0.70 a 0.90
B72: Límite de transición de φ en Y | D72: =MAX(0.001,MIN(0.1*$D$11*$D$58/1000,0.7*$D$70)) | E72: t
B73: Esbeltez: límite k·lu/r | D73: =IF($D$26="Sí",MIN(40,34-12*$D$27),22) | F73: Arriostrado: 34 − 12·M1/M2 ≤ 40 · No arriostrado: 22 (10.12.2 / 10.13.2)
B74: Esbeltez: k·lu/r flexión en X (r = 0.3H) | D74: =$D$25*$D$24*100/(0.3*$D$15)
B75: Esbeltez: k·lu/r flexión en Y (r = 0.3B) | D75: =$D$25*$D$24*100/(0.3*$D$14)
B76: Módulo del concreto Ec = 15000√f'c | C76: Ec | D76: =15000*SQRT($D$11) | E76: kgf/cm²
B77: Carga crítica Pc = π²·0.4·Ec·Ig/((1+βd)(k·lu)²) en X | C77: Pc | D77: =PI()^2*0.4*$D$76*$D$14*$D$15^3/12/(1+$D$28)/($D$25*$D$24*100)^2/1000 | E77: t | F77: 10.12.3
B78: Carga crítica en Y | C78: Pc | D78: =PI()^2*0.4*$D$76*$D$15*$D$14^3/12/(1+$D$28)/($D$25*$D$24*100)^2/1000 | E78: t
B79: Cm = 0.6 + 0.4·M1/M2 ≥ 0.4 | C79: Cm | D79: =MAX(0.4,0.6+0.4*$D$27)
B80: δs = 1/(1 − Q) (no arriostrado) | C80: δs | D80: =IF($D$29>=1,99,1/(1-$D$29)) | F80: 10.13.4.1
B82: 3. VERIFICACIÓN POR FLEXOCOMPRESIÓN (E.060 10.3 y 9.3.2.2)
B83: φ = 0.70 en compresión; sube linealmente a 0.90 cuando φPn baja de mín(0.1f'c·Ag, φPb) a cero. Biaxial: Bresler (1/Pni = 1/Pnx + 1/Pny − 1/Po) si Pu ≥ 0.1f'c·Ag; si no, Mux/φMnx + Muy/φMny ≤ 1.
B84: Carga axial máxima de las combinaciones | C84: Pu máx | D84: =MAX($C$40:$C$48) | E84: t
B85: Pu máx ≤ φPn máx | C85: =IF($D$84<=$D$68,"CUMPLE","NO CUMPLE") | F85: Si no cumple: aumente la sección o f'c
B86: Relación demanda/capacidad máxima | C86: D/C | D86: =MAX($H$40:$H$48) | F86: Columna H de la tabla de combinaciones
B87: D/C ≤ 1.00 en todas las combinaciones | C87: =IF($D$86<=1.0001,"CUMPLE","NO CUMPLE") | F87: Si no cumple: más acero o mayor sección
B89: 4. ESBELTEZ (E.060 10.11–10.13)
B90: k·lu/r máximo / límite | D90: =FIXED(MAX($D$74,$D$75),1)&" / "&FIXED($D$73,1)
B91: Efectos de esbeltez | D91: =IF(MAX($D$74,$D$75)<$D$73,"Se desprecian (no se amplifican momentos)",IF($D$26="Sí","Se amplifican con δns = Cm/(1 − Pu/0.75Pc)","Se amplifican con δs = 1/(1 − Q)"))
B92: Factor de amplificación máximo usado | C92: δ máx | D92: =MAX(BS40:BT48) | F92: Los D/C de la tabla ya usan los momentos amplificados
B93: Esbeltez dentro de los límites (k·lu/r ≤ 100, Pu < 0.75Pc, δs ≤ 1.5) | C93: =IF(AND(MAX($D$74,$D$75)<=100,$D$92<99,OR($D$26="Sí",$D$80<=1.5)),"CUMPLE","NO CUMPLE") | F93: Si no cumple: aumente la sección o use análisis de segundo orden
B95: 5. CORTANTE POR CAPACIDAD Y CONFINAMIENTO (E.060 21.4 / 21.6)
B96: Factor de momento probable | C96: k | D96: =IF($D$13="Pórticos o dual tipo II",1.25,1.0) | F96: Pórticos: 1.25·Mn (21.6.5) · Muros: Mn (21.4.3)
B97: Mn máximo en X para Pn ≤ Pu máx | C97: Mnx | D97: =_xlfn.MAXIFS($AN$9:$AN$48,$AM$9:$AM$48,"<="&$D$84) | E97: t·m
B98: Mn máximo en Y para Pn ≤ Pu máx | C98: Mny | D98: =_xlfn.MAXIFS($AX$9:$AX$48,$AW$9:$AW$48,"<="&$D$84) | E98: t·m
B99: Carga axial mínima (para Vc) | C99: Nu | D99: =MAX(0,MIN($C$40:$C$48)) | E99: t
B100: Cortante en dirección Y
B101: Cortante por capacidad 2·k·Mn/hn | C101: Vcap | D101: =2*$D$96*$D$97/$D$24 | E101: t
B102: CORTANTE DE DISEÑO en Y | C102: Vu | D102: =IF($D$13="Pórticos o dual tipo II",MAX($D$34,$D$101),MAX($D$34,MIN($D$101,$D$34+1.5*$D$35))) | E102: t | F102: Muros: menor entre capacidad y Vua + 1.5·VS (= 2.5·sismo si Vua viene de 1.25(CM+CV) ± S)
B103: Vc = 0.53√f'c(1 + Nu/140Ag)·b·d | C103: Vc | D103: =IF(MIN($C$40:$C$48)<0,0,0.53*SQRT($D$11)*(1+$D$99*1000/(140*$D$58))*$D$14*($D$15-$D$61)/1000) | E103: t | F103: E.060 11.3.1.2
B104: Vs = Vu/φ − Vc | C104: Vs | D104: =MAX(0,$D$102/0.85-$D$103) | E104: t
...

Sheet PLACA
B1: DISEÑO DE PLACA (MURO ESTRUCTURAL) · NTE E.060 11.10 Y 21.9
B2: ALF_BIM · Plantilla Excel Estructuras · NTE E.060 Concreto Armado · v2.1.0
B3: Proyecto | C3: =INICIO!$D$7
B4: Ubicación | C4: =INICIO!$D$9
B5: Elemento | C5: Placa PL-1, 1er piso, eje 1
B6: Calculista | C6: =INICIO!$D$10&IF(INICIO!$D$11="",""," · CIP "&INICIO!$D$11) | AD6: Capas (no imprimir)
B7: Fecha | C7: =INICIO!$D$12 | AH7: Diagrama (no imprimir)
AD8: 1 | AE8: =$D$43 | AF8: =$D$26/2*$D$39 | AH8: c (cm) | AI8: a (cm) | AJ8: Pn (t) | AK8: Mn (t·m) | AL8: φ | AM8: φPn (t) | AN8: φMn (t·m) | AO8: −e (m) | AP8: φPn sin tope | BB8: =$D$20 | BC8: =$D$19
AD9: 2 | AE9: =$D$25-$D$43 | AF9: =$D$26/2*$D$39 | AH9: 0 | AI9: 0 | AJ9: =-$D$12*$D$47/1000 | AK9: 0 | AL9: 0.9 | AM9: =AL9*AJ9 | AN9: 0 | AO9: -1000000000 | AP9: =AM9
B10: 1. DATOS DE ENTRADA | AD10: 3 | AE10: =IF(1<=$D$46,$D$25+$D$44*1/($D$46+1),0) | AF10: =IF(1<=$D$46,$D$45*$D$32*$D$40/$D$46,0) | AH10: =0.02*$D$36 | AI10: =MIN($D$49*AH10,$D$36) | AJ10: =(0.85*$D$11*AI10*$D$14+SUMPRODUCT($AF$8:$AF$37,(ABS(6000*(1-$AE$8:$AE$37/AH10)+$D$12)-ABS(6000*(1-$AE$8:$AE$37/AH10)-$D$12))/2-0.85*$D$11*($AE$8:$AE$37<AI10)))/1000 | AK10: =(0.85*$D$11*AI10*$D$14*($D$36/2-AI10/2)+SUMPRODUCT($AF$8:$AF$37,(ABS(6000*(1-$AE$8:$AE$37/AH10)+$D$12)-ABS(6000*(1-$AE$8:$AE$37/AH10)-$D$12))/2-0.85*$D$11*($AE$8:$AE$37<AI10),$D$36/2-$AE$8:$AE$37))/100000 | AL10: =IF(AJ10<=0,0.9,MAX(0.7,0.9/(1+0.2*AJ10/$D$54))) | AM10: =MIN(AL10*AJ10,$D$51) | AN10: =MAX(0,AL10*AK10) | AO10: =IF(AP10>0,-AN10/AP10,-1E+9) | AP10: =AL10*AJ10
B11: Resistencia del concreto | C11: f'c | D11: 210 | E11: kgf/cm² | AD11: 4 | AE11: =IF(2<=$D$46,$D$25+$D$44*2/($D$46+1),0) | AF11: =IF(2<=$D$46,$D$45*$D$32*$D$40/$D$46,0) | AH11: =0.04*$D$36 | AI11: =MIN($D$49*AH11,$D$36) | AJ11: =(0.85*$D$11*AI11*$D$14+SUMPRODUCT($AF$8:$AF$37,(ABS(6000*(1-$AE$8:$AE$37/AH11)+$D$12)-ABS(6000*(1-$AE$8:$AE$37/AH11)-$D$12))/2-0.85*$D$11*($AE$8:$AE$37<AI11)))/1000 | AK11: =(0.85*$D$11*AI11*$D$14*($D$36/2-AI11/2)+SUMPRODUCT($AF$8:$AF$37,(ABS(6000*(1-$AE$8:$AE$37/AH11)+$D$12)-ABS(6000*(1-$AE$8:$AE$37/AH11)-$D$12))/2-0.85*$D$11*($AE$8:$AE$37<AI11),$D$36/2-$AE$8:$AE$37))/100000 | AL11: =IF(AJ11<=0,0.9,MAX(0.7,0.9/(1+0.2*AJ11/$D$54))) | AM11: =MIN(AL11*AJ11,$D$51) | AN11: =MAX(0,AL11*AK11) | AO11: =IF(AP11>0,-AN11/AP11,-1E+9) | AP11: =AL11*AJ11
B12: Fluencia del acero | C12: fy | D12: 4200 | E12: kgf/cm² | AD12: 5 | AE12: =IF(3<=$D$46,$D$25+$D$44*3/($D$46+1),0) | AF12: =IF(3<=$D$46,$D$45*$D$32*$D$40/$D$46,0) | AH12: =0.06*$D$36 | AI12: =MIN($D$49*AH12,$D$36) | AJ12: =(0.85*$D$11*AI12*$D$14+SUMPRODUCT($AF$8:$AF$37,(ABS(6000*(1-$AE$8:$AE$37/AH12)+$D$12)-ABS(6000*(1-$AE$8:$AE$37/AH12)-$D$12))/2-0.85*$D$11*($AE$8:$AE$37<AI12)))/1000 | AK12: =(0.85*$D$11*AI12*$D$14*($D$36/2-AI12/2)+SUMPRODUCT($AF$8:$AF$37,(ABS(6000*(1-$AE$8:$AE$37/AH12)+$D$12)-ABS(6000*(1-$AE$8:$AE$37/AH12)-$D$12))/2-0.85*$D$11*($AE$8:$AE$37<AI12),$D$36/2-$AE$8:$AE$37))/100000 | AL12: =IF(AJ12<=0,0.9,MAX(0.7,0.9/(1+0.2*AJ12/$D$54))) | AM12: =MIN(AL12*AJ12,$D$51) | AN12: =MAX(0,AL12*AK12) | AO12: =IF(AP12>0,-AN12/AP12,-1E+9) | AP12: =AL12*AJ12
B13: Longitud del muro | C13: lm | D13: 3 | E13: m | AD13: 6 | AE13: =IF(4<=$D$46,$D$25+$D$44*4/($D$46+1),0) | AF13: =IF(4<=$D$46,$D$45*$D$32*$D$40/$D$46,0) | AH13: =0.08*$D$36 | AI13: =MIN($D$49*AH13,$D$36) | AJ13: =(0.85*$D$11*AI13*$D$14+SUMPRODUCT($AF$8:$AF$37,(ABS(6000*(1-$AE$8:$AE$37/AH13)+$D$12)-ABS(6000*(1-$AE$8:$AE$37/AH13)-$D$12))/2-0.85*$D$11*($AE$8:$AE$37<AI13)))/1000 | AK13: =(0.85*$D$11*AI13*$D$14*($D$36/2-AI13/2)+SUMPRODUCT($AF$8:$AF$37,(ABS(6000*(1-$AE$8:$AE$37/AH13)+$D$12)-ABS(6000*(1-$AE$8:$AE$37/AH13)-$D$12))/2-0.85*$D$11*($AE$8:$AE$37<AI13),$D$36/2-$AE$8:$AE$37))/100000 | AL13: =IF(AJ13<=0,0.9,MAX(0.7,0.9/(1+0.2*AJ13/$D$54))) | AM13: =MIN(AL13*AJ13,$D$51) | AN13: =MAX(0,AL13*AK13) | AO13: =IF(AP13>0,-AN13/AP13,-1E+9) | AP13: =AL13*AJ13
B14: Espesor del muro | C14: t | D14: 25 | E14: cm | AD14: 7 | AE14: =IF(5<=$D$46,$D$25+$D$44*5/($D$46+1),0) | AF14: =IF(5<=$D$46,$D$45*$D$32*$D$40/$D$46,0) | AH14: =0.1*$D$36 | AI14: =MIN($D$49*AH14,$D$36) | AJ14: =(0.85*$D$11*AI14*$D$14+SUMPRODUCT($AF$8:$AF$37,(ABS(6000*(1-$AE$8:$AE$37/AH14)+$D$12)-ABS(6000*(1-$AE$8:$AE$37/AH14)-$D$12))/2-0.85*$D$11*($AE$8:$AE$37<AI14)))/1000 | AK14: =(0.85*$D$11*AI14*$D$14*($D$36/2-AI14/2)+SUMPRODUCT($AF$8:$AF$37,(ABS(6000*(1-$AE$8:$AE$37/AH14)+$D$12)-ABS(6000*(1-$AE$8:$AE$37/AH14)-$D$12))/2-0.85*$D$11*($AE$8:$AE$37<AI14),$D$36/2-$AE$8:$AE$37))/100000 | AL14: =IF(AJ14<=0,0.9,MAX(0.7,0.9/(1+0.2*AJ14/$D$54))) | AM14: =MIN(AL14*AJ14,$D$51) | AN14: =MAX(0,AL14*AK14) | AO14: =IF(AP14>0,-AN14/AP14,-1E+9) | AP14: =AL14*AJ14
B15: Altura total del muro | C15: hm | D15: 12 | E15: m | AD15: 8 | AE15: =IF(6<=$D$46,$D$25+$D$44*6/($D$46+1),0) | AF15: =IF(6<=$D$46,$D$45*$D$32*$D$40/$D$46,0) | AH15: =0.13*$D$36 | AI15: =MIN($D$49*AH15,$D$36) | AJ15: =(0.85*$D$11*AI15*$D$14+SUMPRODUCT($AF$8:$AF$37,(ABS(6000*(1-$AE$8:$AE$37/AH15)+$D$12)-ABS(6000*(1-$AE$8:$AE$37/AH15)-$D$12))/2-0.85*$D$11*($AE$8:$AE$37<AI15)))/1000 | AK15: =(0.85*$D$11*AI15*$D$14*($D$36/2-AI15/2)+SUMPRODUCT($AF$8:$AF$37,(ABS(6000*(1-$AE$8:$AE$37/AH15)+$D$12)-ABS(6000*(1-$AE$8:$AE$37/AH15)-$D$12))/2-0.85*$D$11*($AE$8:$AE$37<AI15),$D$36/2-$AE$8:$AE$37))/100000 | AL15: =IF(AJ15<=0,0.9,MAX(0.7,0.9/(1+0.2*AJ15/$D$54))) | AM15: =MIN(AL15*AJ15,$D$51) | AN15: =MAX(0,AL15*AK15) | AO15: =IF(AP15>0,-AN15/AP15,-1E+9) | AP15: =AL15*AJ15
B16: Altura libre del entrepiso | C16: hu | D16: 2.7 | E16: m | AD16: 9 | AE16: =IF(7<=$D$46,$D$25+$D$44*7/($D$46+1),0) | AF16: =IF(7<=$D$46,$D$45*$D$32*$D$40/$D$46,0) | AH16: =0.16*$D$36 | AI16: =MIN($D$49*AH16,$D$36) | AJ16: =(0.85*$D$11*AI16*$D$14+SUMPRODUCT($AF$8:$AF$37,(ABS(6000*(1-$AE$8:$AE$37/AH16)+$D$12)-ABS(6000*(1-$AE$8:$AE$37/AH16)-$D$12))/2-0.85*$D$11*($AE$8:$AE$37<AI16)))/1000 | AK16: =(0.85*$D$11*AI16*$D$14*($D$36/2-AI16/2)+SUMPRODUCT($AF$8:$AF$37,(ABS(6000*(1-$AE$8:$AE$37/AH16)+$D$12)-ABS(6000*(1-$AE$8:$AE$37/AH16)-$D$12))/2-0.85*$D$11*($AE$8:$AE$37<AI16),$D$36/2-$AE$8:$AE$37))/100000 | AL16: =IF(AJ16<=0,0.9,MAX(0.7,0.9/(1+0.2*AJ16/$D$54))) | AM16: =MIN(AL16*AJ16,$D$51) | AN16: =MAX(0,AL16*AK16) | AO16: =IF(AP16>0,-AN16/AP16,-1E+9) | AP16: =AL16*AJ16
B17: Coeficiente de reducción sísmica R | C17: R | D17: 6 | F17: Límite de Mn/Mua (21.9.5.3) | AD17: 10 | AE17: =IF(8<=$D$46,$D$25+$D$44*8/($D$46+1),0) | AF17: =IF(8<=$D$46,$D$45*$D$32*$D$40/$D$46,0) | AH17: =0.2*$D$36 | AI17: =MIN($D$49*AH17,$D$36) | AJ17: =(0.85*$D$11*AI17*$D$14+SUMPRODUCT($AF$8:$AF$37,(ABS(6000*(1-$AE$8:$AE$37/AH17)+$D$12)-ABS(6000*(1-$AE$8:$AE$37/AH17)-$D$12))/2-0.85*$D$11*($AE$8:$AE$37<AI17)))/1000 | AK17: =(0.85*$D$11*AI17*$D$14*($D$36/2-AI17/2)+SUMPRODUCT($AF$8:$AF$37,(ABS(6000*(1-$AE$8:$AE$37/AH17)+$D$12)-ABS(6000*(1-$AE$8:$AE$37/AH17)-$D$12))/2-0.85*$D$11*($AE$8:$AE$37<AI17),$D$36/2-$AE$8:$AE$37))/100000 | AL17: =IF(AJ17<=0,0.9,MAX(0.7,0.9/(1+0.2*AJ17/$D$54))) | AM17: =MIN(AL17*AJ17,$D$51) | AN17: =MAX(0,AL17*AK17) | AO17: =IF(AP17>0,-AN17/AP17,-1E+9) | AP17: =AL17*AJ17
B18: Fuerzas en la base (envolvente) | AD18: 11 | AE18: =IF(9<=$D$46,$D$25+$D$44*9/($D$46+1),0) | AF18: =IF(9<=$D$46,$D$45*$D$32*$D$40/$D$46,0) | AH18: =0.25*$D$36 | AI18: =MIN($D$49*AH18,$D$36) | AJ18: =(0.85*$D$11*AI18*$D$14+SUMPRODUCT($AF$8:$AF$37,(ABS(6000*(1-$AE$8:$AE$37/AH18)+$D$12)-ABS(6000*(1-$AE$8:$AE$37/AH18)-$D$12))/2-0.85*$D$11*($AE$8:$AE$37<AI18)))/1000 | AK18: =(0.85*$D$11*AI18*$D$14*($D$36/2-AI18/2)+SUMPRODUCT($AF$8:$AF$37,(ABS(6000*(1-$AE$8:$AE$37/AH18)+$D$12)-ABS(6000*(1-$AE$8:$AE$37/AH18)-$D$12))/2-0.85*$D$11*($AE$8:$AE$37<AI18),$D$36/2-$AE$8:$AE$37))/100000 | AL18: =IF(AJ18<=0,0.9,MAX(0.7,0.9/(1+0.2*AJ18/$D$54))) | AM18: =MIN(AL18*AJ18,$D$51) | AN18: =MAX(0,AL18*AK18) | AO18: =IF(AP18>0,-AN18/AP18,-1E+9) | AP18: =AL18*AJ18
B19: Carga axial última | C19: Pu | D19: 120 | E19: t | AD19: 12 | AE19: =IF(10<=$D$46,$D$25+$D$44*10/($D$46+1),0) | AF19: =IF(10<=$D$46,$D$45*$D$32*$D$40/$D$46,0) | AH19: =0.3*$D$36 | AI19: =MIN($D$49*AH19,$D$36) | AJ19: =(0.85*$D$11*AI19*$D$14+SUMPRODUCT($AF$8:$AF$37,(ABS(6000*(1-$AE$8:$AE$37/AH19)+$D$12)-ABS(6000*(1-$AE$8:$AE$37/AH19)-$D$12))/2-0.85*$D$11*($AE$8:$AE$37<AI19)))/1000 | AK19: =(0.85*$D$11*AI19*$D$14*($D$36/2-AI19/2)+SUMPRODUCT($AF$8:$AF$37,(ABS(6000*(1-$AE$8:$AE$37/AH19)+$D$12)-ABS(6000*(1-$AE$8:$AE$37/AH19)-$D$12))/2-0.85*$D$11*($AE$8:$AE$37<AI19),$D$36/2-$AE$8:$AE$37))/100000 | AL19: =IF(AJ19<=0,0.9,MAX(0.7,0.9/(1+0.2*AJ19/$D$54))) | AM19: =MIN(AL19*AJ19,$D$51) | AN19: =MAX(0,AL19*AK19) | AO19: =IF(AP19>0,-AN19/AP19,-1E+9) | AP19: =AL19*AJ19
B20: Momento último del análisis | C20: Mua | D20: 280 | E20: t·m | AD20: 13 | AE20: =IF(11<=$D$46,$D$25+$D$44*11/($D$46+1),0) | AF20: =IF(11<=$D$46,$D$45*$D$32*$D$40/$D$46,0) | AH20: =0.35*$D$36 | AI20: =MIN($D$49*AH20,$D$36) | AJ20: =(0.85*$D$11*AI20*$D$14+SUMPRODUCT($AF$8:$AF$37,(ABS(6000*(1-$AE$8:$AE$37/AH20)+$D$12)-ABS(6000*(1-$AE$8:$AE$37/AH20)-$D$12))/2-0.85*$D$11*($AE$8:$AE$37<AI20)))/1000 | AK20: =(0.85*$D$11*AI20*$D$14*($D$36/2-AI20/2)+SUMPRODUCT($AF$8:$AF$37,(ABS(6000*(1-$AE$8:$AE$37/AH20)+$D$12)-ABS(6000*(1-$AE$8:$AE$37/AH20)-$D$12))/2-0.85*$D$11*($AE$8:$AE$37<AI20),$D$36/2-$AE$8:$AE$37))/100000 | AL20: =IF(AJ20<=0,0.9,MAX(0.7,0.9/(1+0.2*AJ20/$D$54))) | AM20: =MIN(AL20*AJ20,$D$51) | AN20: =MAX(0,AL20*AK20) | AO20: =IF(AP20>0,-AN20/AP20,-1E+9) | AP20: =AL20*AJ20
B21: Cortante último del análisis | C21: Vua | D21: 55 | E21: t | AD21: 14 | AE21: =IF(12<=$D$46,$D$25+$D$44*12/($D$46+1),0) | AF21: =IF(12<=$D$46,$D$45*$D$32*$D$40/$D$46,0) | AH21: =0.375*$D$36 | AI21: =MIN($D$49*AH21,$D$36) | AJ21: =(0.85*$D$11*AI21*$D$14+SUMPRODUCT($AF$8:$AF$37,(ABS(6000*(1-$AE$8:$AE$37/AH21)+$D$12)-ABS(6000*(1-$AE$8:$AE$37/AH21)-$D$12))/2-0.85*$D$11*($AE$8:$AE$37<AI21)))/1000 | AK21: =(0.85*$D$11*AI21*$D$14*($D$36/2-AI21/2)+SUMPRODUCT($AF$8:$AF$37,(ABS(6000*(1-$AE$8:$AE$37/AH21)+$D$12)-ABS(6000*(1-$AE$8:$AE$37/AH21)-$D$12))/2-0.85*$D$11*($AE$8:$AE$37<AI21),$D$36/2-$AE$8:$AE$37))/100000 | AL21: =IF(AJ21<=0,0.9,MAX(0.7,0.9/(1+0.2*AJ21/$D$54))) | AM21: =MIN(AL21*AJ21,$D$51) | AN21: =MAX(0,AL21*AK21) | AO21: =IF(AP21>0,-AN21/AP21,-1E+9) | AP21: =AL21*AJ21
B22: Desplazamiento inelástico del techo δu | C22: δu | D22: 6 | E22: cm | F22: E.030: 0.75R × elástico (0.85R irregular) | AD22: 15 | AE22: =IF(13<=$D$46,$D$25+$D$44*13/($D$46+1),0) | AF22: =IF(13<=$D$46,$D$45*$D$32*$D$40/$D$46,0) | AH22: =0.4*$D$36 | AI22: =MIN($D$49*AH22,$D$36) | AJ22: =(0.85*$D$11*AI22*$D$14+SUMPRODUCT($AF$8:$AF$37,(ABS(6000*(1-$AE$8:$AE$37/AH22)+$D$12)-ABS(6000*(1-$AE$8:$AE$37/AH22)-$D$12))/2-0.85*$D$11*($AE$8:$AE$37<AI22)))/1000 | AK22: =(0.85*$D$11*AI22*$D$14*($D$36/2-AI22/2)+SUMPRODUCT($AF$8:$AF$37,(ABS(6000*(1-$AE$8:$AE$37/AH22)+$D$12)-ABS(6000*(1-$AE$8:$AE$37/AH22)-$D$12))/2-0.85*$D$11*($AE$8:$AE$37<AI22),$D$36/2-$AE$8:$AE$37))/100000 | AL22: =IF(AJ22<=0,0.9,MAX(0.7,0.9/(1+0.2*AJ22/$D$54))) | AM22: =MIN(AL22*AJ22,$D$51) | AN22: =MAX(0,AL22*AK22) | AO22: =IF(AP22>0,-AN22/AP22,-1E+9) | AP22: =AL22*AJ22
B23: Refuerzo | AD23: 16 | AE23: =IF(14<=$D$46,$D$25+$D$44*14/($D$46+1),0) | AF23: =IF(14<=$D$46,$D$45*$D$32*$D$40/$D$46,0) | AH23: =0.425*$D$36 | AI23: =MIN($D$49*AH23,$D$36) | AJ23: =(0.85*$D$11*AI23*$D$14+SUMPRODUCT($AF$8:$AF$37,(ABS(6000*(1-$AE$8:$AE$37/AH23)+$D$12)-ABS(6000*(1-$AE$8:$AE$37/AH23)-$D$12))/2-0.85*$D$11*($AE$8:$AE$37<AI23)))/1000 | AK23: =(0.85*$D$11*AI23*$D$14*($D$36/2-AI23/2)+SUMPRODUCT($AF$8:$AF$37,(ABS(6000*(1-$AE$8:$AE$37/AH23)+$D$12)-ABS(6000*(1-$AE$8:$AE$37/AH23)-$D$12))/2-0.85*$D$11*($AE$8:$AE$37<AI23),$D$36/2-$AE$8:$AE$37))/100000 | AL23: =IF(AJ23<=0,0.9,MAX(0.7,0.9/(1+0.2*AJ23/$D$54))) | AM23: =MIN(AL23*AJ23,$D$51) | AN23: =MAX(0,AL23*AK23) | AO23: =IF(AP23>0,-AN23/AP23,-1E+9) | AP23: =AL23*AJ23
B24: Recubrimiento libre | C24: r | D24: 4 | E24: cm | AD24: 17 | AE24: =IF(15<=$D$46,$D$25+$D$44*15/($D$46+1),0) | AF24: =IF(15<=$D$46,$D$45*$D$32*$D$40/$D$46,0) | AH24: =0.45*$D$36 | AI24: =MIN($D$49*AH24,$D$36) | AJ24: =(0.85*$D$11*AI24*$D$14+SUMPRODUCT($AF$8:$AF$37,(ABS(6000*(1-$AE$8:$AE$37/AH24)+$D$12)-ABS(6000*(1-$AE$8:$AE$37/AH24)-$D$12))/2-0.85*$D$11*($AE$8:$AE$37<AI24)))/1000 | AK24: =(0.85*$D$11*AI24*$D$14*($D$36/2-AI24/2)+SUMPRODUCT($AF$8:$AF$37,(ABS(6000*(1-$AE$8:$AE$37/AH24)+$D$12)-ABS(6000*(1-$AE$8:$AE$37/AH24)-$D$12))/2-0.85*$D$11*($AE$8:$AE$37<AI24),$D$36/2-$AE$8:$AE$37))/100000 | AL24: =IF(AJ24<=0,0.9,MAX(0.7,0.9/(1+0.2*AJ24/$D$54))) | AM24: =MIN(AL24*AJ24,$D$51) | AN24: =MAX(0,AL24*AK24) | AO24: =IF(AP24>0,-AN24/AP24,-1E+9) | AP24: =AL24*AJ24
B25: Longitud de cada núcleo de borde | C25: lb | D25: 40 | E25: cm | AD25: 18 | AE25: =IF(16<=$D$46,$D$25+$D$44*16/($D$46+1),0) | AF25: =IF(16<=$D$46,$D$45*$D$32*$D$40/$D$46,0) | AH25: =0.475*$D$36 | AI25: =MIN($D$49*AH25,$D$36) | AJ25: =(0.85*$D$11*AI25*$D$14+SUMPRODUCT($AF$8:$AF$37,(ABS(6000*(1-$AE$8:$AE$37/AH25)+$D$12)-ABS(6000*(1-$AE$8:$AE$37/AH25)-$D$12))/2-0.85*$D$11*($AE$8:$AE$37<AI25)))/1000 | AK25: =(0.85*$D$11*AI25*$D$14*($D$36/2-AI25/2)+SUMPRODUCT($AF$8:$AF$37,(ABS(6000*(1-$AE$8:$AE$37/AH25)+$D$12)-ABS(6000*(1-$AE$8:$AE$37/AH25)-$D$12))/2-0.85*$D$11*($AE$8:$AE$37<AI25),$D$36/2-$AE$8:$AE$37))/100000 | AL25: =IF(AJ25<=0,0.9,MAX(0.7,0.9/(1+0.2*AJ25/$D$54))) | AM25: =MIN(AL25*AJ25,$D$51) | AN25: =MAX(0,AL25*AK25) | AO25: =IF(AP25>0,-AN25/AP25,-1E+9) | AP25: =AL25*AJ25
B26: Varillas por núcleo de borde (par) | C26: nb | D26: 8 | AD26: 19 | AE26: =IF(17<=$D$46,$D$25+$D$44*17/($D$46+1),0) | AF26: =IF(17<=$D$46,$D$45*$D$32*$D$40/$D$46,0) | AH26: =0.5*$D$36 | AI26: =MIN($D$49*AH26,$D$36) | AJ26: =(0.85*$D$11*AI26*$D$14+SUMPRODUCT($AF$8:$AF$37,(ABS(6000*(1-$AE$8:$AE$37/AH26)+$D$12)-ABS(6000*(1-$AE$8:$AE$37/AH26)-$D$12))/2-0.85*$D$11*($AE$8:$AE$37<AI26)))/1000 | AK26: =(0.85*$D$11*AI26*$D$14*($D$36/2-AI26/2)+SUMPRODUCT($AF$8:$AF$37,(ABS(6000*(1-$AE$8:$AE$37/AH26)+$D$12)-ABS(6000*(1-$AE$8:$AE$37/AH26)-$D$12))/2-0.85*$D$11*($AE$8:$AE$37<AI26),$D$36/2-$AE$8:$AE$37))/100000 | AL26: =IF(AJ26<=0,0.9,MAX(0.7,0.9/(1+0.2*AJ26/$D$54))) | AM26: =MIN(AL26*AJ26,$D$51) | AN26: =MAX(0,AL26*AK26) | AO26: =IF(AP26>0,-AN26/AP26,-1E+9) | AP26: =AL26*AJ26
B27: Varilla del núcleo | C27: Øb | D27: 3/4" | AD27: 20 | AE27: =IF(18<=$D$46,$D$25+$D$44*18/($D$46+1),0) | AF27: =IF(18<=$D$46,$D$45*$D$32*$D$40/$D$46,0) | AH27: =0.525*$D$36 | AI27: =MIN($D$49*AH27,$D$36) | AJ27: =(0.85*$D$11*AI27*$D$14+SUMPRODUCT($AF$8:$AF$37,(ABS(6000*(1-$AE$8:$AE$37/AH27)+$D$12)-ABS(6000*(1-$AE$8:$AE$37/AH27)-$D$12))/2-0.85*$D$11*($AE$8:$AE$37<AI27)))/1000 | AK27: =(0.85*$D$11*AI27*$D$14*($D$36/2-AI27/2)+SUMPRODUCT($AF$8:$AF$37,(ABS(6000*(1-$AE$8:$AE$37/AH27)+$D$12)-ABS(6000*(1-$AE$8:$AE$37/AH27)-$D$12))/2-0.85*$D$11*($AE$8:$AE$37<AI27),$D$36/2-$AE$8:$AE$37))/100000 | AL27: =IF(AJ27<=0,0.9,MAX(0.7,0.9/(1+0.2*AJ27/$D$54))) | AM27: =MIN(AL27*AJ27,$D$51) | AN27: =MAX(0,AL27*AK27) | AO27: =IF(AP27>0,-AN27/AP27,-1E+9) | AP27: =AL27*AJ27
B28: Varilla vertical del alma | C28: Øv | D28: 1/2" | AD28: 21 | AE28: =IF(19<=$D$46,$D$25+$D$44*19/($D$46+1),0) | AF28: =IF(19<=$D$46,$D$45*$D$32*$D$40/$D$46,0) | AH28: =0.55*$D$36 | AI28: =MIN($D$49*AH28,$D$36) | AJ28: =(0.85*$D$11*AI28*$D$14+SUMPRODUCT($AF$8:$AF$37,(ABS(6000*(1-$AE$8:$AE$37/AH28)+$D$12)-ABS(6000*(1-$AE$8:$AE$37/AH28)-$D$12))/2-0.85*$D$11*($AE$8:$AE$37<AI28)))/1000 | AK28: =(0.85*$D$11*AI28*$D$14*($D$36/2-AI28/2)+SUMPRODUCT($AF$8:$AF$37,(ABS(6000*(1-$AE$8:$AE$37/AH28)+$D$12)-ABS(6000*(1-$AE$8:$AE$37/AH28)-$D$12))/2-0.85*$D$11*($AE$8:$AE$37<AI28),$D$36/2-$AE$8:$AE$37))/100000 | AL28: =IF(AJ28<=0,0.9,MAX(0.7,0.9/(1+0.2*AJ28/$D$54))) | AM28: =MIN(AL28*AJ28,$D$51) | AN28: =MAX(0,AL28*AK28) | AO28: =IF(AP28>0,-AN28/AP28,-1E+9) | AP28: =AL28*AJ28
B29: Espaciamiento vertical del alma | C29: sv | D29: 20 | E29: cm | AD29: 22 | AE29: =IF(20<=$D$46,$D$25+$D$44*20/($D$46+1),0) | AF29: =IF(20<=$D$46,$D$45*$D$32*$D$40/$D$46,0) | AH29: =0.575*$D$36 | AI29: =MIN($D$49*AH29,$D$36) | AJ29: =(0.85*$D$11*AI29*$D$14+SUMPRODUCT($AF$8:$AF$37,(ABS(6000*(1-$AE$8:$AE$37/AH29)+$D$12)-ABS(6000*(1-$AE$8:$AE$37/AH29)-$D$12))/2-0.85*$D$11*($AE$8:$AE$37<AI29)))/1000 | AK29: =(0.85*$D$11*AI29*$D$14*($D$36/2-AI29/2)+SUMPRODUCT($AF$8:$AF$37,(ABS(6000*(1-$AE$8:$AE$37/AH29)+$D$12)-ABS(6000*(1-$AE$8:$AE$37/AH29)-$D$12))/2-0.85*$D$11*($AE$8:$AE$37<AI29),$D$36/2-$AE$8:$AE$37))/100000 | AL29: =IF(AJ29<=0,0.9,MAX(0.7,0.9/(1+0.2*AJ29/$D$54))) | AM29: =MIN(AL29*AJ29,$D$51) | AN29: =MAX(0,AL29*AK29) | AO29: =IF(AP29>0,-AN29/AP29,-1E+9) | AP29: =AL29*AJ29
B30: Varilla horizontal | C30: Øh | D30: 1/2" | AD30: 23 | AE30: =IF(21<=$D$46,$D$25+$D$44*21/($D$46+1),0) | AF30: =IF(21<=$D$46,$D$45*$D$32*$D$40/$D$46,0) | AH30: =0.6*$D$36 | AI30: =MIN($D$49*AH30,$D$36) | AJ30: =(0.85*$D$11*AI30*$D$14+SUMPRODUCT($AF$8:$AF$37,(ABS(6000*(1-$AE$8:$AE$37/AH30)+$D$12)-ABS(6000*(1-$AE$8:$AE$37/AH30)-$D$12))/2-0.85*$D$11*($AE$8:$AE$37<AI30)))/1000 | AK30: =(0.85*$D$11*AI30*$D$14*($D$36/2-AI30/2)+SUMPRODUCT($AF$8:$AF$37,(ABS(6000*(1-$AE$8:$AE$37/AH30)+$D$12)-ABS(6000*(1-$AE$8:$AE$37/AH30)-$D$12))/2-0.85*$D$11*($AE$8:$AE$37<AI30),$D$36/2-$AE$8:$AE$37))/100000 | AL30: =IF(AJ30<=0,0.9,MAX(0.7,0.9/(1+0.2*AJ30/$D$54))) | AM30: =MIN(AL30*AJ30,$D$51) | AN30: =MAX(0,AL30*AK30) | AO30: =IF(AP30>0,-AN30/AP30,-1E+9) | AP30: =AL30*AJ30
B31: Espaciamiento horizontal | C31: sh | D31: 20 | E31: cm | AD31: 24 | AE31: =IF(22<=$D$46,$D$25+$D$44*22/($D$46+1),0) | AF31: =IF(22<=$D$46,$D$45*$D$32*$D$40/$D$46,0) | AH31: =0.625*$D$36 | AI31: =MIN($D$49*AH31,$D$36) | AJ31: =(0.85*$D$11*AI31*$D$14+SUMPRODUCT($AF$8:$AF$37,(ABS(6000*(1-$AE$8:$AE$37/AH31)+$D$12)-ABS(6000*(1-$AE$8:$AE$37/AH31)-$D$12))/2-0.85*$D$11*($AE$8:$AE$37<AI31)))/1000 | AK31: =(0.85*$D$11*AI31*$D$14*($D$36/2-AI31/2)+SUMPRODUCT($AF$8:$AF$37,(ABS(6000*(1-$AE$8:$AE$37/AH31)+$D$12)-ABS(6000*(1-$AE$8:$AE$37/AH31)-$D$12))/2-0.85*$D$11*($AE$8:$AE$37<AI31),$D$36/2-$AE$8:$AE$37))/100000 | AL31: =IF(AJ31<=0,0.9,MAX(0.7,0.9/(1+0.2*AJ31/$D$54))) | AM31: =MIN(AL31*AJ31,$D$51) | AN31: =MAX(0,AL31*AK31) | AO31: =IF(AP31>0,-AN31/AP31,-1E+9) | AP31: =AL31*AJ31
B32: Número de capas (mallas) | D32: 2 | F32: Dos capas si t ≥ 20 cm o Vu > 0.53√f'c·Acw (21.9.4.3) | AD32: 25 | AE32: =IF(23<=$D$46,$D$25+$D$44*23/($D$46+1),0) | AF32: =IF(23<=$D$46,$D$45*$D$32*$D$40/$D$46,0) | AH32: =0.65*$D$36 | AI32: =MIN($D$49*AH32,$D$36) | AJ32: =(0.85*$D$11*AI32*$D$14+SUMPRODUCT($AF$8:$AF$37,(ABS(6000*(1-$AE$8:$AE$37/AH32)+$D$12)-ABS(6000*(1-$AE$8:$AE$37/AH32)-$D$12))/2-0.85*$D$11*($AE$8:$AE$37<AI32)))/1000 | AK32: =(0.85*$D$11*AI32*$D$14*($D$36/2-AI32/2)+SUMPRODUCT($AF$8:$AF$37,(ABS(6000*(1-$AE$8:$AE$37/AH32)+$D$12)-ABS(6000*(1-$AE$8:$AE$37/AH32)-$D$12))/2-0.85*$D$11*($AE$8:$AE$37<AI32),$D$36/2-$AE$8:$AE$37))/100000 | AL32: =IF(AJ32<=0,0.9,MAX(0.7,0.9/(1+0.2*AJ32/$D$54))) | AM32: =MIN(AL32*AJ32,$D$51) | AN32: =MAX(0,AL32*AK32) | AO32: =IF(AP32>0,-AN32/AP32,-1E+9) | AP32: =AL32*AJ32
B33: Estribo del núcleo | C33: Øe | D33: 3/8" | AD33: 26 | AE33: =IF(24<=$D$46,$D$25+$D$44*24/($D$46+1),0) | AF33: =IF(24<=$D$46,$D$45*$D$32*$D$40/$D$46,0) | AH33: =0.675*$D$36 | AI33: =MIN($D$49*AH33,$D$36) | AJ33: =(0.85*$D$11*AI33*$D$14+SUMPRODUCT($AF$8:$AF$37,(ABS(6000*(1-$AE$8:$AE$37/AH33)+$D$12)-ABS(6000*(1-$AE$8:$AE$37/AH33)-$D$12))/2-0.85*$D$11*($AE$8:$AE$37<AI33)))/1000 | AK33: =(0.85*$D$11*AI33*$D$14*($D$36/2-AI33/2)+SUMPRODUCT($AF$8:$AF$37,(ABS(6000*(1-$AE$8:$AE$37/AH33)+$D$12)-ABS(6000*(1-$AE$8:$AE$37/AH33)-$D$12))/2-0.85*$D$11*($AE$8:$AE$37<AI33),$D$36/2-$AE$8:$AE$37))/100000 | AL33: =IF(AJ33<=0,0.9,MAX(0.7,0.9/(1+0.2*AJ33/$D$54))) | AM33: =MIN(AL33*AJ33,$D$51) | AN33: =MAX(0,AL33*AK33) | AO33: =IF(AP33>0,-AN33/AP33,-1E+9) | AP33: =AL33*AJ33
AD34: 27 | AE34: =IF(25<=$D$46,$D$25+$D$44*25/($D$46+1),0) | AF34: =IF(25<=$D$46,$D$45*$D$32*$D$40/$D$46,0) | AH34: =0.7*$D$36 | AI34: =MIN($D$49*AH34,$D$36) | AJ34: =(0.85*$D$11*AI34*$D$14+SUMPRODUCT($AF$8:$AF$37,(ABS(6000*(1-$AE$8:$AE$37/AH34)+$D$12)-ABS(6000*(1-$AE$8:$AE$37/AH34)-$D$12))/2-0.85*$D$11*($AE$8:$AE$37<AI34)))/1000 | AK34: =(0.85*$D$11*AI34*$D$14*($D$36/2-AI34/2)+SUMPRODUCT($AF$8:$AF$37,(ABS(6000*(1-$AE$8:$AE$37/AH34)+$D$12)-ABS(6000*(1-$AE$8:$AE$37/AH34)-$D$12))/2-0.85*$D$11*($AE$8:$AE$37<AI34),$D$36/2-$AE$8:$AE$37))/100000 | AL34: =IF(AJ34<=0,0.9,MAX(0.7,0.9/(1+0.2*AJ34/$D$54))) | AM34: =MIN(AL34*AJ34,$D$51) | AN34: =MAX(0,AL34*AK34) | AO34: =IF(AP34>0,-AN34/AP34,-1E+9) | AP34: =AL34*AJ34
B35: 2. PROPIEDADES | AD35: 28 | AE35: =IF(26<=$D$46,$D$25+$D$44*26/($D$46+1),0) | AF35: =IF(26<=$D$46,$D$45*$D$32*$D$40/$D$46,0) | AH35: =0.75*$D$36 | AI35: =MIN($D$49*AH35,$D$36) | AJ35: =(0.85*$D$11*AI35*$D$14+SUMPRODUCT($AF$8:$AF$37,(ABS(6000*(1-$AE$8:$AE$37/AH35)+$D$12)-ABS(6000*(1-$AE$8:$AE$37/AH35)-$D$12))/2-0.85*$D$11*($AE$8:$AE$37<AI35)))/1000 | AK35: =(0.85*$D$11*AI35*$D$14*($D$36/2-AI35/2)+SUMPRODUCT($AF$8:$AF$37,(ABS(6000*(1-$AE$8:$AE$37/AH35)+$D$12)-ABS(6000*(1-$AE$8:$AE$37/AH35)-$D$12))/2-0.85*$D$11*($AE$8:$AE$37<AI35),$D$36/2-$AE$8:$AE$37))/100000 | AL35: =IF(AJ35<=0,0.9,MAX(0.7,0.9/(1+0.2*AJ35/$D$54))) | AM35: =MIN(AL35*AJ35,$D$51) | AN35: =MAX(0,AL35*AK35) | AO35: =IF(AP35>0,-AN35/AP35,-1E+9) | AP35: =AL35*AJ35
B36: Longitud en cm | C36: lm | D36: =$D$13*100 | E36: cm | AD36: 29 | AE36: =$D$36-$D$25+$D$43 | AF36: =$D$26/2*$D$39 | AH36: =0.8*$D$36 | AI36: =MIN($D$49*AH36,$D$36) | AJ36: =(0.85*$D$11*AI36*$D$14+SUMPRODUCT($AF$8:$AF$37,(ABS(6000*(1-$AE$8:$AE$37/AH36)+$D$12)-ABS(6000*(1-$AE$8:$AE$37/AH36)-$D$12))/2-0.85*$D$11*($AE$8:$AE$37<AI36)))/1000 | AK36: =(0.85*$D$11*AI36*$D$14*($D$36/2-AI36/2)+SUMPRODUCT($AF$8:$AF$37,(ABS(6000*(1-$AE$8:$AE$37/AH36)+$D$12)-ABS(6000*(1-$AE$8:$AE$37/AH36)-$D$12))/2-0.85*$D$11*($AE$8:$AE$37<AI36),$D$36/2-$AE$8:$AE$37))/100000 | AL36: =IF(AJ36<=0,0.9,MAX(0.7,0.9/(1+0.2*AJ36/$D$54))) | AM36: =MIN(AL36*AJ36,$D$51) | AN36: =MAX(0,AL36*AK36) | AO36: =IF(AP36>0,-AN36/AP36,-1E+9) | AP36: =AL36*AJ36
B37: Área de corte Acw = t·lm | C37: Acw | D37: =$D$14*$D$36 | E37: cm² | AD37: 30 | AE37: =$D$36-$D$43 | AF37: =$D$26/2*$D$39 | AH37: =0.85*$D$36 | AI37: =MIN($D$49*AH37,$D$36) | AJ37: =(0.85*$D$11*AI37*$D$14+SUMPRODUCT($AF$8:$AF$37,(ABS(6000*(1-$AE$8:$AE$37/AH37)+$D$12)-ABS(6000*(1-$AE$8:$AE$37/AH37)-$D$12))/2-0.85*$D$11*($AE$8:$AE$37<AI37)))/1000 | AK37: =(0.85*$D$11*AI37*$D$14*($D$36/2-AI37/2)+SUMPRODUCT($AF$8:$AF$37,(ABS(6000*(1-$AE$8:$AE$37/AH37)+$D$12)-ABS(6000*(1-$AE$8:$AE$37/AH37)-$D$12))/2-0.85*$D$11*($AE$8:$AE$37<AI37),$D$36/2-$AE$8:$AE$37))/100000 | AL37: =IF(AJ37<=0,0.9,MAX(0.7,0.9/(1+0.2*AJ37/$D$54))) | AM37: =MIN(AL37*AJ37,$D$51) | AN37: =MAX(0,AL37*AK37) | AO37: =IF(AP37>0,-AN37/AP37,-1E+9) | AP37: =AL37*AJ37
B38: Diámetro de la varilla del núcleo | C38: db | D38: =INDEX(BAR_DB,MATCH($D$27,BAR_NOM,0)) | E38: cm | AH38: =0.9*$D$36 | AI38: =MIN($D$49*AH38,$D$36) | AJ38: =(0.85*$D$11*AI38*$D$14+SUMPRODUCT($AF$8:$AF$37,(ABS(6000*(1-$AE$8:$AE$37/AH38)+$D$12)-ABS(6000*(1-$AE$8:$AE$37/AH38)-$D$12))/2-0.85*$D$11*($AE$8:$AE$37<AI38)))/1000 | AK38: =(0.85*$D$11*AI38*$D$14*($D$36/2-AI38/2)+SUMPRODUCT($AF$8:$AF$37,(ABS(6000*(1-$AE$8:$AE$37/AH38)+$D$12)-ABS(6000*(1-$AE$8:$AE$37/AH38)-$D$12))/2-0.85*$D$11*($AE$8:$AE$37<AI38),$D$36/2-$AE$8:$AE$37))/100000 | AL38: =IF(AJ38<=0,0.9,MAX(0.7,0.9/(1+0.2*AJ38/$D$54))) | AM38: =MIN(AL38*AJ38,$D$51) | AN38: =MAX(0,AL38*AK38) | AO38: =IF(AP38>0,-AN38/AP38,-1E+9) | AP38: =AL38*AJ38
B39: Área de la varilla del núcleo | C39: Ab | D39: =INDEX(BAR_AS,MATCH($D$27,BAR_NOM,0)) | E39: cm² | AH39: =0.95*$D$36 | AI39: =MIN($D$49*AH39,$D$36) | AJ39: =(0.85*$D$11*AI39*$D$14+SUMPRODUCT($AF$8:$AF$37,(ABS(6000*(1-$AE$8:$AE$37/AH39)+$D$12)-ABS(6000*(1-$AE$8:$AE$37/AH39)-$D$12))/2-0.85*$D$11*($AE$8:$AE$37<AI39)))/1000 | AK39: =(0.85*$D$11*AI39*$D$14*($D$36/2-AI39/2)+SUMPRODUCT($AF$8:$AF$37,(ABS(6000*(1-$AE$8:$AE$37/AH39)+$D$12)-ABS(6000*(1-$AE$8:$AE$37/AH39)-$D$12))/2-0.85*$D$11*($AE$8:$AE$37<AI39),$D$36/2-$AE$8:$AE$37))/100000 | AL39: =IF(AJ39<=0,0.9,MAX(0.7,0.9/(1+0.2*AJ39/$D$54))) | AM39: =MIN(AL39*AJ39,$D$51) | AN39: =MAX(0,AL39*AK39) | AO39: =IF(AP39>0,-AN39/AP39,-1E+9) | AP39: =AL39*AJ39
B40: Área de la varilla vertical | C40: Ab | D40: =INDEX(BAR_AS,MATCH($D$28,BAR_NOM,0)) | E40: cm² | AH40: =1.0*$D$36 | AI40: =MIN($D$49*AH40,$D$36) | AJ40: =(0.85*$D$11*AI40*$D$14+SUMPRODUCT($AF$8:$AF$37,(ABS(6000*(1-$AE$8:$AE$37/AH40)+$D$12)-ABS(6000*(1-$AE$8:$AE$37/AH40)-$D$12))/2-0.85*$D$11*($AE$8:$AE$37<AI40)))/1000 | AK40: =(0.85*$D$11*AI40*$D$14*($D$36/2-AI40/2)+SUMPRODUCT($AF$8:$AF$37,(ABS(6000*(1-$AE$8:$AE$37/AH40)+$D$12)-ABS(6000*(1-$AE$8:$AE$37/AH40)-$D$12))/2-0.85*$D$11*($AE$8:$AE$37<AI40),$D$36/2-$AE$8:$AE$37))/100000 | AL40: =IF(AJ40<=0,0.9,MAX(0.7,0.9/(1+0.2*AJ40/$D$54))) | AM40: =MIN(AL40*AJ40,$D$51) | AN40: =MAX(0,AL40*AK40) | AO40: =IF(AP40>0,-AN40/AP40,-1E+9) | AP40: =AL40*AJ40
B41: Área de la varilla horizontal | C41: Ab | D41: =INDEX(BAR_AS,MATCH($D$30,BAR_NOM,0)) | E41: cm² | AH41: =1.1*$D$36 | AI41: =MIN($D$49*AH41,$D$36) | AJ41: =(0.85*$D$11*AI41*$D$14+SUMPRODUCT($AF$8:$AF$37,(ABS(6000*(1-$AE$8:$AE$37/AH41)+$D$12)-ABS(6000*(1-$AE$8:$AE$37/AH41)-$D$12))/2-0.85*$D$11*($AE$8:$AE$37<AI41)))/1000 | AK41: =(0.85*$D$11*AI41*$D$14*($D$36/2-AI41/2)+SUMPRODUCT($AF$8:$AF$37,(ABS(6000*(1-$AE$8:$AE$37/AH41)+$D$12)-ABS(6000*(1-$AE$8:$AE$37/AH41)-$D$12))/2-0.85*$D$11*($AE$8:$AE$37<AI41),$D$36/2-$AE$8:$AE$37))/100000 | AL41: =IF(AJ41<=0,0.9,MAX(0.7,0.9/(1+0.2*AJ41/$D$54))) | AM41: =MIN(AL41*AJ41,$D$51) | AN41: =MAX(0,AL41*AK41) | AO41: =IF(AP41>0,-AN41/AP41,-1E+9) | AP41: =AL41*AJ41
B42: Diámetro del estribo | C42: dbe | D42: =INDEX(BAR_DB,MATCH($D$33,BAR_NOM,0)) | E42: cm | AH42: =1.2*$D$36 | AI42: =MIN($D$49*AH42,$D$36) | AJ42: =(0.85*$D$11*AI42*$D$14+SUMPRODUCT($AF$8:$AF$37,(ABS(6000*(1-$AE$8:$AE$37/AH42)+$D$12)-ABS(6000*(1-$AE$8:$AE$37/AH42)-$D$12))/2-0.85*$D$11*($AE$8:$AE$37<AI42)))/1000 | AK42: =(0.85*$D$11*AI42*$D$14*($D$36/2-AI42/2)+SUMPRODUCT($AF$8:$AF$37,(ABS(6000*(1-$AE$8:$AE$37/AH42)+$D$12)-ABS(6000*(1-$AE$8:$AE$37/AH42)-$D$12))/2-0.85*$D$11*($AE$8:$AE$37<AI42),$D$36/2-$AE$8:$AE$37))/100000 | AL42: =IF(AJ42<=0,0.9,MAX(0.7,0.9/(1+0.2*AJ42/$D$54))) | AM42: =MIN(AL42*AJ42,$D$51) | AN42: =MAX(0,AL42*AK42) | AO42: =IF(AP42>0,-AN42/AP42,-1E+9) | AP42: =AL42*AJ42
B43: Recubrimiento al centro de las varillas del núcleo | C43: rc | D43: =$D$24+$D$42+$D$38/2 | E43: cm | AH43: =1.35*$D$36 | AI43: =MIN($D$49*AH43,$D$36) | AJ43: =(0.85*$D$11*AI43*$D$14+SUMPRODUCT($AF$8:$AF$37,(ABS(6000*(1-$AE$8:$AE$37/AH43)+$D$12)-ABS(6000*(1-$AE$8:$AE$37/AH43)-$D$12))/2-0.85*$D$11*($AE$8:$AE$37<AI43)))/1000 | AK43: =(0.85*$D$11*AI43*$D$14*($D$36/2-AI43/2)+SUMPRODUCT($AF$8:$AF$37,(ABS(6000*(1-$AE$8:$AE$37/AH43)+$D$12)-ABS(6000*(1-$AE$8:$AE$37/AH43)-$D$12))/2-0.85*$D$11*($AE$8:$AE$37<AI43),$D$36/2-$AE$8:$AE$37))/100000 | AL43: =IF(AJ43<=0,0.9,MAX(0.7,0.9/(1+0.2*AJ43/$D$54))) | AM43: =MIN(AL43*AJ43,$D$51) | AN43: =MAX(0,AL43*AK43) | AO43: =IF(AP43>0,-AN43/AP43,-1E+9) | AP43: =AL43*AJ43
B44: Longitud del alma entre núcleos | C44: Lw | D44: =MAX(0,$D$36-2*$D$25) | E44: cm | AH44: =1.5*$D$36 | AI44: =MIN($D$49*AH44,$D$36) | AJ44: =(0.85*$D$11*AI44*$D$14+SUMPRODUCT($AF$8:$AF$37,(ABS(6000*(1-$AE$8:$AE$37/AH44)+$D$12)-ABS(6000*(1-$AE$8:$AE$37/AH44)-$D$12))/2-0.85*$D$11*($AE$8:$AE$37<AI44)))/1000 | AK44: =(0.85*$D$11*AI44*$D$14*($D$36/2-AI44/2)+SUMPRODUCT($AF$8:$AF$37,(ABS(6000*(1-$AE$8:$AE$37/AH44)+$D$12)-ABS(6000*(1-$AE$8:$AE$37/AH44)-$D$12))/2-0.85*$D$11*($AE$8:$AE$37<AI44),$D$36/2-$AE$8:$AE$37))/100000 | AL44: =IF(AJ44<=0,0.9,MAX(0.7,0.9/(1+0.2*AJ44/$D$54))) | AM44: =MIN(AL44*AJ44,$D$51) | AN44: =MAX(0,AL44*AK44) | AO44: =IF(AP44>0,-AN44/AP44,-1E+9) | AP44: =AL44*AJ44
B45: Líneas de varillas verticales en el alma | C45: n | D45: =MAX(0,CEILING($D$44/$D$29,1)-1) | AH45: =1.75*$D$36 | AI45: =MIN($D$49*AH45,$D$36) | AJ45: =(0.85*$D$11*AI45*$D$14+SUMPRODUCT($AF$8:$AF$37,(ABS(6000*(1-$AE$8:$AE$37/AH45)+$D$12)-ABS(6000*(1-$AE$8:$AE$37/AH45)-$D$12))/2-0.85*$D$11*($AE$8:$AE$37<AI45)))/1000 | AK45: =(0.85*$D$11*AI45*$D$14*($D$36/2-AI45/2)+SUMPRODUCT($AF$8:$AF$37,(ABS(6000*(1-$AE$8:$AE$37/AH45)+$D$12)-ABS(6000*(1-$AE$8:$AE$37/AH45)-$D$12))/2-0.85*$D$11*($AE$8:$AE$37<AI45),$D$36/2-$AE$8:$AE$37))/100000 | AL45: =IF(AJ45<=0,0.9,MAX(0.7,0.9/(1+0.2*AJ45/$D$54))) | AM45: =MIN(AL45*AJ45,$D$51) | AN45: =MAX(0,AL45*AK45) | AO45: =IF(AP45>0,-AN45/AP45,-1E+9) | AP45: =AL45*AJ45
B46: Capas de cálculo del alma (máx. 26) | D46: =MIN(26,$D$45) | AH46: =2.0*$D$36 | AI46: =MIN($D$49*AH46,$D$36) | AJ46: =(0.85*$D$11*AI46*$D$14+SUMPRODUCT($AF$8:$AF$37,(ABS(6000*(1-$AE$8:$AE$37/AH46)+$D$12)-ABS(6000*(1-$AE$8:$AE$37/AH46)-$D$12))/2-0.85*$D$11*($AE$8:$AE$37<AI46)))/1000 | AK46: =(0.85*$D$11*AI46*$D$14*($D$36/2-AI46/2)+SUMPRODUCT($AF$8:$AF$37,(ABS(6000*(1-$AE$8:$AE$37/AH46)+$D$12)-ABS(6000*(1-$AE$8:$AE$37/AH46)-$D$12))/2-0.85*$D$11*($AE$8:$AE$37<AI46),$D$36/2-$AE$8:$AE$37))/100000 | AL46: =IF(AJ46<=0,0.9,MAX(0.7,0.9/(1+0.2*AJ46/$D$54))) | AM46: =MIN(AL46*AJ46,$D$51) | AN46: =MAX(0,AL46*AK46) | AO46: =IF(AP46>0,-AN46/AP46,-1E+9) | AP46: =AL46*AJ46
B47: Acero vertical total | C47: Ast | D47: =2*$D$26*$D$39+$D$45*$D$32*$D$40 | E47: cm² | AH47: =3.0*$D$36 | AI47: =MIN($D$49*AH47,$D$36) | AJ47: =(0.85*$D$11*AI47*$D$14+SUMPRODUCT($AF$8:$AF$37,(ABS(6000*(1-$AE$8:$AE$37/AH47)+$D$12)-ABS(6000*(1-$AE$8:$AE$37/AH47)-$D$12))/2-0.85*$D$11*($AE$8:$AE$37<AI47)))/1000 | AK47: =(0.85*$D$11*AI47*$D$14*($D$36/2-AI47/2)+SUMPRODUCT($AF$8:$AF$37,(ABS(6000*(1-$AE$8:$AE$37/AH47)+$D$12)-ABS(6000*(1-$AE$8:$AE$37/AH47)-$D$12))/2-0.85*$D$11*($AE$8:$AE$37<AI47),$D$36/2-$AE$8:$AE$37))/100000 | AL47: =IF(AJ47<=0,0.9,MAX(0.7,0.9/(1+0.2*AJ47/$D$54))) | AM47: =MIN(AL47*AJ47,$D$51) | AN47: =MAX(0,AL47*AK47) | AO47: =IF(AP47>0,-AN47/AP47,-1E+9) | AP47: =AL47*AJ47
B48: Área bruta | C48: Ag | D48: =$D$14*$D$36 | E48: cm² | AH48: =10.0*$D$36 | AI48: =MIN($D$49*AH48,$D$36) | AJ48: =(0.85*$D$11*AI48*$D$14+SUMPRODUCT($AF$8:$AF$37,(ABS(6000*(1-$AE$8:$AE$37/AH48)+$D$12)-ABS(6000*(1-$AE$8:$AE$37/AH48)-$D$12))/2-0.85*$D$11*($AE$8:$AE$37<AI48)))/1000 | AK48: =(0.85*$D$11*AI48*$D$14*($D$36/2-AI48/2)+SUMPRODUCT($AF$8:$AF$37,(ABS(6000*(1-$AE$8:$AE$37/AH48)+$D$12)-ABS(6000*(1-$AE$8:$AE$37/AH48)-$D$12))/2-0.85*$D$11*($AE$8:$AE$37<AI48),$D$36/2-$AE$8:$AE$37))/100000 | AL48: =IF(AJ48<=0,0.9,MAX(0.7,0.9/(1+0.2*AJ48/$D$54))) | AM48: =MIN(AL48*AJ48,$D$51) | AN48: =MAX(0,AL48*AK48) | AO48: =IF(AP48>0,-AN48/AP48,-1E+9) | AP48: =AL48*AJ48
B49: Factor β1 | C49: β1 | D49: =IF($D$11<=280,0.85,MAX(0.65,0.85-0.05*($D$11-280)/70))
B50: Po = 0.85f'c(Ag − Ast) + fy·Ast | C50: Po | D50: =(0.85*$D$11*($D$48-$D$47)+$D$12*$D$47)/1000 | E50: t
B51: φPn máx = 0.80·0.70·Po | C51: φPnmáx | D51: =0.8*0.7*$D$50 | E51: t
B52: t ≥ hu/25 y t ≥ 15 cm (21.9.3.2) | C52: =IF($D$14>=MAX($D$16*100/25,15),"CUMPLE","NO CUMPLE")
B53: Carga balanceada | C53: Pb | D53: =(0.85*$D$11*MIN($D$49*(6000*MAX($AE$8:$AE$37)/(6000+$D$12)),$D$36)*$D$14+SUMPRODUCT($AF$8:$AF$37,(ABS(6000*(1-$AE$8:$AE$37/(6000*MAX($AE$8:$AE$37)/(6000+$D$12)))+$D$12)-ABS(6000*(1-$AE$8:$AE$37/(6000*MAX($AE$8:$AE$37)/(6000+$D$12)))-$D$12))/2-0.85*$D$11*($AE$8:$AE$37<MIN($D$49*(6000*MAX($AE$8:$AE$37)/(6000+$D$12)),$D$36))))/1000 | E53: t
B54: Límite de transición de φ | D54: =MAX(0.001,MIN(0.1*$D$11*$D$48/1000,0.7*$D$53)) | E54: t
B56: 3. FLEXOCOMPRESIÓN
B57: Pu ≤ φPn máx | C57: =IF($D$19<=$D$51,"CUMPLE","NO CUMPLE")
B58: Índice en el diagrama | D58: =IFERROR(MATCH($D$19,$AM$9:$AM$48,1),0)
B59: φMn para Pu | C59: φMn | D59: =IF($D$58<=0,INDEX($AN$9:$AN$48,1),IF($D$58>=40,INDEX($AN$9:$AN$48,40),INDEX($AN$9:$AN$48,$D$58)+(INDEX($AN$9:$AN$48,$D$58+1)-INDEX($AN$9:$AN$48,$D$58))*($D$19-INDEX($AM$9:$AM$48,$D$58))/MAX(1E-9,INDEX($AM$9:$AM$48,$D$58+1)-INDEX($AM$9:$AM$48,$D$58)))) | E59: t·m
B60: Mua ≤ φMn | C60: =IF($D$20<=$D$59,"CUMPLE","NO CUMPLE") | F60: Si no cumple: más acero en los núcleos o mayor longitud
B61: Índice nominal | D61: =IFERROR(MATCH($D$19,$AJ$9:$AJ$48,1),0)
B62: Mn nominal para Pu | C62: Mn | D62: =IF($D$61<=0,INDEX($AK$9:$AK$48,1),IF($D$61>=40,INDEX($AK$9:$AK$48,40),INDEX($AK$9:$AK$48,$D$61)+(INDEX($AK$9:$AK$48,$D$61+1)-INDEX($AK$9:$AK$48,$D$61))*($D$19-INDEX($AJ$9:$AJ$48,$D$61))/MAX(1E-9,INDEX($AJ$9:$AJ$48,$D$61+1)-INDEX($AJ$9:$AJ$48,$D$61)))) | E62: t·m
B63: Profundidad del eje neutro c para Pu | C63: c | D63: =IF($D$61<=0,INDEX($AH$9:$AH$48,1),IF($D$61>=40,INDEX($AH$9:$AH$48,40),INDEX($AH$9:$AH$48,$D$61)+(INDEX($AH$9:$AH$48,$D$61+1)-INDEX($AH$9:$AH$48,$D$61))*($D$19-INDEX($AJ$9:$AJ$48,$D$61))/MAX(1E-9,INDEX($AJ$9:$AJ$48,$D$61+1)-INDEX($AJ$9:$AJ$48,$D$61)))) | E63: cm
B65: 4. CORTANTE (E.060 11.10 y 21.9.5.3)
B66: Amplificación Mn/Mua (≤ R) | C66: Mn/Mua | D66: =MIN($D$17,MAX(1,$D$62/$D$20))
B67: CORTANTE DE DISEÑO Vu = Vua·Mn/Mua | C67: Vu | D67: =$D$21*$D$66 | E67: t
B68: Coeficiente αc (hm/lm) | C68: αc | D68: =IF($D$15/$D$13<=1.5,0.8,IF($D$15/$D$13>=2,0.53,0.8-(0.8-0.53)*($D$15/$D$13-1.5)/0.5)) | F68: 0.25/0.17 MPa = 0.80/0.53 kgf/cm²
B69: Vc = αc·√f'c·Acw (reducido si Pu < 0) | C69: Vc | D69: =$D$68*SQRT($D$11)*$D$37/1000*MAX(0,1-0.0284*MAX(0,-$D$19)*1000/$D$48) | E69: t | F69: 11.10.5 y 11.10.6
B70: Vu/φ ≤ Vn máx = 2.6·√f'c·Acw | C70: =IF($D$67/0.85<=2.6*SQRT($D$11)*$D$37/1000,"CUMPLE","NO CUMPLE") | F70: 11.10.4: aumente t o lm
B71: Vs = Vu/φ − Vc | C71: Vs | D71: =MAX(0,$D$67/0.85-$D$69) | E71: t
B72: ρh por resistencia = Vs/(Acw·fy) | C72: ρh | D72: =$D$71*1000/($D$37*$D$12)
B73: ρh mínimo | C73: ρh mín | D73: =IF($D$67<0.27*SQRT($D$11)*$D$37/1000,0.002,0.0025) | F73: 0.0020 si Vu < 0.27√f'c·Acw; si no, 0.0025 (11.10.7/8)
B74: ρh requerido | C74: ρh | D74: =MAX($D$72,$D$73)
B75: ρh colocado | C75: ρh | D75: =$D$32*$D$41/($D$14*$D$31)
B76: ρh colocado ≥ requerido y s ≤ 3t, 40 cm | C76: =IF(AND($D$75>=$D$74,$D$31<=MIN(3*$D$14,40)),"CUMPLE","NO CUMPLE")
B77: ρv mínimo | C77: ρv mín | D77: =IF($D$67<0.27*SQRT($D$11)*$D$37/1000,0.0015,MIN($D$74,MAX(0.0025,0.0025+0.5*(2.5-$D$15/$D$13)*($D$74-0.0025)))) | F77: 11.10.10; si hm/lm ≤ 2: ρv ≥ ρh (21.9.5.2)
B78: ρv requerido | C78: ρv | D78: =IF($D$15/$D$13<=2,MAX($D$77,$D$74),$D$77)
B79: ρv colocado en el alma | C79: ρv | D79: =$D$32*$D$40/($D$14*$D$29)
B80: ρv colocado ≥ requerido y s ≤ 3t, 40 cm | C80: =IF(AND($D$79>=$D$78,$D$29<=MIN(3*$D$14,40)),"CUMPLE","NO CUMPLE")
B81: Número de capas suficiente | C81: =IF(OR($D$32=2,AND($D$14<20,$D$67<=0.53*SQRT($D$11)*$D$37/1000)),"CUMPLE","NO CUMPLE") | F81: Use 2 capas
B83: 5. ELEMENTOS DE BORDE (E.060 21.9.7)
B84: Deriva global δu/hm (≥ 0.005) | C84: δu/hm | D84: =MAX(0.005,$D$22/($D$15*100))
B85: c límite = lm/(600·δu/hm) | C85: clím | D85: =$D$36/(600*$D$84) | E85: cm | F85: 21.9.7.4
B86: Esfuerzo de compresión Pu/A + Mu·(lm/2)/I | C86: σ | D86: =$D$19*1000/$D$48+$D$20*100000*($D$36/2)/($D$14*$D$36^3/12) | E86: kgf/cm² | F86: 21.9.7.5: límite 0.2f'c
B87: ¿Requiere elemento de borde confinado? | D87: =IF(OR($D$63>=$D$85,$D$86>0.2*$D$11),"SÍ","NO") | F87: Por desplazamiento o por esfuerzo
B88: Longitud del elemento de borde máx(c − 0.1lm, c/2) | C88: Lb | D88: =MAX($D$63-0.1*$D$36,$D$63/2) | E88: cm | F88: 21.9.7.6(a)
B89: Núcleo colocado ≥ longitud requerida | C89: =IF(OR($D$87="NO",$D$25>=$D$88),"CUMPLE","NO CUMPLE") | F89: Si no cumple: alargue el núcleo
B90: Espaciamiento de estribos en el borde | C90: s | D90: =FLOOR(MIN(10*$D$38,MIN($D$14,$D$25),25),2.5) | E90: cm | F90: 10db, menor dimensión, 25 cm
B91: E.060 21.9.7.6 no exige Ash en los elementos de borde: se usan los diámetros de estribo de 21.4.4.4 (Ø 3/8" hasta barras de 1") y s ≤ 10db, menor dimensión, 25 cm.
B92: ESTRIBOS DEL NÚCLEO | D92: ="□ Ø "&$D$33&" @ "&FIXED($D$90/100,IF(MOD(ROUND($D$90*10,0),50)=0,2,3))&" m"
B94: 6. RESUMEN
B95: Núcleos de borde | D95: =$D$26&" Ø "&$D$27&" en "&FIXED($D$25,0)&" cm, a cada extremo"
B96: Alma | D96: ="Vertical Ø "&$D$28&" @ "&FIXED($D$29/100,IF(MOD(ROUND($D$29*10,0),50)=0,2,3))&" · Horizontal Ø "&$D$30&" @ "&FIXED($D$31/100,IF(MOD(ROUND($D$31*10,0),50)=0,2,3))&" m ("&$D$32&" capas)"
B97: ESTADO GENERAL DEL DISEÑO | C97: =IF(AND($C$52="CUMPLE",$C$57="CUMPLE",$C$60="CUMPLE",$C$70="CUMPLE",$C$76="CUMPLE",$C$80="CUMPLE",$C$81="CUMPLE",$C$89="CUMPLE"),"CUMPLE","NO CUMPLE") | F97: Revise las líneas en rojo
B99: 7. DIAGRAMA DE INTERACCIÓN (punto rojo: Mua, Pu)

Sheet LOSA_MACIZA
B1: LOSA MACIZA EN DOS DIRECCIONES · NTE E.060 13.7
B2: ALF_BIM · Plantilla Excel Estructuras · NTE E.060 Concreto Armado · v2.1.0
B3: Proyecto | C3: =INICIO!$D$7
B4: Ubicación | C4: =INICIO!$D$9
B5: Elemento | C5: Paño A-B / 1-2, techo 1er piso
B6: Calculista | C6: =INICIO!$D$10&IF(INICIO!$D$11="",""," · CIP "&INICIO!$D$11)
B7: Fecha | C7: =INICIO!$D$12
B10: 1. DATOS DE ENTRADA
B11: Resistencia del concreto | C11: f'c | D11: 210 | E11: kgf/cm²
B12: Fluencia del acero | C12: fy | D12: 4200 | E12: kgf/cm²
B13: Luz libre en una dirección | C13: L1 | D13: 4 | E13: m
B14: Luz libre en la otra dirección | C14: L2 | D14: 5 | E14: m | F14: A = menor, B = mayor
B15: Condición de bordes | D15: Caso 4 · 2 bordes adyacentes continuos
B16: Espesor de la losa | C16: h | D16: 15 | E16: cm
B17: Acabados | C17: pt | D17: 100 | E17: kgf/m²
B18: Tabiquería repartida | C18: tab | D18: 100 | E18: kgf/m²
B19: Uso (sobrecarga E.020) | D19: Vivienda
B20: Sobrecarga manual (si eligió «Otro») | C20: s/c | D20: 0 | E20: kgf/m²
B21: Varilla | C21: Ø | D21: 3/8"
B22: Recubrimiento libre | C22: r | D22: 2 | E22: cm | F22: E.060 7.7.1: losas 2 cm
B24: 2. CARGAS Y COEFICIENTES
B25: Luz corta A | C25: A | D25: =MIN($D$13,$D$14) | E25: m
B26: Luz larga B | C26: B | D26: =MAX($D$13,$D$14) | E26: m
B27: Relación m = A/B | C27: m | D27: =$D$25/$D$26
B28: m ≥ 0.50 (B/A ≤ 2, 13.7.1) | C28: =IF($D$27>=0.5,"CUMPLE","NO CUMPLE") | F28: Si no cumple: diséñela como losa en una dirección
B29: Número de caso | D29: =VALUE(MID($D$15,6,1))
B30: m para las tablas (0.50 a 1.00) | D30: =MAX(0.5,MIN(1,$D$27))
B31: Peso propio 2400·h | C31: pp | D31: =2400*$D$16/100 | E31: kgf/m²
B32: Sobrecarga | C32: s/c | D32: =IF($D$19="Otro (ingresar valor manual)",$D$20,INDEX(USO_SC,MATCH($D$19,USO_NOM,0))) | E32: kgf/m²
B33: Carga muerta amplificada 1.4·CM | C33: wud | D33: =1.4*($D$31+$D$17+$D$18)/1000 | E33: t/m²
B34: Carga viva amplificada 1.7·CV | C34: wul | D34: =1.7*$D$32/1000 | E34: t/m²
B35: Carga última total | C35: wu | D35: =$D$33+$D$34 | E35: t/m²
B36: CV ≤ 2·CM (servicio, 13.7.1) | C36: =IF($D$32<=2*($D$31+$D$17+$D$18),"CUMPLE","REVISAR")
B37: Coeficiente Ca negativo | D37: =INDEX(LNEG,MATCH($D$30,INDEX(LNEG,0,1),-1),(2*$D$29+0))+(INDEX(LNEG,MIN(MATCH($D$30,INDEX(LNEG,0,1),-1)+1,11),(2*$D$29+0))-INDEX(LNEG,MATCH($D$30,INDEX(LNEG,0,1),-1),(2*$D$29+0)))*IF(INDEX(INDEX(LNEG,0,1),MATCH($D$30,INDEX(LNEG,0,1),-1))=INDEX(INDEX(LNEG,0,1),MIN(MATCH($D$30,INDEX(LNEG,0,1),-1)+1,11)),0,(INDEX(INDEX(LNEG,0,1),MATCH($D$30,INDEX(LNEG,0,1),-1))-$D$30)/(INDEX(INDEX(LNEG,0,1),MATCH($D$30,INDEX(LNEG,0,1),-1))-INDEX(INDEX(LNEG,0,1),MIN(MATCH($D$30,INDEX(LNEG,0,1),-1)+1,11)))) | F37: Tablas 13.1–13.3, interpolado
B38: Coeficiente Cb negativo | D38: =INDEX(LNEG,MATCH($D$30,INDEX(LNEG,0,1),-1),(2*$D$29+1))+(INDEX(LNEG,MIN(MATCH($D$30,INDEX(LNEG,0,1),-1)+1,11),(2*$D$29+1))-INDEX(LNEG,MATCH($D$30,INDEX(LNEG,0,1),-1),(2*$D$29+1)))*IF(INDEX(INDEX(LNEG,0,1),MATCH($D$30,INDEX(LNEG,0,1),-1))=INDEX(INDEX(LNEG,0,1),MIN(MATCH($D$30,INDEX(LNEG,0,1),-1)+1,11)),0,(INDEX(INDEX(LNEG,0,1),MATCH($D$30,INDEX(LNEG,0,1),-1))-$D$30)/(INDEX(INDEX(LNEG,0,1),MATCH($D$30,INDEX(LNEG,0,1),-1))-INDEX(INDEX(LNEG,0,1),MIN(MATCH($D$30,INDEX(LNEG,0,1),-1)+1,11))))
B39: Coeficiente Ca positivo CM | D39: =INDEX(LPCM,MATCH($D$30,INDEX(LPCM,0,1),-1),(2*$D$29+0))+(INDEX(LPCM,MIN(MATCH($D$30,INDEX(LPCM,0,1),-1)+1,11),(2*$D$29+0))-INDEX(LPCM,MATCH($D$30,INDEX(LPCM,0,1),-1),(2*$D$29+0)))*IF(INDEX(INDEX(LPCM,0,1),MATCH($D$30,INDEX(LPCM,0,1),-1))=INDEX(INDEX(LPCM,0,1),MIN(MATCH($D$30,INDEX(LPCM,0,1),-1)+1,11)),0,(INDEX(INDEX(LPCM,0,1),MATCH($D$30,INDEX(LPCM,0,1),-1))-$D$30)/(INDEX(INDEX(LPCM,0,1),MATCH($D$30,INDEX(LPCM,0,1),-1))-INDEX(INDEX(LPCM,0,1),MIN(MATCH($D$30,INDEX(LPCM,0,1),-1)+1,11))))
B40: Coeficiente Cb positivo CM | D40: =INDEX(LPCM,MATCH($D$30,INDEX(LPCM,0,1),-1),(2*$D$29+1))+(INDEX(LPCM,MIN(MATCH($D$30,INDEX(LPCM,0,1),-1)+1,11),(2*$D$29+1))-INDEX(LPCM,MATCH($D$30,INDEX(LPCM,0,1),-1),(2*$D$29+1)))*IF(INDEX(INDEX(LPCM,0,1),MATCH($D$30,INDEX(LPCM,0,1),-1))=INDEX(INDEX(LPCM,0,1),MIN(MATCH($D$30,INDEX(LPCM,0,1),-1)+1,11)),0,(INDEX(INDEX(LPCM,0,1),MATCH($D$30,INDEX(LPCM,0,1),-1))-$D$30)/(INDEX(INDEX(LPCM,0,1),MATCH($D$30,INDEX(LPCM,0,1),-1))-INDEX(INDEX(LPCM,0,1),MIN(MATCH($D$30,INDEX(LPCM,0,1),-1)+1,11))))
B41: Coeficiente Ca positivo CV | D41: =INDEX(LPCV,MATCH($D$30,INDEX(LPCV,0,1),-1),(2*$D$29+0))+(INDEX(LPCV,MIN(MATCH($D$30,INDEX(LPCV,0,1),-1)+1,11),(2*$D$29+0))-INDEX(LPCV,MATCH($D$30,INDEX(LPCV,0,1),-1),(2*$D$29+0)))*IF(INDEX(INDEX(LPCV,0,1),MATCH($D$30,INDEX(LPCV,0,1),-1))=INDEX(INDEX(LPCV,0,1),MIN(MATCH($D$30,INDEX(LPCV,0,1),-1)+1,11)),0,(INDEX(INDEX(LPCV,0,1),MATCH($D$30,INDEX(LPCV,0,1),-1))-$D$30)/(INDEX(INDEX(LPCV,0,1),MATCH($D$30,INDEX(LPCV,0,1),-1))-INDEX(INDEX(LPCV,0,1),MIN(MATCH($D$30,INDEX(LPCV,0,1),-1)+1,11))))
B42: Coeficiente Cb positivo CV | D42: =INDEX(LPCV,MATCH($D$30,INDEX(LPCV,0,1),-1),(2*$D$29+1))+(INDEX(LPCV,MIN(MATCH($D$30,INDEX(LPCV,0,1),-1)+1,11),(2*$D$29+1))-INDEX(LPCV,MATCH($D$30,INDEX(LPCV,0,1),-1),(2*$D$29+1)))*IF(INDEX(INDEX(LPCV,0,1),MATCH($D$30,INDEX(LPCV,0,1),-1))=INDEX(INDEX(LPCV,0,1),MIN(MATCH($D$30,INDEX(LPCV,0,1),-1)+1,11)),0,(INDEX(INDEX(LPCV,0,1),MATCH($D$30,INDEX(LPCV,0,1),-1))-$D$30)/(INDEX(INDEX(LPCV,0,1),MATCH($D$30,INDEX(LPCV,0,1),-1))-INDEX(INDEX(LPCV,0,1),MIN(MATCH($D$30,INDEX(LPCV,0,1),-1)+1,11))))
B44: 3. MOMENTOS (franja central, por metro de ancho)
B45: Ma− borde continuo = Ca·wu·A² | C45: Ma− | D45: =$D$37*$D$35*$D$25^2 | E45: t·m/m | F45: 0 = no hay borde largo continuo
B46: Mb− borde continuo = Cb·wu·B² | C46: Mb− | D46: =$D$38*$D$35*$D$26^2 | E46: t·m/m | F46: 0 = no hay borde corto continuo
B47: Ma+ = (CaD·wud + CaL·wul)·A² | C47: Ma+ | D47: =($D$39*$D$33+$D$41*$D$34)*$D$25^2 | E47: t·m/m
B48: Mb+ = (CbD·wud + CbL·wul)·B² | C48: Mb+ | D48: =($D$40*$D$33+$D$42*$D$34)*$D$26^2 | E48: t·m/m
B49: Ma− borde largo discontinuo = Ma+/3 | D49: =IF(OR($D$29=1,$D$29=3,$D$29=4,$D$29=6,$D$29=7,$D$29=8),$D$47/3,0) | E49: t·m/m | F49: 13.7.3.5 · 0 = no hay borde largo discontinuo
B50: Mb− borde corto discontinuo = Mb+/3 | D50: =IF(OR($D$29=1,$D$29=4,$D$29=5,$D$29=6,$D$29=7,$D$29=9),$D$48/3,0) | E50: t·m/m | F50: 0 = no hay borde corto discontinuo
B52: 4. ACERO DE REFUERZO (b = 100 cm)
B53: Diámetro de la varilla | C53: db | D53: =INDEX(BAR_DB,MATCH($D$21,BAR_NOM,0)) | E53: cm
B54: Área de la varilla | C54: Ab | D54: =INDEX(BAR_AS,MATCH($D$21,BAR_NOM,0)) | E54: cm²
B55: Peralte efectivo dirección corta (capa exterior) | C55: dA | D55: =$D$16-$D$22-$D$53/2 | E55: cm
B56: Peralte efectivo dirección larga (capa interior) | C56: dB | D56: =$D$55-$D$53 | E56: cm
B57: As mínimo 0.0018·b·h | C57: Asmín | D57: =0.0018*100*$D$16 | E57: cm²/m | F57: 9.7.2 / 10.5.4
B58: Dirección corta · negativo continuo: As | C58: As | D58: =MAX($D$57*IF($D$45=0,0,1),0.85*$D$11*100*$D$55/$D$12*(1-SQRT(MAX(0,1-2*$D$45*100000/(0.9*0.85*$D$11*100*$D$55^2))))) | E58: cm²/m
B59: Dirección corta · negativo continuo: espaciamiento | C59: s | D59: =IF($D$58=0,0,MIN(FLOOR($D$54*100/$D$58,2.5),3*$D$16,40)) | E59: cm | F59: s ≤ 3h y 40 cm
B60: Dirección corta · negativo continuo: ARMADURA | D60: =IF($D$58=0,"—","Ø "&$D$21&" @ "&FIXED($D$59/100,IF(MOD(ROUND($D$59*10,0),50)=0,2,3))&" m")
B61: Dirección corta · negativo discontinuo: As | C61: As | D61: =MAX($D$57*IF($D$49=0,0,1),0.85*$D$11*100*$D$55/$D$12*(1-SQRT(MAX(0,1-2*$D$49*100000/(0.9*0.85*$D$11*100*$D$55^2))))) | E61: cm²/m
B62: Dirección corta · negativo discontinuo: espaciamiento | C62: s | D62: =IF($D$61=0,0,MIN(FLOOR($D$54*100/$D$61,2.5),3*$D$16,40)) | E62: cm | F62: s ≤ 3h y 40 cm
B63: Dirección corta · negativo discontinuo: ARMADURA | D63: =IF($D$61=0,"—","Ø "&$D$21&" @ "&FIXED($D$62/100,IF(MOD(ROUND($D$62*10,0),50)=0,2,3))&" m")
B64: Dirección corta · positivo: As | C64: As | D64: =MAX($D$57*IF($D$47=0,0,1),0.85*$D$11*100*$D$55/$D$12*(1-SQRT(MAX(0,1-2*$D$47*100000/(0.9*0.85*$D$11*100*$D$55^2))))) | E64: cm²/m
B65: Dirección corta · positivo: espaciamiento | C65: s | D65: =IF($D$64=0,0,MIN(FLOOR($D$54*100/$D$64,2.5),3*$D$16,40)) | E65: cm | F65: s ≤ 3h y 40 cm
B66: Dirección corta · positivo: ARMADURA | D66: =IF($D$64=0,"—","Ø "&$D$21&" @ "&FIXED($D$65/100,IF(MOD(ROUND($D$65*10,0),50)=0,2,3))&" m")
B67: Dirección larga · negativo continuo: As | C67: As | D67: =MAX($D$57*IF($D$46=0,0,1),0.85*$D$11*100*$D$56/$D$12*(1-SQRT(MAX(0,1-2*$D$46*100000/(0.9*0.85*$D$11*100*$D$56^2))))) | E67: cm²/m
B68: Dirección larga · negativo continuo: espaciamiento | C68: s | D68: =IF($D$67=0,0,MIN(FLOOR($D$54*100/$D$67,2.5),3*$D$16,40)) | E68: cm | F68: s ≤ 3h y 40 cm
B69: Dirección larga · negativo continuo: ARMADURA | D69: =IF($D$67=0,"—","Ø "&$D$21&" @ "&FIXED($D$68/100,IF(MOD(ROUND($D$68*10,0),50)=0,2,3))&" m")
B70: Dirección larga · negativo discontinuo: As | C70: As | D70: =MAX($D$57*IF($D$50=0,0,1),0.85*$D$11*100*$D$56/$D$12*(1-SQRT(MAX(0,1-2*$D$50*100000/(0.9*0.85*$D$11*100*$D$56^2))))) | E70: cm²/m
B71: Dirección larga · negativo discontinuo: espaciamiento | C71: s | D71: =IF($D$70=0,0,MIN(FLOOR($D$54*100/$D$70,2.5),3*$D$16,40)) | E71: cm | F71: s ≤ 3h y 40 cm
B72: Dirección larga · negativo discontinuo: ARMADURA | D72: =IF($D$70=0,"—","Ø "&$D$21&" @ "&FIXED($D$71/100,IF(MOD(ROUND($D$71*10,0),50)=0,2,3))&" m")
B73: Dirección larga · positivo: As | C73: As | D73: =MAX($D$57*IF($D$48=0,0,1),0.85*$D$11*100*$D$56/$D$12*(1-SQRT(MAX(0,1-2*$D$48*100000/(0.9*0.85*$D$11*100*$D$56^2))))) | E73: cm²/m
B74: Dirección larga · positivo: espaciamiento | C74: s | D74: =IF($D$73=0,0,MIN(FLOOR($D$54*100/$D$73,2.5),3*$D$16,40)) | E74: cm | F74: s ≤ 3h y 40 cm
B75: Dirección larga · positivo: ARMADURA | D75: =IF($D$73=0,"—","Ø "&$D$21&" @ "&FIXED($D$74/100,IF(MOD(ROUND($D$74*10,0),50)=0,2,3))&" m")
B76: Secciones suficientes a flexión | C76: =IF(AND(1-2*$D$45*100000/(0.9*0.85*$D$11*100*$D$55^2)>=0,1-2*$D$47*100000/(0.9*0.85*$D$11*100*$D$55^2)>=0,1-2*$D$46*100000/(0.9*0.85*$D$11*100*$D$56^2)>=0,1-2*$D$48*100000/(0.9*0.85*$D$11*100*$D$56^2)>=0),"CUMPLE","NO CUMPLE") | F76: Si no cumple: aumente h
B78: 5. CORTANTE Y CARGA A LAS VIGAS (13.7.4)
B79: Factor 1.15 (borde continuo opuesto a discontinuo) | D79: =IF(OR($D$29=4,$D$29=6,$D$29=8),1.15,1)
B80: Vu = wu·(A/2 − d)·(1 − 0.5m) | C80: Vu | D80: =$D$79*$D$35*($D$25/2-$D$55/100)*(1-0.5*$D$27) | E80: t/m | F80: Ec. 13-10
B81: φVc = 0.85·0.53·√f'c·b·d | C81: φVc | D81: =0.85*0.53*SQRT($D$11)*100*$D$55/1000 | E81: t/m
B82: Vu ≤ φVc | C82: =IF($D$80<=$D$81,"CUMPLE","NO CUMPLE") | F82: Si no cumple: aumente h
B83: Carga a la viga del lado corto wu·A/3 | D83: =$D$35*$D$25/3 | E83: t/m | F83: Áreas tributarias a 45°
B84: Carga a la viga del lado largo wu·A/3·(3 − m²)/2 | D84: =$D$35*$D$25/3*(3-$D$27^2)/2 | E84: t/m
B86: 6. ESPESOR (E.060 9.6.3.3 con vigas rígidas)
B87: h mín = ln(0.8 + fy/14000)/(36 + 9β) | C87: hmín | D87: =MAX(9,$D$26*100*(0.8+$D$12/14000)/(36+9*$D$26/$D$25)) | E87: cm | F87: αfm > 2; ≥ 9 cm
B88: h ≥ h mín | C88: =IF($D$16>=$D$87,"CUMPLE","NO CUMPLE") | F88: Si no cumple: aumente h o verifique deflexiones
B89: Criterio práctico perímetro/180 | D89: =2*($D$25+$D$26)/180*100 | E89: cm
B91: 7. RESUMEN
B92: Dirección corta: positivo · negativo continuo · discontinuo | D92: =$D$66&" · "&$D$60&" · "&$D$63
B93: Dirección larga: positivo · negativo continuo · discontinuo | D93: =$D$75&" · "&$D$69&" · "&$D$72
B94: ESTADO GENERAL DEL DISEÑO | C94: =IF(AND($C$28="CUMPLE",$C$76="CUMPLE",$C$82="CUMPLE",$C$88="CUMPLE"),"CUMPLE","NO CUMPLE") | F94: Revise las líneas en rojo

Sheet ALIGERADO
B1: DISEÑO DE LOSA ALIGERADA EN UNA DIRECCIÓN · NTE E.060
B2: ALF_BIM · Plantilla Excel Estructuras · NTE E.060 Concreto Armado · v2.1.0
B3: Proyecto | C3: =INICIO!$D$7
B4: Ubicación | C4: =INICIO!$D$9
B5: Elemento | C5: Aligerado 1er piso, ejes A–F
B6: Calculista | C6: =INICIO!$D$10&IF(INICIO!$D$11="",""," · CIP "&INICIO!$D$11)
B7: Fecha | C7: =INICIO!$D$12
B10: 1. DATOS DE ENTRADA
B11: Resistencia del concreto | C11: f'c | D11: 210 | E11: kgf/cm²
B12: Fluencia del acero | C12: fy | D12: 4200 | E12: kgf/cm²
B13: Peralte del aligerado | C13: h | D13: 20 | E13: cm | F13: Viguetas 10 cm @ 40 cm, losa superior 5 cm
B14: Uso (sobrecarga de la E.020) | D14: Vivienda
B15: Sobrecarga manual (solo si eligió «Otro») | C15: s/c | D15: 0 | E15: kgf/m²
B16: Piso terminado / acabados | C16: pt | D16: 100 | E16: kgf/m² | F16: Usual 100 kgf/m²
B17: Tabiquería repartida | C17: tab | D17: 100 | E17: kgf/m² | F17: E.020: tabiquería móvil 50–150 kgf/m²
B18: Recubrimiento al centro de la varilla | C18: r | D18: 3 | E18: cm | F18: E.060 7.7.1: 2 cm libre + Ø/2 → d = h − 3 cm
B19: ¿Soporta tabiques susceptibles de dañarse por deflexiones? | D19: Sí | F19: Tabla 9.2: Sí → ℓ/480 · No → ℓ/240 (diferida + viva)
B20: Apoyos extremos | D20: Viga (monolítico) | F20: Define M(−) extremo y M(+) de los tramos extremos
B21: Número de tramos | C21: n | D21: 3 | F21: De 1 a 5
D23: Tramo 1 | E23: Tramo 2 | F23: Tramo 3 | G23: Tramo 4 | H23: Tramo 5
B24: Luz libre de cada tramo (m) | D24: 4 | E24: 4.2 | F24: 3.8 | G24: 4 | H24: 4
B25: Ingrese solo las luces de los tramos 1 a n; las demás se ignoran. Luz libre = distancia entre caras de apoyos.
B27: 2. METRADO DE CARGAS POR VIGUETA (ancho tributario 0.40 m)
B28: Peso propio del aligerado | C28: pp | D28: =INDEX(ALIG_PP,MATCH($D$13,ALIG_H,0)) | E28: kgf/m² | F28: E.020 Anexo 1
B29: Sobrecarga de uso | C29: s/c | D29: =IF($D$14="Otro (ingresar valor manual)",$D$15,INDEX(USO_SC,MATCH($D$14,USO_NOM,0))) | E29: kgf/m²
B30: Carga muerta por vigueta | C30: wD | D30: =($D$28+$D$16+$D$17)*0.4/1000 | E30: t/m
B31: Carga viva por vigueta | C31: wL | D31: =$D$29*0.4/1000 | E31: t/m
B32: Carga última wu = 1.4·wD + 1.7·wL | C32: wu | D32: =1.4*$D$30+1.7*$D$31 | E32: t/m | F32: E.060 9.2.1
B34: 3. VERIFICACIONES PREVIAS
B35: Luz libre mayor | C35: ln máx | D35: =MAX(IF($D$21>=1,$D$24,0),IF($D$21>=2,$E$24,0),IF($D$21>=3,$F$24,0),IF($D$21>=4,$G$24,0),IF($D$21>=5,$H$24,0)) | E35: m
B36: Peralte de referencia sin verificar deflexiones (Tabla 9.1) | C36: hmín | D36: =MAX(IF($D$21>=1,$D$24/IF($D$21=1,16,IF(OR(1=1,1=$D$21),18.5,21)),0),IF($D$21>=2,$E$24/IF($D$21=1,16,IF(OR(2=1,2=$D$21),18.5,21)),0),IF($D$21>=3,$F$24/IF($D$21=1,16,IF(OR(3=1,3=$D$21),18.5,21)),0),IF($D$21>=4,$G$24/IF($D$21=1,16,IF(OR(4=1,4=$D$21),18.5,21)),0),IF($D$21>=5,$H$24/IF($D$21=1,16,IF(OR(5=1,5=$D$21),18.5,21)),0))*100 | E36: cm | F36: E.060 9.6.2.1: ℓ/16 simple · ℓ/18.5 un extremo continuo · ℓ/21 ambos continuos
B37: h ≥ peralte de la Tabla 9.1 | C37: =IF($D$13>=$D$36,"CUMPLE","REVISAR") | F37: Si sale REVISAR: las deflexiones se calculan en la sección 8 (decide el estado general)
B38: Criterio práctico usual ln/25 (s/c ≤ 300 kgf/m²) | D38: =$D$35/25*100 | E38: cm | F38: Práctica peruana (E.060-1989). No figura en la E.060-2009
B39: Luces de los tramos 1 a n ingresadas (> 0) | C39: =IF(AND(OR($D$21<1,N($D$24)>0),OR($D$21<2,N($E$24)>0),OR($D$21<3,N($F$24)>0),OR($D$21<4,N($G$24)>0),OR($D$21<5,N($H$24)>0)),"CUMPLE","NO CUMPLE") | F39: Complete las luces que faltan
B40: Relación máxima entre luces adyacentes | D40: =MAX(IF($D$21>=2,MAX($D$24,$E$24)/MIN($D$24,$E$24),1),IF($D$21>=3,MAX($E$24,$F$24)/MIN($E$24,$F$24),1),IF($D$21>=4,MAX($F$24,$G$24)/MIN($F$24,$G$24),1),IF($D$21>=5,MAX($G$24,$H$24)/MIN($G$24,$H$24),1)) | F40: Método de coeficientes: ≤ 1.20 (E.060 8.3.3)
B41: Aplicabilidad del método de coeficientes | C41: =IF(OR($D$21=1,AND($D$40<=1.2,$D$31<=3*$D$30)),"CUMPLE","REVISAR") | F41: Luces ±20 % y CV ≤ 3CM (n = 1: viga simple wu·ln²/8). Si no: analice con SAP2000/ETABS
B42: Peralte efectivo | C42: d | D42: =$D$13-$D$18 | E42: cm
B43: β1 | C43: β1 | D43: =IF($D$11<=280,0.85,MAX(0.65,0.85-0.05*($D$11-280)/70))
B44: Cuantía balanceada | C44: ρb | D44: =0.85*$D$43*$D$11/$D$12*6000/(6000+$D$12)
B46: 4. ACERO MÍNIMO (E.060 10.5.1: φMn ≥ 1.2·Mcr) Y MÁXIMO (0.75·ρb)
B47: Centroide de la sección T desde arriba | C47: ȳ | D47: =(40*5*2.5+10*($D$13-5)*(5+($D$13-5)/2))/(40*5+10*($D$13-5)) | E47: cm | F47: bf = 40, hf = 5, bw = 10 cm
B48: Inercia bruta de la sección T | C48: Ig | D48: =40*5^3/12+40*5*($D$47-2.5)^2+10*($D$13-5)^3/12+10*($D$13-5)*(5+($D$13-5)/2-$D$47)^2 | E48: cm⁴
B49: Módulo de rotura fr = 2·√f'c | C49: fr | D49: =2*SQRT($D$11) | E49: kgf/cm² | F49: E.060 9.6.2.3
B50: Momento de agrietamiento positivo | C50: Mcr+ | D50: =$D$49*$D$48/($D$13-$D$47)/100000 | E50: t·m
B51: Momento de agrietamiento negativo | C51: Mcr− | D51: =$D$49*$D$48/$D$47/100000 | E51: t·m
B52: As mín positivo (b = 40 cm) | C52: As+mín | D52: =0.85*$D$11*40*$D$42/$D$12*(1-SQRT(MAX(0,1-2*1.2*$D$50*100000/(0.9*0.85*$D$11*40*$D$42^2)))) | E52: cm²
B53: As mín negativo (b = 10 cm) | C53: As−mín | D53: =0.85*$D$11*10*$D$42/$D$12*(1-SQRT(MAX(0,1-2*1.2*$D$51*100000/(0.9*0.85*$D$11*10*$D$42^2)))) | E53: cm²
B54: As máx negativo 0.75·ρb·bw·d | C54: As−máx | D54: =0.75*$D$44*10*$D$42 | E54: cm²
B55: Eje neutro balanceado cb = 6000·d/(6000 + fy) | C55: cb | D55: =6000*$D$42/(6000+$D$12) | E55: cm
B56: As máx positivo 0.75·Asb de la sección T | C56: As+máx | D56: =0.75*IF($D$43*$D$55<=5,0.85*$D$11*40*$D$43*$D$55,0.85*$D$11*(30*5+10*$D$43*$D$55))/$D$12 | E56: cm² | F56: Asb con bf = 40, hf = 5, bw = 10 cm
B58: 5. MOMENTOS NEGATIVOS EN LOS APOYOS (E.060 8.3.3)
B59: Concepto | C59: Apoyo 0 | D59: Apoyo 1 | E59: Apoyo 2 | F59: Apoyo 3 | G59: Apoyo 4 | H59: Apoyo 5
B60: Coeficiente | C60: =IF($D$21>=1,(IF($D$20="Viga (monolítico)",1/24,0)),"") | D60: =IF($D$21<1,"",IF($D$21=1,(IF($D$20="Viga (monolítico)",1/24,0)),IF($D$21=2,1/9,IF(OR(1=1,1=$D$21-1),1/10,1/11)))) | E60: =IF($D$21<2,"",IF($D$21=2,(IF($D$20="Viga (monolítico)",1/24,0)),IF($D$21=2,1/9,IF(OR(2=1,2=$D$21-1),1/10,1/11)))) | F60: =IF($D$21<3,"",IF($D$21=3,(IF($D$20="Viga (monolítico)",1/24,0)),IF($D$21=2,1/9,IF(OR(3=1,3=$D$21-1),1/10,1/11)))) | G60: =IF($D$21<4,"",IF($D$21=4,(IF($D$20="Viga (monolítico)",1/24,0)),IF($D$21=2,1/9,IF(OR(4=1,4=$D$21-1),1/10,1/11)))) | H60: =IF($D$21<5,"",IF($D$21=5,(IF($D$20="Viga (monolítico)",1/24,0)),IF($D$21=2,1/9,IF(OR(5=1,5=$D$21-1),1/10,1/11))))
B61: Coeficiente (fracción) | C61: =IF(C60="","",IF(C60=0,"0 (articulado)","1/"&ROUND(1/C60,0))) | D61: =IF(D60="","",IF(D60=0,"0 (articulado)","1/"&ROUND(1/D60,0))) | E61: =IF(E60="","",IF(E60=0,"0 (articulado)","1/"&ROUND(1/E60,0))) | F61: =IF(F60="","",IF(F60=0,"0 (articulado)","1/"&ROUND(1/F60,0))) | G61: =IF(G60="","",IF(G60=0,"0 (articulado)","1/"&ROUND(1/G60,0))) | H61: =IF(H60="","",IF(H60=0,"0 (articulado)","1/"&ROUND(1/H60,0)))
B62: Luz ln (promedio en apoyos interiores) (m) | C62: =$D$24 | D62: =IF($D$21<1,"",IF($D$21=1,$D$24,($D$24+$E$24)/2)) | E62: =IF($D$21<2,"",IF($D$21=2,$E$24,($E$24+$F$24)/2)) | F62: =IF($D$21<3,"",IF($D$21=3,$F$24,($F$24+$G$24)/2)) | G62: =IF($D$21<4,"",IF($D$21=4,$G$24,($G$24+$H$24)/2)) | H62: =IF($D$21=5,$H$24,"")
B63: Mu− = coef·wu·ln² (t·m) | C63: =IF(C60="","",C60*$D$32*C62^2) | D63: =IF(D60="","",D60*$D$32*D62^2) | E63: =IF(E60="","",E60*$D$32*E62^2) | F63: =IF(F60="","",F60*$D$32*F62^2) | G63: =IF(G60="","",G60*$D$32*G62^2) | H63: =IF(H60="","",H60*$D$32*H62^2)
B64: As requerido (b = 10 cm) (cm²) | C64: =IF(C63="","",0.85*$D$11*10*$D$42/$D$12*(1-SQRT(MAX(0,1-2*C63*100000/(0.9*0.85*$D$11*10*$D$42^2))))) | D64: =IF(D63="","",0.85*$D$11*10*$D$42/$D$12*(1-SQRT(MAX(0,1-2*D63*100000/(0.9*0.85*$D$11*10*$D$42^2))))) | E64: =IF(E63="","",0.85*$D$11*10*$D$42/$D$12*(1-SQRT(MAX(0,1-2*E63*100000/(0.9*0.85*$D$11*10*$D$42^2))))) | F64: =IF(F63="","",0.85*$D$11*10*$D$42/$D$12*(1-SQRT(MAX(0,1-2*F63*100000/(0.9*0.85*$D$11*10*$D$42^2))))) | G64: =IF(G63="","",0.85*$D$11*10*$D$42/$D$12*(1-SQRT(MAX(0,1-2*G63*100000/(0.9*0.85*$D$11*10*$D$42^2))))) | H64: =IF(H63="","",0.85*$D$11*10*$D$42/$D$12*(1-SQRT(MAX(0,1-2*H63*100000/(0.9*0.85*$D$11*10*$D$42^2)))))
B65: As de diseño = máx(As, As mín) (cm²) | C65: =IF(C64="","",IF(C63=0,0.71,MAX(C64,$D$53))) | D65: =IF(D64="","",IF(D63=0,0.71,MAX(D64,$D$53))) | E65: =IF(E64="","",IF(E63=0,0.71,MAX(E64,$D$53))) | F65: =IF(F64="","",IF(F63=0,0.71,MAX(F64,$D$53))) | G65: =IF(G64="","",IF(G63=0,0.71,MAX(G64,$D$53))) | H65: =IF(H64="","",IF(H63=0,0.71,MAX(H64,$D$53)))
B66: Bastón superior | C66: =IF(C65="","",IF(C65>MAX(COMB_AS),"Aumentar h",INDEX(COMB_NOM,SUMPRODUCT(--(COMB_AS<C65-0.0001))+1))) | D66: =IF(D65="","",IF(D65>MAX(COMB_AS),"Aumentar h",INDEX(COMB_NOM,SUMPRODUCT(--(COMB_AS<D65-0.0001))+1))) | E66: =IF(E65="","",IF(E65>MAX(COMB_AS),"Aumentar h",INDEX(COMB_NOM,SUMPRODUCT(--(COMB_AS<E65-0.0001))+1))) | F66: =IF(F65="","",IF(F65>MAX(COMB_AS),"Aumentar h",INDEX(COMB_NOM,SUMPRODUCT(--(COMB_AS<F65-0.0001))+1))) | G66: =IF(G65="","",IF(G65>MAX(COMB_AS),"Aumentar h",INDEX(COMB_NOM,SUMPRODUCT(--(COMB_AS<G65-0.0001))+1))) | H66: =IF(H65="","",IF(H65>MAX(COMB_AS),"Aumentar h",INDEX(COMB_NOM,SUMPRODUCT(--(COMB_AS<H65-0.0001))+1)))
B67: As colocado (cm²) | C67: =IF(OR(C65="",C66="Aumentar h"),"",INDEX(COMB_AS,MATCH(C66,COMB_NOM,0))) | D67: =IF(OR(D65="",D66="Aumentar h"),"",INDEX(COMB_AS,MATCH(D66,COMB_NOM,0))) | E67: =IF(OR(E65="",E66="Aumentar h"),"",INDEX(COMB_AS,MATCH(E66,COMB_NOM,0))) | F67: =IF(OR(F65="",F66="Aumentar h"),"",INDEX(COMB_AS,MATCH(F66,COMB_NOM,0))) | G67: =IF(OR(G65="",G66="Aumentar h"),"",INDEX(COMB_AS,MATCH(G66,COMB_NOM,0))) | H67: =IF(OR(H65="",H66="Aumentar h"),"",INDEX(COMB_AS,MATCH(H66,COMB_NOM,0)))
B68: Control (sección y As ≤ As máx) | C68: =IF(C63="","",IF(AND(1-2*C63*100000/(0.9*0.85*$D$11*10*$D$42^2)>=0,C65<=$D$54),"CUMPLE","NO CUMPLE: ensanche")) | D68: =IF(D63="","",IF(AND(1-2*D63*100000/(0.9*0.85*$D$11*10*$D$42^2)>=0,D65<=$D$54),"CUMPLE","NO CUMPLE: ensanche")) | E68: =IF(E63="","",IF(AND(1-2*E63*100000/(0.9*0.85*$D$11*10*$D$42^2)>=0,E65<=$D$54),"CUMPLE","NO CUMPLE: ensanche")) | F68: =IF(F63="","",IF(AND(1-2*F63*100000/(0.9*0.85*$D$11*10*$D$42^2)>=0,F65<=$D$54),"CUMPLE","NO CUMPLE: ensanche")) | G68: =IF(G63="","",IF(AND(1-2*G63*100000/(0.9*0.85*$D$11*10*$D$42^2)>=0,G65<=$D$54),"CUMPLE","NO CUMPLE: ensanche")) | H68: =IF(H63="","",IF(AND(1-2*H63*100000/(0.9*0.85*$D$11*10*$D$42^2)>=0,H65<=$D$54),"CUMPLE","NO CUMPLE: ensanche"))
B69: Apoyo extremo sobre muro de albañilería: M = 0; se coloca 1 Ø 3/8" de montaje (acero mínimo constructivo).
B71: 6. MOMENTOS POSITIVOS EN LOS TRAMOS (E.060 8.3.3)
B72: Concepto | D72: Tramo 1 | E72: Tramo 2 | F72: Tramo 3 | G72: Tramo 4 | H72: Tramo 5
B73: Coeficiente | D73: =IF($D$21<1,"",IF($D$21=1,1/8,IF(OR(1=1,1=$D$21),(IF($D$20="Viga (monolítico)",1/14,1/11)),1/16))) | E73: =IF($D$21<2,"",IF($D$21=1,1/8,IF(OR(2=1,2=$D$21),(IF($D$20="Viga (monolítico)",1/14,1/11)),1/16))) | F73: =IF($D$21<3,"",IF($D$21=1,1/8,IF(OR(3=1,3=$D$21),(IF($D$20="Viga (monolítico)",1/14,1/11)),1/16))) | G73: =IF($D$21<4,"",IF($D$21=1,1/8,IF(OR(4=1,4=$D$21),(IF($D$20="Viga (monolítico)",1/14,1/11)),1/16))) | H73: =IF($D$21<5,"",IF($D$21=1,1/8,IF(OR(5=1,5=$D$21),(IF($D$20="Viga (monolítico)",1/14,1/11)),1/16)))
B74: Coeficiente (fracción) | D74: =IF(D73="","","1/"&ROUND(1/D73,0)) | E74: =IF(E73="","","1/"&ROUND(1/E73,0)) | F74: =IF(F73="","","1/"&ROUND(1/F73,0)) | G74: =IF(G73="","","1/"&ROUND(1/G73,0)) | H74: =IF(H73="","","1/"&ROUND(1/H73,0))
B75: Mu+ = coef·wu·ln² (t·m) | D75: =IF(D73="","",D73*$D$32*$D$24^2) | E75: =IF(E73="","",E73*$D$32*$E$24^2) | F75: =IF(F73="","",F73*$D$32*$F$24^2) | G75: =IF(G73="","",G73*$D$32*$G$24^2) | H75: =IF(H73="","",H73*$D$32*$H$24^2)
B76: As requerido (b = 40 cm) (cm²) | D76: =IF(D75="","",0.85*$D$11*40*$D$42/$D$12*(1-SQRT(MAX(0,1-2*D75*100000/(0.9*0.85*$D$11*40*$D$42^2))))) | E76: =IF(E75="","",0.85*$D$11*40*$D$42/$D$12*(1-SQRT(MAX(0,1-2*E75*100000/(0.9*0.85*$D$11*40*$D$42^2))))) | F76: =IF(F75="","",0.85*$D$11*40*$D$42/$D$12*(1-SQRT(MAX(0,1-2*F75*100000/(0.9*0.85*$D$11*40*$D$42^2))))) | G76: =IF(G75="","",0.85*$D$11*40*$D$42/$D$12*(1-SQRT(MAX(0,1-2*G75*100000/(0.9*0.85*$D$11*40*$D$42^2))))) | H76: =IF(H75="","",0.85*$D$11*40*$D$42/$D$12*(1-SQRT(MAX(0,1-2*H75*100000/(0.9*0.85*$D$11*40*$D$42^2)))))
B77: Profundidad del bloque a (cm) | D77: =IF(D76="","",D76*$D$12/(0.85*$D$11*40)) | E77: =IF(E76="","",E76*$D$12/(0.85*$D$11*40)) | F77: =IF(F76="","",F76*$D$12/(0.85*$D$11*40)) | G77: =IF(G76="","",G76*$D$12/(0.85*$D$11*40)) | H77: =IF(H76="","",H76*$D$12/(0.85*$D$11*40))
B78: As de diseño = máx(As, As mín) (cm²) | D78: =IF(D76="","",MAX(D76,$D$52)) | E78: =IF(E76="","",MAX(E76,$D$52)) | F78: =IF(F76="","",MAX(F76,$D$52)) | G78: =IF(G76="","",MAX(G76,$D$52)) | H78: =IF(H76="","",MAX(H76,$D$52))
B79: Acero inferior | D79: =IF(D78="","",IF(D78>MAX(COMB_AS),"Aumentar h",INDEX(COMB_NOM,SUMPRODUCT(--(COMB_AS<D78-0.0001))+1))) | E79: =IF(E78="","",IF(E78>MAX(COMB_AS),"Aumentar h",INDEX(COMB_NOM,SUMPRODUCT(--(COMB_AS<E78-0.0001))+1))) | F79: =IF(F78="","",IF(F78>MAX(COMB_AS),"Aumentar h",INDEX(COMB_NOM,SUMPRODUCT(--(COMB_AS<F78-0.0001))+1))) | G79: =IF(G78="","",IF(G78>MAX(COMB_AS),"Aumentar h",INDEX(COMB_NOM,SUMPRODUCT(--(COMB_AS<G78-0.0001))+1))) | H79: =IF(H78="","",IF(H78>MAX(COMB_AS),"Aumentar h",INDEX(COMB_NOM,SUMPRODUCT(--(COMB_AS<H78-0.0001))+1)))
B80: As colocado (cm²) | D80: =IF(OR(D78="",D79="Aumentar h"),"",INDEX(COMB_AS,MATCH(D79,COMB_NOM,0))) | E80: =IF(OR(E78="",E79="Aumentar h"),"",INDEX(COMB_AS,MATCH(E79,COMB_NOM,0))) | F80: =IF(OR(F78="",F79="Aumentar h"),"",INDEX(COMB_AS,MATCH(F79,COMB_NOM,0))) | G80: =IF(OR(G78="",G79="Aumentar h"),"",INDEX(COMB_AS,MATCH(G79,COMB_NOM,0))) | H80: =IF(OR(H78="",H79="Aumentar h"),"",INDEX(COMB_AS,MATCH(H79,COMB_NOM,0)))
B81: Control (a ≤ hf = 5 cm y As ≤ As máx) | D81: =IF(D75="","",IF(AND(D77<=5,D78<=$D$56),"CUMPLE","REVISAR: viga T")) | E81: =IF(E75="","",IF(AND(E77<=5,E78<=$D$56),"CUMPLE","REVISAR: viga T")) | F81: =IF(F75="","",IF(AND(F77<=5,F78<=$D$56),"CUMPLE","REVISAR: viga T")) | G81: =IF(G75="","",IF(AND(G77<=5,G78<=$D$56),"CUMPLE","REVISAR: viga T")) | H81: =IF(H75="","",IF(AND(H77<=5,H78<=$D$56),"CUMPLE","REVISAR: viga T"))
B83: 7. VERIFICACIÓN POR CORTANTE EN LAS VIGUETAS (E.060 8.11.8 y 11.3)
B84: φVc = 0.85·1.1·0.53·√f'c·bw·d (10 % adicional en viguetas) | C84: φVc | D84: =0.85*1.1*0.53*SQRT($D$11)*10*$D$42/1000 | E84: t
B85: Concepto | D85: Tramo 1 | E85: Tramo 2 | F85: Tramo 3 | G85: Tramo 4 | H85: Tramo 5
B86: Vu en la cara (1.15 en el primer apoyo interior) (t) | D86: =IF($D$21<1,"",$D$32*$D$24/2*IF(AND($D$21>=2,OR(1=1,1=$D$21)),1.15,1)) | E86: =IF($D$21<2,"",$D$32*$E$24/2*IF(AND($D$21>=2,OR(2=1,2=$D$21)),1.15,1)) | F86: =IF($D$21<3,"",$D$32*$F$24/2*IF(AND($D$21>=2,OR(3=1,3=$D$21)),1.15,1)) | G86: =IF($D$21<4,"",$D$32*$G$24/2*IF(AND($D$21>=2,OR(4=1,4=$D$21)),1.15,1)) | H86: =IF($D$21<5,"",$D$32*$H$24/2*IF(AND($D$21>=2,OR(5=1,5=$D$21)),1.15,1))
B87: Vu a «d» de la cara (t) | D87: =IF(D86="","",D86-$D$32*$D$42/100) | E87: =IF(E86="","",E86-$D$32*$D$42/100) | F87: =IF(F86="","",F86-$D$32*$D$42/100) | G87: =IF(G86="","",G86-$D$32*$D$42/100) | H87: =IF(H86="","",H86-$D$32*$D$42/100)
B88: Control Vu ≤ φVc | D88: =IF(D87="","",IF(D87<=$D$84,"CUMPLE","NO CUMPLE: ensanche")) | E88: =IF(E87="","",IF(E87<=$D$84,"CUMPLE","NO CUMPLE: ensanche")) | F88: =IF(F87="","",IF(F87<=$D$84,"CUMPLE","NO CUMPLE: ensanche")) | G88: =IF(G87="","",IF(G87<=$D$84,"CUMPLE","NO CUMPLE: ensanche")) | H88: =IF(H87="","",IF(H87<=$D$84,"CUMPLE","NO CUMPLE: ensanche"))
B89: Si no cumple: ensanche alternado o corrido de viguetas en la zona del apoyo (retirando ladrillos) o aumente h.
B91: 8. DEFLEXIONES EN SERVICIO (E.060 9.6.2, Tabla 9.2)
B92: Δ = 5·ln²/(48·Ec·Ie)·[Mm − 0.1(M1 + M2)] con Ie de Branson (9.6.2.4). Diferida: λ = 2 (5 años, ρ' = 0). Límites (Tabla 9.2): ΔL ≤ ℓ/360 y λ·ΔD + ΔL ≤ ℓ/480 (con tabiques frágiles) o ℓ/240.
B93: Módulo del concreto Ec = 15000·√f'c | C93: Ec | D93: =15000*SQRT($D$11) | E93: kgf/cm² | F93: E.060 8.5
B94: Relación modular n = Es/Ec | C94: n | D94: =2000000/$D$93
B95: Carga de servicio por vigueta wD + wL | C95: ws | D95: =$D$30+$D$31 | E95: t/m
B96: Concepto | D96: Tramo 1 | E96: Tramo 2 | F96: Tramo 3 | G96: Tramo 4 | H96: Tramo 5
B97: Mm servicio al centro (t·m) | D97: =IF(D73="","",D73*$D$95*$D$24^2) | E97: =IF(E73="","",E73*$D$95*$E$24^2) | F97: =IF(F73="","",F73*$D$95*$F$24^2) | G97: =IF(G73="","",G73*$D$95*$G$24^2) | H97: =IF(H73="","",H73*$D$95*$H$24^2)
B98: M1 + M2 servicio en apoyos (t·m) | D98: =IF(D73="","",IF($D$21=1,0,C60*$D$95*C62^2+D60*$D$95*D62^2)) | E98: =IF(E73="","",IF($D$21=1,0,D60*$D$95*D62^2+E60*$D$95*E62^2)) | F98: =IF(F73="","",IF($D$21=1,0,E60*$D$95*E62^2+F60*$D$95*F62^2)) | G98: =IF(G73="","",IF($D$21=1,0,F60*$D$95*F62^2+G60*$D$95*G62^2)) | H98: =IF(H73="","",IF($D$21=1,0,G60*$D$95*G62^2+H60*$D$95*H62^2))
B99: Eje neutro fisurado kd (cm) | D99: =IF(D80="","",(-$D$94*D80+SQRT(($D$94*D80)^2+2*40*$D$94*D80*$D$42))/40) | E99: =IF(E80="","",(-$D$94*E80+SQRT(($D$94*E80)^2+2*40*$D$94*E80*$D$42))/40) | F99: =IF(F80="","",(-$D$94*F80+SQRT(($D$94*F80)^2+2*40*$D$94*F80*$D$42))/40) | G99: =IF(G80="","",(-$D$94*G80+SQRT(($D$94*G80)^2+2*40*$D$94*G80*$D$42))/40) | H99: =IF(H80="","",(-$D$94*H80+SQRT(($D$94*H80)^2+2*40*$D$94*H80*$D$42))/40)
B100: Icr = b·kd³/3 + n·As·(d − kd)² (cm⁴) | D100: =IF(D99="","",40*D99^3/3+$D$94*D80*($D$42-D99)^2) | E100: =IF(E99="","",40*E99^3/3+$D$94*E80*($D$42-E99)^2) | F100: =IF(F99="","",40*F99^3/3+$D$94*F80*($D$42-F99)^2) | G100: =IF(G99="","",40*G99^3/3+$D$94*G80*($D$42-G99)^2) | H100: =IF(H99="","",40*H99^3/3+$D$94*H80*($D$42-H99)^2)
B101: Ie (Branson) (cm⁴) | D101: =IF(D97="","",IF(D97<=$D$50,$D$48,MIN($D$48,($D$50/D97)^3*$D$48+(1-($D$50/D97)^3)*D100))) | E101: =IF(E97="","",IF(E97<=$D$50,$D$48,MIN($D$48,($D$50/E97)^3*$D$48+(1-($D$50/E97)^3)*E100))) | F101: =IF(F97="","",IF(F97<=$D$50,$D$48,MIN($D$48,($D$50/F97)^3*$D$48+(1-($D$50/F97)^3)*F100))) | G101: =IF(G97="","",IF(G97<=$D$50,$D$48,MIN($D$48,($D$50/G97)^3*$D$48+(1-($D$50/G97)^3)*G100))) | H101: =IF(H97="","",IF(H97<=$D$50,$D$48,MIN($D$48,($D$50/H97)^3*$D$48+(1-($D$50/H97)^3)*H100)))
B102: Δ inmediata CM + CV (cm) | D102: =IF(D97="","",MAX(0,5*($D$24*100)^2/(48*$D$93*D101)*(D97-0.1*D98)*100000)) | E102: =IF(E97="","",MAX(0,5*($E$24*100)^2/(48*$D$93*E101)*(E97-0.1*E98)*100000)) | F102: =IF(F97="","",MAX(0,5*($F$24*100)^2/(48*$D$93*F101)*(F97-0.1*F98)*100000)) | G102: =IF(G97="","",MAX(0,5*($G$24*100)^2/(48*$D$93*G101)*(G97-0.1*G98)*100000)) | H102: =IF(H97="","",MAX(0,5*($H$24*100)^2/(48*$D$93*H101)*(H97-0.1*H98)*100000))
B103: Ie solo con CM (cm⁴) | D103: =IF(D97="","",IF(D97*$D$30/$D$95<=$D$50,$D$48,MIN($D$48,($D$50/(D97*$D$30/$D$95))^3*$D$48+(1-($D$50/(D97*$D$30/$D$95))^3)*D100))) | E103: =IF(E97="","",IF(E97*$D$30/$D$95<=$D$50,$D$48,MIN($D$48,($D$50/(E97*$D$30/$D$95))^3*$D$48+(1-($D$50/(E97*$D$30/$D$95))^3)*E100))) | F103: =IF(F97="","",IF(F97*$D$30/$D$95<=$D$50,$D$48,MIN($D$48,($D$50/(F97*$D$30/$D$95))^3*$D$48+(1-($D$50/(F97*$D$30/$D$95))^3)*F100))) | G103: =IF(G97="","",IF(G97*$D$30/$D$95<=$D$50,$D$48,MIN($D$48,($D$50/(G97*$D$30/$D$95))^3*$D$48+(1-($D$50/(G97*$D$30/$D$95))^3)*G100))) | H103: =IF(H97="","",IF(H97*$D$30/$D$95<=$D$50,$D$48,MIN($D$48,($D$50/(H97*$D$30/$D$95))^3*$D$48+(1-($D$50/(H97*$D$30/$D$95))^3)*H100)))
B104: ΔD inmediata por CM (cm) | D104: =IF(D97="","",MAX(0,5*($D$24*100)^2/(48*$D$93*D103)*(D97-0.1*D98)*$D$30/$D$95*100000)) | E104: =IF(E97="","",MAX(0,5*($E$24*100)^2/(48*$D$93*E103)*(E97-0.1*E98)*$D$30/$D$95*100000)) | F104: =IF(F97="","",MAX(0,5*($F$24*100)^2/(48*$D$93*F103)*(F97-0.1*F98)*$D$30/$D$95*100000)) | G104: =IF(G97="","",MAX(0,5*($G$24*100)^2/(48*$D$93*G103)*(G97-0.1*G98)*$D$30/$D$95*100000)) | H104: =IF(H97="","",MAX(0,5*($H$24*100)^2/(48*$D$93*H103)*(H97-0.1*H98)*$D$30/$D$95*100000))
B105: ΔL = Δ(CM+CV) − ΔCM (cm) | D105: =IF(D102="","",MAX(0,D102-D104)) | E105: =IF(E102="","",MAX(0,E102-E104)) | F105: =IF(F102="","",MAX(0,F102-F104)) | G105: =IF(G102="","",MAX(0,G102-G104)) | H105: =IF(H102="","",MAX(0,H102-H104))
B106: 2·ΔD + ΔL (cm) | D106: =IF(D102="","",2*D104+D105) | E106: =IF(E102="","",2*E104+E105) | F106: =IF(F102="","",2*F104+F105) | G106: =IF(G102="","",2*G104+G105) | H106: =IF(H102="","",2*H104+H105)
B107: Control ΔL ≤ ℓ/360 y 2ΔD + ΔL ≤ ℓ/480 (o ℓ/240) | D107: =IF(D102="","",IF(AND(D105<=$D$24*100/360,D106<=$D$24*100/IF($D$19="Sí",480,240)),"CUMPLE","NO CUMPLE: aumente h")) | E107: =IF(E102="","",IF(AND(E105<=$E$24*100/360,E106<=$E$24*100/IF($D$19="Sí",480,240)),"CUMPLE","NO CUMPLE: aumente h")) | F107: =IF(F102="","",IF(AND(F105<=$F$24*100/360,F106<=$F$24*100/IF($D$19="Sí",480,240)),"CUMPLE","NO CUMPLE: aumente h")) | G107: =IF(G102="","",IF(AND(G105<=$G$24*100/360,G106<=$G$24*100/IF($D$19="Sí",480,240)),"CUMPLE","NO CUMPLE: aumente h")) | H107: =IF(H102="","",IF(AND(H105<=$H$24*100/360,H106<=$H$24*100/IF($D$19="Sí",480,240)),"CUMPLE","NO CUMPLE: aumente h"))
B109: 9. ACERO DE TEMPERATURA EN LA LOSA SUPERIOR (E.060 9.7)
B110: As = 0.0018·b·hf (b = 100 cm, hf = 5 cm) | C110: Ast | D110: =0.0018*100*5 | E110: cm²/m
B111: Espaciamiento con Ø 1/4" | C111: s | D111: =MIN(FLOOR(0.32/$D$110*100,2.5),5*5,40) | E111: cm | F111: s ≤ 5·hf y 40 cm
...

Sheet ESCALERA
B1: DISEÑO DE ESCALERA DE UN TRAMO CON DESCANSO · NTE E.060
B2: ALF_BIM · Plantilla Excel Estructuras · NTE E.060 Concreto Armado · v2.1.0
B3: Proyecto | C3: =INICIO!$D$7
B4: Ubicación | C4: =INICIO!$D$9
B5: Elemento | C5: Escalera E-1, tramo 1 | H5: Croquis
B6: Calculista | C6: =INICIO!$D$10&IF(INICIO!$D$11="",""," · CIP "&INICIO!$D$11) | H6: =-$D$19/2 | I6: 0
B7: Fecha | C7: =INICIO!$D$12 | H7: =MIN(0,$D$17-1)*$D$15/100 | I7: =MIN(0,$D$17)*$D$16/100
H8: =MIN(0,$D$17-1)*$D$15/100 | I8: =MIN(0+1,$D$17)*$D$16/100
H9: =MIN(1,$D$17-1)*$D$15/100 | I9: =MIN(1,$D$17)*$D$16/100
B10: 1. DATOS DE ENTRADA | H10: =MIN(1,$D$17-1)*$D$15/100 | I10: =MIN(1+1,$D$17)*$D$16/100
B11: Resistencia del concreto | C11: f'c | D11: 210 | E11: kgf/cm² | H11: =MIN(2,$D$17-1)*$D$15/100 | I11: =MIN(2,$D$17)*$D$16/100
B12: Fluencia del acero | C12: fy | D12: 4200 | E12: kgf/cm² | H12: =MIN(2,$D$17-1)*$D$15/100 | I12: =MIN(2+1,$D$17)*$D$16/100
B13: Peso unitario del concreto | C13: γc | D13: 2.4 | E13: t/m³ | H13: =MIN(3,$D$17-1)*$D$15/100 | I13: =MIN(3,$D$17)*$D$16/100
B14: Geometría | H14: =MIN(3,$D$17-1)*$D$15/100 | I14: =MIN(3+1,$D$17)*$D$16/100
B15: Paso | C15: P | D15: 25 | E15: cm | F15: A.010: P ≥ 25 cm | H15: =MIN(4,$D$17-1)*$D$15/100 | I15: =MIN(4,$D$17)*$D$16/100
B16: Contrapaso | C16: CP | D16: 17.5 | E16: cm | F16: A.010: CP ≤ 18 cm | H16: =MIN(4,$D$17-1)*$D$15/100 | I16: =MIN(4+1,$D$17)*$D$16/100
B17: Número de contrapasos del tramo | C17: n | D17: 8 | H17: =MIN(5,$D$17-1)*$D$15/100 | I17: =MIN(5,$D$17)*$D$16/100
B18: Longitud del descanso | C18: Ld | D18: 1.2 | E18: m | H18: =MIN(5,$D$17-1)*$D$15/100 | I18: =MIN(5+1,$D$17)*$D$16/100
B19: Ancho de los apoyos (vigas o muros) | C19: a | D19: 0.25 | E19: m | F19: La luz de cálculo va de eje a eje de apoyos | H19: =MIN(6,$D$17-1)*$D$15/100 | I19: =MIN(6,$D$17)*$D$16/100
B20: Ancho de la escalera | C20: B | D20: 1.2 | E20: m | F20: Vivienda ≥ 0.90 m (A.010) | H20: =MIN(6,$D$17-1)*$D$15/100 | I20: =MIN(6+1,$D$17)*$D$16/100
B21: Espesor de la garganta | C21: t | D21: 15 | E21: cm | F21: Predimensionamiento: ln/25 a ln/20 | H21: =MIN(7,$D$17-1)*$D$15/100 | I21: =MIN(7,$D$17)*$D$16/100
B22: Espesor del descanso | C22: td | D22: 15 | E22: cm | H22: =MIN(7,$D$17-1)*$D$15/100 | I22: =MIN(7+1,$D$17)*$D$16/100
B23: Recubrimiento libre | C23: r | D23: 2 | E23: cm | F23: E.060 7.7.1: losas no expuestas 2 cm | H23: =MIN(8,$D$17-1)*$D$15/100 | I23: =MIN(8,$D$17)*$D$16/100
B24: Cargas | H24: =MIN(8,$D$17-1)*$D$15/100 | I24: =MIN(8+1,$D$17)*$D$16/100
B25: Acabados | C25: pt | D25: 0.1 | E25: t/m² | H25: =MIN(9,$D$17-1)*$D$15/100 | I25: =MIN(9,$D$17)*$D$16/100
B26: Sobrecarga | C26: s/c | D26: 0.2 | E26: t/m² | F26: E.020: vivienda 0.20; oficinas, colegios, hospitales 0.40 t/m² | H26: =MIN(9,$D$17-1)*$D$15/100 | I26: =MIN(9+1,$D$17)*$D$16/100
B27: Varilla longitudinal | C27: Ø | D27: 1/2" | H27: =MIN(10,$D$17-1)*$D$15/100 | I27: =MIN(10,$D$17)*$D$16/100
B28: Varilla transversal | C28: Øt | D28: 3/8" | H28: =MIN(10,$D$17-1)*$D$15/100 | I28: =MIN(10+1,$D$17)*$D$16/100
B29: Fracción del momento máximo para el acero negativo | C29: k− | D29: 0.5 | F29: Apoyos poco rígidos: 1/3 a 1/2 de M+ (criterio usual) | H29: =MIN(11,$D$17-1)*$D$15/100 | I29: =MIN(11,$D$17)*$D$16/100
H30: =MIN(11,$D$17-1)*$D$15/100 | I30: =MIN(11+1,$D$17)*$D$16/100
B31: 2. GEOMETRÍA Y PREDIMENSIONAMIENTO (RNE A.010) | H31: =MIN(12,$D$17-1)*$D$15/100 | I31: =MIN(12,$D$17)*$D$16/100
B32: 2·CP + P | D32: =2*$D$16+$D$15 | E32: cm | F32: Debe estar entre 60 y 64 cm | H32: =MIN(12,$D$17-1)*$D$15/100 | I32: =MIN(12+1,$D$17)*$D$16/100
B33: 60 ≤ 2CP + P ≤ 64 cm | C33: =IF(AND($D$32>=60,$D$32<=64),"CUMPLE","NO CUMPLE") | F33: Ajuste paso o contrapaso | H33: =MIN(13,$D$17-1)*$D$15/100 | I33: =MIN(13,$D$17)*$D$16/100
B34: P ≥ 25 cm y CP ≤ 18 cm | C34: =IF(AND($D$15>=25,$D$16<=18),"CUMPLE","NO CUMPLE") | H34: =MIN(13,$D$17-1)*$D$15/100 | I34: =MIN(13+1,$D$17)*$D$16/100
B35: Proyección horizontal del tramo inclinado (n − 1)·P | C35: L1 | D35: =($D$17-1)*$D$15/100 | E35: m | H35: =MIN(14,$D$17-1)*$D$15/100 | I35: =MIN(14,$D$17)*$D$16/100
B36: Altura que sube el tramo n·CP | C36: h | D36: =$D$17*$D$16/100 | E36: m | H36: =MIN(14,$D$17-1)*$D$15/100 | I36: =MIN(14+1,$D$17)*$D$16/100
B37: cos θ = P/√(P² + CP²) | C37: cos θ | D37: =$D$15/SQRT($D$15^2+$D$16^2) | H37: =MIN(15,$D$17-1)*$D$15/100 | I37: =MIN(15,$D$17)*$D$16/100
B38: Tramo inclinado de cálculo L1 + a/2 | C38: L1' | D38: =$D$35+$D$19/2 | E38: m | H38: =MIN(15,$D$17-1)*$D$15/100 | I38: =MIN(15+1,$D$17)*$D$16/100
B39: Descanso de cálculo Ld + a/2 | C39: L2' | D39: =$D$18+$D$19/2 | E39: m | H39: =MIN(16,$D$17-1)*$D$15/100 | I39: =MIN(16,$D$17)*$D$16/100
B40: Luz de cálculo (eje a eje) | C40: L | D40: =$D$38+$D$39 | E40: m | H40: =MIN(16,$D$17-1)*$D$15/100 | I40: =MIN(16+1,$D$17)*$D$16/100
B41: t mínimo = ln/25 | D41: =($D$35+$D$18)/25*100 | E41: cm | F41: ln = luz libre L1 + Ld | H41: =MIN(17,$D$17-1)*$D$15/100 | I41: =MIN(17,$D$17)*$D$16/100
B42: t máximo = ln/20 | D42: =($D$35+$D$18)/20*100 | E42: cm | H42: =MIN(17,$D$17-1)*$D$15/100 | I42: =MIN(17+1,$D$17)*$D$16/100
B43: ln/25 ≤ t (predimensionamiento) | C43: =IF($D$21>=$D$41-0.01,"CUMPLE","REVISAR") | F43: Si no cumple: aumente t | H43: =MIN(18,$D$17-1)*$D$15/100 | I43: =MIN(18,$D$17)*$D$16/100
H44: =MIN(18,$D$17-1)*$D$15/100 | I44: =MIN(18+1,$D$17)*$D$16/100
B45: 3. METRADO DE CARGAS (por m² en proyección horizontal) | H45: =MIN(19,$D$17-1)*$D$15/100 | I45: =MIN(19,$D$17)*$D$16/100
B46: Peso propio del tramo inclinado γc·(CP/2 + t/cos θ) | C46: wpp1 | D46: =$D$13*($D$16/200+$D$21/100/$D$37) | E46: t/m² | F46: w = γ·(CP/2 + t·√(1 + (CP/P)²)) | H46: =MIN(19,$D$17-1)*$D$15/100 | I46: =MIN(19+1,$D$17)*$D$16/100
B47: Peso propio del descanso γc·td | C47: wpp2 | D47: =$D$13*$D$22/100 | E47: t/m² | H47: =MIN(20,$D$17-1)*$D$15/100 | I47: =MIN(20,$D$17)*$D$16/100
B48: wu1 = [1.4·(wpp1 + pt) + 1.7·s/c]·B | C48: wu1 | D48: =(1.4*($D$46+$D$25)+1.7*$D$26)*$D$20 | E48: t/m | F48: E.060 9.2.1 | H48: =MIN(20,$D$17-1)*$D$15/100 | I48: =MIN(20+1,$D$17)*$D$16/100
B49: wu2 = [1.4·(wpp2 + pt) + 1.7·s/c]·B | C49: wu2 | D49: =(1.4*($D$47+$D$25)+1.7*$D$26)*$D$20 | E49: t/m | H49: =MIN(21,$D$17-1)*$D$15/100 | I49: =MIN(21,$D$17)*$D$16/100
H50: =MIN(21,$D$17-1)*$D$15/100 | I50: =MIN(21+1,$D$17)*$D$16/100
B51: 4. ANÁLISIS (viga simplemente apoyada en proyección horizontal) | H51: =MIN(22,$D$17-1)*$D$15/100 | I51: =MIN(22,$D$17)*$D$16/100
B52: Reacción en el apoyo del tramo inclinado | C52: RA | D52: =($D$48*$D$38*($D$40-$D$38/2)+$D$49*$D$39^2/2)/$D$40 | E52: t | H52: =MIN(22,$D$17-1)*$D$15/100 | I52: =MIN(22+1,$D$17)*$D$16/100
B53: Reacción en el apoyo del descanso | C53: RB | D53: =$D$48*$D$38+$D$49*$D$39-$D$52 | E53: t | H53: =MIN(23,$D$17-1)*$D$15/100 | I53: =MIN(23,$D$17)*$D$16/100
B54: Posición del cortante nulo desde A | C54: x0 | D54: =IF($D$52<=$D$48*$D$38,$D$52/$D$48,$D$38+($D$52-$D$48*$D$38)/$D$49) | E54: m | H54: =MIN(23,$D$17-1)*$D$15/100 | I54: =MIN(23+1,$D$17)*$D$16/100
B55: Momento máximo | C55: Mmáx | D55: =IF($D$54<=$D$38,$D$52^2/(2*$D$48),$D$52*$D$54-$D$48*$D$38*($D$54-$D$38/2)-$D$49*($D$54-$D$38)^2/2) | E55: t·m | H55: =MIN(24,$D$17-1)*$D$15/100 | I55: =MIN(24,$D$17)*$D$16/100
H56: =MIN(24,$D$17-1)*$D$15/100 | I56: =MIN(24+1,$D$17)*$D$16/100
B57: 5. DISEÑO POR FLEXIÓN (φ = 0.90) | H57: =$D$35+$D$18+$D$19/2 | I57: =$D$36
B58: Factor β1 | C58: β1 | D58: =IF($D$11<=280,0.85,MAX(0.65,0.85-0.05*($D$11-280)/70)) | F58: E.060 10.2.7.3
B59: Cuantía balanceada | C59: ρb | D59: =0.85*$D$58*$D$11/$D$12*6000/(6000+$D$12) | F59: Límite: ρ ≤ 0.75·ρb (E.060 10.3.4) | H59: =-$D$19/2 | I59: =0
B60: Diámetro de la varilla | C60: db | D60: =INDEX(BAR_DB,MATCH($D$27,BAR_NOM,0)) | E60: cm | H60: =-$D$19/2 | I60: =-$D$19/2*$D$16/$D$15-$D$21/100/$D$37
B61: Área de la varilla | C61: Ab | D61: =INDEX(BAR_AS,MATCH($D$27,BAR_NOM,0)) | E61: cm² | H61: =MIN($D$35+$D$18,($D$36-$D$22/100+$D$21/100/$D$37)*$D$15/$D$16) | I61: =$D$36-$D$22/100
B62: Peralte efectivo d = t − r − db/2 | C62: d | D62: =$D$21-$D$23-$D$60/2 | E62: cm | H62: =$D$35+$D$18+$D$19/2 | I62: =$D$36-$D$22/100
B63: Ancho de diseño | C63: b | D63: =$D$20*100 | E63: cm | H63: =$D$35+$D$18+$D$19/2 | I63: =$D$36
B64: Control de la sección (debe ser ≥ 0) | D64: =1-2*$D$55*100000/(0.9*0.85*$D$11*$D$63*$D$62^2)
B65: Sección suficiente a flexión | C65: =IF($D$64>=0,"CUMPLE","NO CUMPLE") | F65: Si no cumple: aumente t | H65: =-$D$19/2-0.2 | I65: =-0.6
B66: Acero positivo requerido | C66: As+ | D66: =0.85*$D$11*$D$63*$D$62/$D$12*(1-SQRT(MAX(0,1-2*$D$55*100000/(0.9*0.85*$D$11*$D$63*$D$62^2)))) | E66: cm² | H66: =-$D$19/2-0.2+MAX($D$40+0.6,$D$36+0.8) | I66: =-0.6+MAX($D$40+0.6,$D$36+0.8)
B67: Acero mínimo 0.0018·b·t | C67: Asmín | D67: =0.0018*$D$63*$D$21 | E67: cm² | F67: E.060 10.5.4 / 9.7.2
B68: Acero positivo de diseño | C68: As+ | D68: =MAX($D$66,$D$67) | E68: cm²
B69: As ≤ 0.75·ρb·b·d (falla dúctil) | C69: =IF($D$66<=0.75*$D$59*$D$63*$D$62,"CUMPLE","NO CUMPLE") | F69: Si no cumple: aumente t
B70: Espaciamiento | C70: s | D70: =MIN(FLOOR($D$61*$D$63/$D$68,2.5),3*$D$21,40) | E70: cm | F70: s ≤ 3t y 40 cm
B71: Espaciamiento libre ≥ máx(db, 2.5 cm) y s ≥ 10 cm | C71: =IF(AND($D$70-$D$60>=MAX($D$60,2.5),$D$70>=10),"CUMPLE","NO CUMPLE") | F71: Si no cumple: use varilla mayor
B72: ACERO LONGITUDINAL INFERIOR (+) | D72: ="Ø "&$D$27&" @ "&FIXED($D$70/100,IF(MOD(ROUND($D$70*10,0),50)=0,2,3))&" m"
B73: Momento negativo k−·Mmáx | C73: Mu− | D73: =$D$29*$D$55 | E73: t·m
B74: Acero negativo requerido | C74: As− | D74: =0.85*$D$11*$D$63*$D$62/$D$12*(1-SQRT(MAX(0,1-2*$D$73*100000/(0.9*0.85*$D$11*$D$63*$D$62^2)))) | E74: cm²
B75: Acero negativo de diseño | C75: As− | D75: =MAX($D$74,$D$67) | E75: cm²
B76: Espaciamiento | C76: s | D76: =MIN(FLOOR($D$61*$D$63/$D$75,2.5),3*$D$21,40) | E76: cm
B77: ACERO LONGITUDINAL SUPERIOR (−) en apoyos | D77: ="Ø "&$D$27&" @ "&FIXED($D$76/100,IF(MOD(ROUND($D$76*10,0),50)=0,2,3))&" m" | F77: Longitud ≈ ln/4 desde la cara del apoyo
B78: Área de la varilla transversal | C78: Ab | D78: =INDEX(BAR_AS,MATCH($D$28,BAR_NOM,0)) | E78: cm²
B79: Acero de temperatura 0.0018·100·t | C79: Ast | D79: =0.0018*100*$D$21 | E79: cm²/m
B80: Espaciamiento | C80: s | D80: =MIN(FLOOR($D$78/$D$79*100,2.5),3*$D$21,40) | E80: cm | F80: s ≤ 3t y 40 cm (E.060 9.7.3)
B81: ACERO TRANSVERSAL (temperatura) | D81: ="Ø "&$D$28&" @ "&FIXED($D$80/100,IF(MOD(ROUND($D$80*10,0),50)=0,2,3))&" m"
B83: 6. VERIFICACIÓN POR CORTANTE (E.060 11.3)
B84: Vu a «d» del apoyo A (perpendicular a la losa) | C84: VuA | D84: =($D$52-$D$48*$D$62/100)*$D$37 | E84: t | F84: Vu = (RA − wu1·d)·cos θ
B85: Vu a «d» del apoyo B (descanso) | C85: VuB | D85: =$D$53-$D$49*$D$62/100 | E85: t
B86: φVc = 0.85·0.53·√f'c·b·d | C86: φVc | D86: =0.85*0.53*SQRT($D$11)*$D$63*$D$62/1000 | E86: t
B87: máx(VuA, VuB) ≤ φVc | C87: =IF(MAX($D$84,$D$85)<=$D$86,"CUMPLE","NO CUMPLE") | F87: Si no cumple: aumente t
B89: 7. RESUMEN
B90: Geometría | D90: =$D$17&" contrapasos de "&FIXED($D$16,1)&" cm · pasos de "&FIXED($D$15,1)&" cm · t = "&FIXED($D$21,0)&" cm"
B91: Acero inferior (+) | D91: =$D$72
B92: Acero superior (−) | D92: =$D$77
B93: Acero transversal | D93: =$D$81
B94: ESTADO GENERAL DEL DISEÑO | C94: =IF(AND($C$33="CUMPLE",$C$34="CUMPLE",$C$65="CUMPLE",$C$69="CUMPLE",$C$71="CUMPLE",$C$87="CUMPLE"),"CUMPLE","NO CUMPLE") | F94: Revise las líneas en rojo
B96: 8. CROQUIS DEL TRAMO (se actualiza con los datos)

Sheet ZAPATA
B1: ZAPATA AISLADA CON MOMENTOS · NTE E.060
B2: ALF_BIM · Plantilla Excel Estructuras · NTE E.060 Concreto Armado · v2.1.0
B3: Proyecto | C3: =INICIO!$D$7
B4: Ubicación | C4: =INICIO!$D$9
B5: Elemento | C5: Zapata Z-1 (columna C-1, eje B-2)
B6: Calculista | C6: =INICIO!$D$10&IF(INICIO!$D$11="",""," · CIP "&INICIO!$D$11) | H6: Datos del croquis
B7: Fecha | C7: =INICIO!$D$12 | H7: =-$D$54/2 | I7: =-$D$55/2
H8: =$D$54/2 | I8: =-$D$55/2
H9: =$D$54/2 | I9: =$D$55/2
B10: 1. DATOS DE ENTRADA | H10: =-$D$54/2 | I10: =$D$55/2
B11: Materiales | H11: =-$D$54/2 | I11: =-$D$55/2
B12: Resistencia del concreto | C12: f'c | D12: 210 | E12: kgf/cm² | F12: Zapatas: f'c ≥ 210 kgf/cm² recomendado
B13: Fluencia del acero | C13: fy | D13: 4200 | E13: kgf/cm² | F13: Acero Grado 60 | H13: =-$D$15/200 | I13: =-$D$16/200
B14: Columna | H14: =$D$15/200 | I14: =-$D$16/200
B15: Dimensión de la columna en X | C15: cx | D15: 40 | E15: cm | H15: =$D$15/200 | I15: =$D$16/200
B16: Dimensión de la columna en Y | C16: cy | D16: 40 | E16: cm | H16: =-$D$15/200 | I16: =$D$16/200
B17: Varilla longitudinal de la columna | C17: Ø col | D17: 3/4" | F17: Para verificar el anclaje en compresión | H17: =-$D$15/200 | I17: =-$D$16/200
B18: Cargas de servicio en la base de la columna
B19: Carga muerta | C19: PD | D19: 60 | E19: t | H19: =-($D$15+$D$80)/200 | I19: =-($D$16+$D$80)/200
B20: Carga viva | C20: PL | D20: 25 | E20: t | H20: =($D$15+$D$80)/200 | I20: =-($D$16+$D$80)/200
B21: Carga axial de sismo (0 si no aplica) | C21: PS | D21: 0 | E21: t | F21: Verificación con 1.30·qadm y U = 1.25(CM+CV)+CS | H21: =($D$15+$D$80)/200 | I21: =($D$16+$D$80)/200
B22: Momentos de servicio en la base (Mx gira alrededor del eje X: varía la presión a lo largo de Y) | H22: =-($D$15+$D$80)/200 | I22: =($D$16+$D$80)/200
B23: Momento muerto Mx | C23: MDx | D23: 1 | E23: t·m | H23: =-($D$15+$D$80)/200 | I23: =-($D$16+$D$80)/200
B24: Momento vivo Mx | C24: MLx | D24: 0.5 | E24: t·m
B25: Momento de sismo Mx | C25: MSx | D25: 3 | E25: t·m | F25: 0 si no aplica | H25: =-MAX($D$54,$D$55)/2-0.1 | I25: =-MAX($D$54,$D$55)/2-0.1
B26: Momento muerto My | C26: MDy | D26: 0.5 | E26: t·m | H26: =-MAX($D$54,$D$55)/2-0.1+MAX($D$54,$D$55)+0.2 | I26: =-MAX($D$54,$D$55)/2-0.1+MAX($D$54,$D$55)+0.2
B27: Momento vivo My | C27: MLy | D27: 0.2 | E27: t·m
B28: Momento de sismo My | C28: MSy | D28: 2 | E28: t·m
B29: Suelo y cimentación
B30: Capacidad portante admisible | C30: qadm | D30: 2 | E30: kgf/cm² | F30: Del estudio de mecánica de suelos (EMS)
B31: Profundidad de desplante | C31: Df | D31: 1.5 | E31: m | F31: Del NPT o nivel de terreno al fondo de zapata
B32: Peso unitario promedio suelo + concreto | C32: γm | D32: 2 | E32: t/m³ | F32: Usual 2.0 t/m³
B33: Sobrecarga sobre el piso | C33: s/c | D33: 0.25 | E33: t/m² | F33: Piso terminado sobre la zapata
B34: Peralte de la zapata | C34: hz | D34: 60 | E34: cm | F34: Mínimo práctico 50–60 cm; se verifica abajo
B35: Recubrimiento inferior | C35: r | D35: 7.5 | E35: cm | F35: E.060 7.7.1: concreto vaciado contra el suelo ≥ 7 cm
B36: Varilla de la parrilla | C36: Ø | D36: 5/8"
B37: Lado X adoptado (vacío = usar el sugerido) | C37: Lx | E37: m | F37: Opcional: escriba su dimensión
B38: Lado Y adoptado (vacío = usar el sugerido) | C38: Ly | E38: m | F38: Opcional: escriba su dimensión
B40: 2. DIMENSIONES EN PLANTA (cargas de servicio)
B41: Capacidad neta del suelo | C41: qn | D41: =$D$30*10-$D$32*$D$31-$D$33 | E41: t/m² | F41: qn = qadm − γm·Df − s/c
B42: Capacidad neta positiva | C42: =IF($D$41>0,"CUMPLE","NO CUMPLE") | F42: Si no cumple: qadm insuficiente para ese Df
B43: Capacidad neta con sismo | C43: qns | D43: =1.3*$D$30*10-$D$32*$D$31-$D$33 | E43: t/m² | F43: 1.30·qadm para cargas de sismo
B44: Área requerida | C44: Areq | D44: =IF($D$41<=0,0.01,MAX(($D$19+$D$20)/$D$41,($D$19+$D$20+$D$21)/$D$43)) | E44: m² | F44: Mayor entre gravedad y gravedad + sismo
B45: Suma de momentos de gravedad |Mx| + |My| | C45: Mg | D45: =ABS($D$23+$D$24)+ABS($D$26+$D$27) | E45: t·m
B46: Suma de momentos con sismo | C46: Ms | D46: =ABS($D$23+$D$24)+ABS($D$25)+ABS($D$26+$D$27)+ABS($D$28) | E46: t·m
B47: Lado equivalente con momentos · iteración 1 | C47: S | D47: =MAX(SQRT(MAX(0,($D$19+$D$20+6*$D$45/(SQRT($D$44)))/$D$41)),SQRT(MAX(0,($D$19+$D$20+$D$21+6*$D$46/(SQRT($D$44)))/$D$43))) | E47: m | F47: S = √[(P + 6ΣM/S)/qn]
B48: Lado equivalente con momentos · iteración 2 | C48: S | D48: =MAX(SQRT(MAX(0,($D$19+$D$20+6*$D$45/($D$47))/$D$41)),SQRT(MAX(0,($D$19+$D$20+$D$21+6*$D$46/($D$47))/$D$43))) | E48: m
B49: Lado equivalente con momentos · iteración 3 | C49: S | D49: =MAX(SQRT(MAX(0,($D$19+$D$20+6*$D$45/($D$48))/$D$41)),SQRT(MAX(0,($D$19+$D$20+$D$21+6*$D$46/($D$48))/$D$43))) | E49: m
B50: Lado equivalente con momentos · iteración 4 | C50: S | D50: =MAX(SQRT(MAX(0,($D$19+$D$20+6*$D$45/($D$49))/$D$41)),SQRT(MAX(0,($D$19+$D$20+$D$21+6*$D$46/($D$49))/$D$43))) | E50: m
B51: Lado equivalente con momentos · iteración 5 | C51: S | D51: =MAX(SQRT(MAX(0,($D$19+$D$20+6*$D$45/($D$50))/$D$41)),SQRT(MAX(0,($D$19+$D$20+$D$21+6*$D$46/($D$50))/$D$43))) | E51: m
B52: Lado X sugerido (volados iguales) | C52: Lx | D52: =CEILING(IF($D$41<=0,1,$D$51)+($D$15-$D$16)/200,0.05) | E52: m | F52: Redondeado a 0.05 m
